Workbook

Sheet Pricing and operating assumptio
A1: Pricing and operating assumptions
A2: Wincheck | 12-month plan · Main Scenario
A4: Variable / dimension | B4: Value
A5: Team monthly price | B5: =199 -> 199
A6: Included fixes per team | B6: =10 -> 10
A7: Extra fix price | B7: =29 -> 29
A8: Pay per fix price | B8: =49 -> 49
A9: Cost per successful fix | B9: =1.5 -> 1.5
A10: Target gross margin | B10: =0.7 -> 0.7
A11: Monthly hosting | B11: =50 -> 50
A12: Monthly tools | B12: =100 -> 100
A13: Founder monthly pay | B13: =4000 -> 4000
A14: Founder pay start month | B14: =7 -> 7
A15: Contract engineer monthly cost | B15: =6000 -> 6000
A16: Earliest hire month | B16: =10 -> 10
A17: Free fixes per project | B17: =1 -> 1

Sheet Monthly operating and hiring fo
A1: Monthly operating and hiring forecast
A2: Wincheck | 12-month plan · Main Scenario
A4: Variable / dimension | B4: 2026-10 | C4: 2026-11 | D4: 2026-12 | E4: 2027-01 | F4: 2027-02 | G4: 2027-03 | H4: 2027-04 | I4: 2027-05 | J4: 2027-06 | K4: 2027-07 | L4: 2027-08 | M4: 2027-09
A5: Paying teams | B5: =0 -> 0 | C5: =1 -> 1 | D5: =2 -> 2 | E5: =3 -> 3 | F5: =4 -> 4 | G5: =5 -> 5 | H5: =8 -> 8 | I5: =11 -> 11 | J5: =15 -> 15 | K5: =20 -> 20 | L5: =25 -> 25 | M5: =30 -> 30
A6: Free projects | B6: =3 -> 3 | C6: =6 -> 6 | D6: =10 -> 10 | E6: =10 -> 10 | F6: =10 -> 10 | G6: =10 -> 10 | H6: =10 -> 10 | I6: =10 -> 10 | J6: =10 -> 10 | K6: =10 -> 10 | ... M6: =10 -> 10
A7: Extra fixes per team | B7: =0 -> 0 | C7: =0 -> 0 | D7: =0 -> 0 | E7: =0 -> 0 | F7: =0 -> 0 | G7: =0 -> 0 | H7: =0 -> 0 | I7: =0 -> 0 | ... M7: =0 -> 0
A8: Paid standalone fixes | B8: =0 -> 0 | C8: =0 -> 0 | D8: =0 -> 0 | E8: =0 -> 0 | F8: =0 -> 0 | G8: =0 -> 0 | H8: =0 -> 0 | I8: =0 -> 0 | ... M8: =0 -> 0
A9: Plan month | B9: =DATEDIF(DATE(2026,10,1),DATE(2026,10,1),"M")+1 -> 1 | C9: =DATEDIF(DATE(2026,10,1),DATE(2026,11,1),"M")+1 -> 2 | D9: =DATEDIF(DATE(2026,10,1),DATE(2026,12,1),"M")+1 -> 3 | E9: =DATEDIF(DATE(2026,10,1),DATE(2027,1,1),"M")+1 -> 4 | F9: =DATEDIF(DATE(2026,10,1),DATE(2027,2,1),"M")+1 -> 5 | G9: =DATEDIF(DATE(2026,10,1),DATE(2027,3,1),"M")+1 -> 6 | H9: =DATEDIF(DATE(2026,10,1),DATE(2027,4,1),"M")+1 -> 7 | I9: =DATEDIF(DATE(2026,10,1),DATE(2027,5,1),"M")+1 -> 8 | J9: =DATEDIF(DATE(2026,10,1),DATE(2027,6,1),"M")+1 -> 9 | K9: =DATEDIF(DATE(2026,10,1),DATE(2027,7,1),"M")+1 -> 10 | L9: =DATEDIF(DATE(2026,10,1),DATE(2027,8,1),"M")+1 -> 11 | M9: =DATEDIF(DATE(2026,10,1),DATE(2027,9,1),"M")+1 -> 12
A10: Team successful fixes | B10: ='Monthly operating and hiring fo'!B5*'Pricing and operating assumptio'!B6 -> 0 | C10: ='Monthly operating and hiring fo'!C5*'Pricing and operating assumptio'!B6 -> 10 | D10: ='Monthly operating and hiring fo'!D5*'Pricing and operating assumptio'!B6 -> 20 | E10: ='Monthly operating and hiring fo'!E5*'Pricing and operating assumptio'!B6 -> 30 | F10: ='Monthly operating and hiring fo'!F5*'Pricing and operating assumptio'!B6 -> 40 | G10: ='Monthly operating and hiring fo'!G5*'Pricing and operating assumptio'!B6 -> 50 | H10: ='Monthly operating and hiring fo'!H5*'Pricing and operating assumptio'!B6 -> 80 | I10: ='Monthly operating and hiring fo'!I5*'Pricing and operating assumptio'!B6 -> 110 | J10: ='Monthly operating and hiring fo'!J5*'Pricing and operating assumptio'!B6 -> 150 | K10: ='Monthly operating and hiring fo'!K5*'Pricing and operating assumptio'!B6 -> 200 | L10: ='Monthly operating and hiring fo'!L5*'Pricing and operating assumptio'!B6 -> 250 | M10: ='Monthly operating and hiring fo'!M5*'Pricing and operating assumptio'!B6 -> 300
A11: Free successful fixes | B11: ='Monthly operating and hiring fo'!B6*'Pricing and operating assumptio'!B17 -> 3 | C11: ='Monthly operating and hiring fo'!C6*'Pricing and operating assumptio'!B17 -> 6 | D11: ='Monthly operating and hiring fo'!D6*'Pricing and operating assumptio'!B17 -> 10 | E11: ='Monthly operating and hiring fo'!E6*'Pricing and operating assumptio'!B17 -> 10 | F11: ='Monthly operating and hiring fo'!F6*'Pricing and operating assumptio'!B17 -> 10 | G11: ='Monthly operating and hiring fo'!G6*'Pricing and operating assumptio'!B17 -> 10 | H11: ='Monthly operating and hiring fo'!H6*'Pricing and operating assumptio'!B17 -> 10 | I11: ='Monthly operating and hiring fo'!I6*'Pricing and operating assumptio'!B17 -> 10 | J11: ='Monthly operating and hiring fo'!J6*'Pricing and operating assumptio'!B17 -> 10 | K11: ='Monthly operating and hiring fo'!K6*'Pricing and operating assumptio'!B17 -> 10 | L11: ='Monthly operating and hiring fo'!L6*'Pricing and operating assumptio'!B17 -> 10 | M11: ='Monthly operating and hiring fo'!M6*'Pricing and operating assumptio'!B17 -> 10
A12: Extra successful fixes | B12: ='Monthly operating and hiring fo'!B5*'Monthly operating and hiring fo'!B7 -> 0 | C12: ='Monthly operating and hiring fo'!C5*'Monthly operating and hiring fo'!C7 -> 0 | D12: ='Monthly operating and hiring fo'!D5*'Monthly operating and hiring fo'!D7 -> 0 | E12: ='Monthly operating and hiring fo'!E5*'Monthly operating and hiring fo'!E7 -> 0 | F12: ='Monthly operating and hiring fo'!F5*'Monthly operating and hiring fo'!F7 -> 0 | G12: ='Monthly operating and hiring fo'!G5*'Monthly operating and hiring fo'!G7 -> 0 | H12: ='Monthly operating and hiring fo'!H5*'Monthly operating and hiring fo'!H7 -> 0 | I12: ='Monthly operating and hiring fo'!I5*'Monthly operating and hiring fo'!I7 -> 0 | ... M12: ='Monthly operating and hiring fo'!M5*'Monthly operating and hiring fo'!M7 -> 0
A13: Team subscription revenue | B13: ='Monthly operating and hiring fo'!B5*'Pricing and operating assumptio'!B5 -> 0 | C13: ='Monthly operating and hiring fo'!C5*'Pricing and operating assumptio'!B5 -> 199 | D13: ='Monthly operating and hiring fo'!D5*'Pricing and operating assumptio'!B5 -> 398 | E13: ='Monthly operating and hiring fo'!E5*'Pricing and operating assumptio'!B5 -> 597 | F13: ='Monthly operating and hiring fo'!F5*'Pricing and operating assumptio'!B5 -> 796 | G13: ='Monthly operating and hiring fo'!G5*'Pricing and operating assumptio'!B5 -> 995 | H13: ='Monthly operating and hiring fo'!H5*'Pricing and operating assumptio'!B5 -> 1592 | I13: ='Monthly operating and hiring fo'!I5*'Pricing and operating assumptio'!B5 -> 2189 | J13: ='Monthly operating and hiring fo'!J5*'Pricing and operating assumptio'!B5 -> 2985 | K13: ='Monthly operating and hiring fo'!K5*'Pricing and operating assumptio'!B5 -> 3980 | L13: ='Monthly operating and hiring fo'!L5*'Pricing and operating assumptio'!B5 -> 4975 | M13: ='Monthly operating and hiring fo'!M5*'Pricing and operating assumptio'!B5 -> 5970
A14: Extra fix revenue | B14: ='Monthly operating and hiring fo'!B12*'Pricing and operating assumptio'!B7 -> 0 | C14: ='Monthly operating and hiring fo'!C12*'Pricing and operating assumptio'!B7 -> 0 | D14: ='Monthly operating and hiring fo'!D12*'Pricing and operating assumptio'!B7 -> 0 | E14: ='Monthly operating and hiring fo'!E12*'Pricing and operating assumptio'!B7 -> 0 | F14: ='Monthly operating and hiring fo'!F12*'Pricing and operating assumptio'!B7 -> 0 | G14: ='Monthly operating and hiring fo'!G12*'Pricing and operating assumptio'!B7 -> 0 | H14: ='Monthly operating and hiring fo'!H12*'Pricing and operating assumptio'!B7 -> 0 | I14: ='Monthly operating and hiring fo'!I12*'Pricing and operating assumptio'!B7 -> 0 | J14: ='Monthly operating and hiring fo'!J12*'Pricing and operating assumptio'!B7 -> 0 | K14: ='Monthly operating and hiring fo'!K12*'Pricing and operating assumptio'!B7 -> 0 | L14: ='Monthly operating and hiring fo'!L12*'Pricing and operating assumptio'!B7 -> 0 | M14: ='Monthly operating and hiring fo'!M12*'Pricing and operating assumptio'!B7 -> 0
A15: Pay per fix revenue | B15: ='Monthly operating and hiring fo'!B8*'Pricing and operating assumptio'!B8 -> 0 | C15: ='Monthly operating and hiring fo'!C8*'Pricing and operating assumptio'!B8 -> 0 | D15: ='Monthly operating and hiring fo'!D8*'Pricing and operating assumptio'!B8 -> 0 | E15: ='Monthly operating and hiring fo'!E8*'Pricing and operating assumptio'!B8 -> 0 | F15: ='Monthly operating and hiring fo'!F8*'Pricing and operating assumptio'!B8 -> 0 | G15: ='Monthly operating and hiring fo'!G8*'Pricing and operating assumptio'!B8 -> 0 | H15: ='Monthly operating and hiring fo'!H8*'Pricing and operating assumptio'!B8 -> 0 | I15: ='Monthly operating and hiring fo'!I8*'Pricing and operating assumptio'!B8 -> 0 | J15: ='Monthly operating and hiring fo'!J8*'Pricing and operating assumptio'!B8 -> 0 | K15: ='Monthly operating and hiring fo'!K8*'Pricing and operating assumptio'!B8 -> 0 | L15: ='Monthly operating and hiring fo'!L8*'Pricing and operating assumptio'!B8 -> 0 | M15: ='Monthly operating and hiring fo'!M8*'Pricing and operating assumptio'!B8 -> 0
A16: Revenue | B16: ='Monthly operating and hiring fo'!B13+'Monthly operating and hiring fo'!B14+'Monthly operating and hiring fo'!B15 -> 0 | C16: ='Monthly operating and hiring fo'!C13+'Monthly operating and hiring fo'!C14+'Monthly operating and hiring fo'!C15 -> 199 | D16: ='Monthly operating and hiring fo'!D13+'Monthly operating and hiring fo'!D14+'Monthly operating and hiring fo'!D15 -> 398 | E16: ='Monthly operating and hiring fo'!E13+'Monthly operating and hiring fo'!E14+'Monthly operating and hiring fo'!E15 -> 597 | F16: ='Monthly operating and hiring fo'!F13+'Monthly operating and hiring fo'!F14+'Monthly operating and hiring fo'!F15 -> 796 | G16: ='Monthly operating and hiring fo'!G13+'Monthly operating and hiring fo'!G14+'Monthly operating and hiring fo'!G15 -> 995 | H16: ='Monthly operating and hiring fo'!H13+'Monthly operating and hiring fo'!H14+'Monthly operating and hiring fo'!H15 -> 1592 | I16: ='Monthly operating and hiring fo'!I13+'Monthly operating and hiring fo'!I14+'Monthly operating and hiring fo'!I15 -> 2189 | ... M16: ='Monthly operating and hiring fo'!M13+'Monthly operating and hiring fo'!M14+'Monthly operating and hiring fo'!M15 -> 5970
A17: Paid delivery cost | B17: =('Monthly operating and hiring fo'!B10+'Monthly operating and hiring fo'!B12+'Monthly operating and hiring fo'!B8)*'Pricing and operating assumptio'!B9 -> 0 | C17: =('Monthly operating and hiring fo'!C10+'Monthly operating and hiring fo'!C12+'Monthly operating and hiring fo'!C8)*'Pricing and operating assumptio'!B9 -> 15 | D17: =('Monthly operating and hiring fo'!D10+'Monthly operating and hiring fo'!D12+'Monthly operating and hiring fo'!D8)*'Pricing and operating assumptio'!B9 -> 30 | E17: =('Monthly operating and hiring fo'!E10+'Monthly operating and hiring fo'!E12+'Monthly operating and hiring fo'!E8)*'Pricing and operating assumptio'!B9 -> 45 | F17: =('Monthly operating and hiring fo'!F10+'Monthly operating and hiring fo'!F12+'Monthly operating and hiring fo'!F8)*'Pricing and operating assumptio'!B9 -> 60 | G17: =('Monthly operating and hiring fo'!G10+'Monthly operating and hiring fo'!G12+'Monthly operating and hiring fo'!G8)*'Pricing and operating assumptio'!B9 -> 75 | H17: =('Monthly operating and hiring fo'!H10+'Monthly operating and hiring fo'!H12+'Monthly operating and hiring fo'!H8)*'Pricing and operating assumptio'!B9 -> 120 | I17: =('Monthly operating and hiring fo'!I10+'Monthly operating and hiring fo'!I12+'Monthly operating and hiring fo'!I8)*'Pricing and operating assumptio'!B9 -> 165 | J17: =('Monthly operating and hiring fo'!J10+'Monthly operating and hiring fo'!J12+'Monthly operating and hiring fo'!J8)*'Pricing and operating assumptio'!B9 -> 225 | K17: =('Monthly operating and hiring fo'!K10+'Monthly operating and hiring fo'!K12+'Monthly operating and hiring fo'!K8)*'Pricing and operating assumptio'!B9 -> 300 | L17: =('Monthly operating and hiring fo'!L10+'Monthly operating and hiring fo'!L12+'Monthly operating and hiring fo'!L8)*'Pricing and operating assumptio'!B9 -> 375 | M17: =('Monthly operating and hiring fo'!M10+'Monthly operating and hiring fo'!M12+'Monthly operating and hiring fo'!M8)*'Pricing and operating assumptio'!B9 -> 450
A18: Gross profit | B18: ='Monthly operating and hiring fo'!B16-'Monthly operating and hiring fo'!B17 -> 0 | C18: ='Monthly operating and hiring fo'!C16-'Monthly operating and hiring fo'!C17 -> 184 | D18: ='Monthly operating and hiring fo'!D16-'Monthly operating and hiring fo'!D17 -> 368 | E18: ='Monthly operating and hiring fo'!E16-'Monthly operating and hiring fo'!E17 -> 552 | F18: ='Monthly operating and hiring fo'!F16-'Monthly operating and hiring fo'!F17 -> 736 | G18: ='Monthly operating and hiring fo'!G16-'Monthly operating and hiring fo'!G17 -> 920 | H18: ='Monthly operating and hiring fo'!H16-'Monthly operating and hiring fo'!H17 -> 1472 | I18: ='Monthly operating and hiring fo'!I16-'Monthly operating and hiring fo'!I17 -> 2024 | ... M18: ='Monthly operating and hiring fo'!M16-'Monthly operating and hiring fo'!M17 -> 5520
A19: Gross margin | B19: =IFERROR('Monthly operating and hiring fo'!B18/'Monthly operating and hiring fo'!B16,"") | C19: =IFERROR('Monthly operating and hiring fo'!C18/'Monthly operating and hiring fo'!C16,"") -> 0.92462312 | D19: =IFERROR('Monthly operating and hiring fo'!D18/'Monthly operating and hiring fo'!D16,"") -> 0.92462312 | E19: =IFERROR('Monthly operating and hiring fo'!E18/'Monthly operating and hiring fo'!E16,"") -> 0.92462312 | F19: =IFERROR('Monthly operating and hiring fo'!F18/'Monthly operating and hiring fo'!F16,"") -> 0.92462312 | G19: =IFERROR('Monthly operating and hiring fo'!G18/'Monthly operating and hiring fo'!G16,"") -> 0.92462312 | H19: =IFERROR('Monthly operating and hiring fo'!H18/'Monthly operating and hiring fo'!H16,"") -> 0.92462312 | I19: =IFERROR('Monthly operating and hiring fo'!I18/'Monthly operating and hiring fo'!I16,"") -> 0.92462312 | ... M19: =IFERROR('Monthly operating and hiring fo'!M18/'Monthly operating and hiring fo'!M16,"") -> 0.92462312
A20: Free project cost | B20: ='Monthly operating and hiring fo'!B11*'Pricing and operating assumptio'!B9 -> 4.5 | C20: ='Monthly operating and hiring fo'!C11*'Pricing and operating assumptio'!B9 -> 9 | D20: ='Monthly operating and hiring fo'!D11*'Pricing and operating assumptio'!B9 -> 15 | E20: ='Monthly operating and hiring fo'!E11*'Pricing and operating assumptio'!B9 -> 15 | F20: ='Monthly operating and hiring fo'!F11*'Pricing and operating assumptio'!B9 -> 15 | G20: ='Monthly operating and hiring fo'!G11*'Pricing and operating assumptio'!B9 -> 15 | H20: ='Monthly operating and hiring fo'!H11*'Pricing and operating assumptio'!B9 -> 15 | I20: ='Monthly operating and hiring fo'!I11*'Pricing and operating assumptio'!B9 -> 15 | J20: ='Monthly operating and hiring fo'!J11*'Pricing and operating assumptio'!B9 -> 15 | K20: ='Monthly operating and hiring fo'!K11*'Pricing and operating assumptio'!B9 -> 15 | L20: ='Monthly operating and hiring fo'!L11*'Pricing and operating assumptio'!B9 -> 15 | M20: ='Monthly operating and hiring fo'!M11*'Pricing and operating assumptio'!B9 -> 15
A21: Fixed overhead | B21: ='Pricing and operating assumptio'!B11+'Pricing and operating assumptio'!B12 -> 150 | C21: ='Pricing and operating assumptio'!B11+'Pricing and operating assumptio'!B12 -> 150 | D21: ='Pricing and operating assumptio'!B11+'Pricing and operating assumptio'!B12 -> 150 | E21: ='Pricing and operating assumptio'!B11+'Pricing and operating assumptio'!B12 -> 150 | F21: ='Pricing and operating assumptio'!B11+'Pricing and operating assumptio'!B12 -> 150 | G21: ='Pricing and operating assumptio'!B11+'Pricing and operating assumptio'!B12 -> 150 | H21: ='Pricing and operating assumptio'!B11+'Pricing and operating assumptio'!B12 -> 150 | I21: ='Pricing and operating assumptio'!B11+'Pricing and operating assumptio'!B12 -> 150 | J21: ='Pricing and operating assumptio'!B11+'Pricing and operating assumptio'!B12 -> 150 | K21: ='Pricing and operating assumptio'!B11+'Pricing and operating assumptio'!B12 -> 150 | L21: ='Pricing and operating assumptio'!B11+'Pricing and operating assumptio'!B12 -> 150 | M21: ='Pricing and operating assumptio'!B11+'Pricing and operating assumptio'!B12 -> 150
A22: Founder pay | B22: =IF(IF(IF(ISERROR('Monthly operating and hiring fo'!B9>='Pricing and operating assumptio'!B14),'Monthly operating and hiring fo'!B9>='Pricing and operating assumptio'!B14,IF(OR('Monthly operating and hiring fo'!B9="",'Pricing and operating assumptio'!B14=""),"",'Monthly operating and hiring fo'!B9>='Pricing and operating assumptio'!B14))="",FALSE,IF(ISERROR('Monthly operating and hiring fo'!B9>='Pricing and operating assumptio'!B14),'Monthly operating and hiring fo'!B9>='Pricing and operating assumptio'!B14,IF(OR('Monthly operating and hiring fo'!B9="",'Pricing and operating assumptio'!B14=""),"",'Monthly operating and hiring fo'!B9>='Pricing and operating assumptio'!B14))),IF('Pricing and operating assumptio'!B13="","",'Pricing and operating assumptio'!B13),0) -> 0 | C22: =IF(IF(IF(ISERROR('Monthly operating and hiring fo'!C9>='Pricing and operating assumptio'!B14),'Monthly operating and hiring fo'!C9>='Pricing and operating assumptio'!B14,IF(OR('Monthly operating and hiring fo'!C9="",'Pricing and operating assumptio'!B14=""),"",'Monthly operating and hiring fo'!C9>='Pricing and operating assumptio'!B14))="",FALSE,IF(ISERROR('Monthly operating and hiring fo'!C9>='Pricing and operating assumptio'!B14),'Monthly operating and hiring fo'!C9>='Pricing and operating assumptio'!B14,IF(OR('Monthly operating and hiring fo'!C9="",'Pricing and operating assumptio'!B14=""),"",'Monthly operating and hiring fo'!C9>='Pricing and operating assumptio'!B14))),IF('Pricing and operating assumptio'!B13="","",'Pricing and operating assumptio'!B13),0) -> 0 | D22: =IF(IF(IF(ISERROR('Monthly operating and hiring fo'!D9>='Pricing and operating assumptio'!B14),'Monthly operating and hiring fo'!D9>='Pricing and operating assumptio'!B14,IF(OR('Monthly operating and hiring fo'!D9="",'Pricing and operating assumptio'!B14=""),"",'Monthly operating and hiring fo'!D9>='Pricing and operating assumptio'!B14))="",FALSE,IF(ISERROR('Monthly operating and hiring fo'!D9>='Pricing and operating assumptio'!B14),'Monthly operating and hiring fo'!D9>='Pricing and operating assumptio'!B14,IF(OR('Monthly operating and hiring fo'!D9="",'Pricing and operating assumptio'!B14=""),"",'Monthly operating and hiring fo'!D9>='Pricing and operating assumptio'!B14))),IF('Pricing and operating assumptio'!B13="","",'Pricing and operating assumptio'!B13),0) -> 0 | E22: =IF(IF(IF(ISERROR('Monthly operating and hiring fo'!E9>='Pricing and operating assumptio'!B14),'Monthly operating and hiring fo'!E9>='Pricing and operating assumptio'!B14,IF(OR('Monthly operating and hiring fo'!E9="",'Pricing and operating assumptio'!B14=""),"",'Monthly operating and hiring fo'!E9>='Pricing and operating assumptio'!B14))="",FALSE,IF(ISERROR('Monthly operating and hiring fo'!E9>='Pricing and operating assumptio'!B14),'Monthly operating and hiring fo'!E9>='Pricing and operating assumptio'!B14,IF(OR('Monthly operating and hiring fo'!E9="",'Pricing and operating assumptio'!B14=""),"",'Monthly operating and hiring fo'!E9>='Pricing and operating assumptio'!B14))),IF('Pricing and operating assumptio'!B13="","",'Pricing and operating assumptio'!B13),0) -> 0 | F22: =IF(IF(IF(ISERROR('Monthly operating and hiring fo'!F9>='Pricing and operating assumptio'!B14),'Monthly operating and hiring fo'!F9>='Pricing and operating assumptio'!B14,IF(OR('Monthly operating and hiring fo'!F9="",'Pricing and operating assumptio'!B14=""),"",'Monthly operating and hiring fo'!F9>='Pricing and operating assumptio'!B14))="",FALSE,IF(ISERROR('Monthly operating and hiring fo'!F9>='Pricing and operating assumptio'!B14),'Monthly operating and hiring fo'!F9>='Pricing and operating assumptio'!B14,IF(OR('Monthly operating and hiring fo'!F9="",'Pricing and operating assumptio'!B14=""),"",'Monthly operating and hiring fo'!F9>='Pricing and operating assumptio'!B14))),IF('Pricing and operating assumptio'!B13="","",'Pricing and operating assumptio'!B13),0) -> 0 | G22: =IF(IF(IF(ISERROR('Monthly operating and hiring fo'!G9>='Pricing and operating assumptio'!B14),'Monthly operating and hiring fo'!G9>='Pricing and operating assumptio'!B14,IF(OR('Monthly operating and hiring fo'!G9="",'Pricing and operating assumptio'!B14=""),"",'Monthly operating and hiring fo'!G9>='Pricing and operating assumptio'!B14))="",FALSE,IF(ISERROR('Monthly operating and hiring fo'!G9>='Pricing and operating assumptio'!B14),'Monthly operating and hiring fo'!G9>='Pricing and operating assumptio'!B14,IF(OR('Monthly operating and hiring fo'!G9="",'Pricing and operating assumptio'!B14=""),"",'Monthly operating and hiring fo'!G9>='Pricing and operating assumptio'!B14))),IF('Pricing and operating assumptio'!B13="","",'Pricing and operating assumptio'!B13),0) -> 0 | H22: =IF(IF(IF(ISERROR('Monthly operating and hiring fo'!H9>='Pricing and operating assumptio'!B14),'Monthly operating and hiring fo'!H9>='Pricing and operating assumptio'!B14,IF(OR('Monthly operating and hiring fo'!H9="",'Pricing and operating assumptio'!B14=""),"",'Monthly operating and hiring fo'!H9>='Pricing and operating assumptio'!B14))="",FALSE,IF(ISERROR('Monthly operating and hiring fo'!H9>='Pricing and operating assumptio'!B14),'Monthly operating and hiring fo'!H9>='Pricing and operating assumptio'!B14,IF(OR('Monthly operating and hiring fo'!H9="",'Pricing and operating assumptio'!B14=""),"",'Monthly operating and hiring fo'!H9>='Pricing and operating assumptio'!B14))),IF('Pricing and operating assumptio'!B13="","",'Pricing and operating assumptio'!B13),0) -> 4000 | I22: =IF(IF(IF(ISERROR('Monthly operating and hiring fo'!I9>='Pricing and operating assumptio'!B14),'Monthly operating and hiring fo'!I9>='Pricing and operating assumptio'!B14,IF(OR('Monthly operating and hiring fo'!I9="",'Pricing and operating assumptio'!B14=""),"",'Monthly operating and hiring fo'!I9>='Pricing and operating assumptio'!B14))="",FALSE,IF(ISERROR('Monthly operating and hiring fo'!I9>='Pricing and operating assumptio'!B14),'Monthly operating and hiring fo'!I9>='Pricing and operating assumptio'!B14,IF(OR('Monthly operating and hiring fo'!I9="",'Pricing and operating assumptio'!B14=""),"",'Monthly operating and hiring fo'!I9>='Pricing and operating assumptio'!B14))),IF('Pricing and operating assumptio'!B13="","",'Pricing and operating assumptio'!B13),0) -> 4000 | J22: =IF(IF(IF(ISERROR('Monthly operating and hiring fo'!J9>='Pricing and operating assumptio'!B14),'Monthly operating and hiring fo'!J9>='Pricing and operating assumptio'!B14,IF(OR('Monthly operating and hiring fo'!J9="",'Pricing and operating assumptio'!B14=""),"",'Monthly operating and hiring fo'!J9>='Pricing and operating assumptio'!B14))="",FALSE,IF(ISERROR('Monthly operating and hiring fo'!J9>='Pricing and operating assumptio'!B14),'Monthly operating and hiring fo'!J9>='Pricing and operating assumptio'!B14,IF(OR('Monthly operating and hiring fo'!J9="",'Pricing and operating assumptio'!B14=""),"",'Monthly operating and hiring fo'!J9>='Pricing and operating assumptio'!B14))),IF('Pricing and operating assumptio'!B13="","",'Pricing and operating assumptio'!B13),0) -> 4000 | K22: =IF(IF(IF(ISERROR('Monthly operating and hiring fo'!K9>='Pricing and operating assumptio'!B14),'Monthly operating and hiring fo'!K9>='Pricing and operating assumptio'!B14,IF(OR('Monthly operating and hiring fo'!K9="",'Pricing and operating assumptio'!B14=""),"",'Monthly operating and hiring fo'!K9>='Pricing and operating assumptio'!B14))="",FALSE,IF(ISERROR('Monthly operating and hiring fo'!K9>='Pricing and operating assumptio'!B14),'Monthly operating and hiring fo'!K9>='Pricing and operating assumptio'!B14,IF(OR('Monthly operating and hiring fo'!K9="",'Pricing and operating assumptio'!B14=""),"",'Monthly operating and hiring fo'!K9>='Pricing and operating assumptio'!B14))),IF('Pricing and operating assumptio'!B13="","",'Pricing and operating assumptio'!B13),0) -> 4000 | L22: =IF(IF(IF(ISERROR('Monthly operating and hiring fo'!L9>='Pricing and operating assumptio'!B14),'Monthly operating and hiring fo'!L9>='Pricing and operating assumptio'!B14,IF(OR('Monthly operating and hiring fo'!L9="",'Pricing and operating assumptio'!B14=""),"",'Monthly operating and hiring fo'!L9>='Pricing and operating assumptio'!B14))="",FALSE,IF(ISERROR('Monthly operating and hiring fo'!L9>='Pricing and operating assumptio'!B14),'Monthly operating and hiring fo'!L9>='Pricing and operating assumptio'!B14,IF(OR('Monthly operating and hiring fo'!L9="",'Pricing and operating assumptio'!B14=""),"",'Monthly operating and hiring fo'!L9>='Pricing and operating assumptio'!B14))),IF('Pricing and operating assumptio'!B13="","",'Pricing and operating assumptio'!B13),0) -> 4000 | M22: =IF(IF(IF(ISERROR('Monthly operating and hiring fo'!M9>='Pricing and operating assumptio'!B14),'Monthly operating and hiring fo'!M9>='Pricing and operating assumptio'!B14,IF(OR('Monthly operating and hiring fo'!M9="",'Pricing and operating assumptio'!B14=""),"",'Monthly operating and hiring fo'!M9>='Pricing and operating assumptio'!B14))="",FALSE,IF(ISERROR('Monthly operating and hiring fo'!M9>='Pricing and operating assumptio'!B14),'Monthly operating and hiring fo'!M9>='Pricing and operating assumptio'!B14,IF(OR('Monthly operating and hiring fo'!M9="",'Pricing and operating assumptio'!B14=""),"",'Monthly operating and hiring fo'!M9>='Pricing and operating assumptio'!B14))),IF('Pricing and operating assumptio'!B13="","",'Pricing and operating assumptio'!B13),0) -> 4000
A23: Cash flow before hire | B23: ='Monthly operating and hiring fo'!B18-'Monthly operating and hiring fo'!B20-'Monthly operating and hiring fo'!B21-'Monthly operating and hiring fo'!B22 -> -154.5 | C23: ='Monthly operating and hiring fo'!C18-'Monthly operating and hiring fo'!C20-'Monthly operating and hiring fo'!C21-'Monthly operating and hiring fo'!C22 -> 25 | D23: ='Monthly operating and hiring fo'!D18-'Monthly operating and hiring fo'!D20-'Monthly operating and hiring fo'!D21-'Monthly operating and hiring fo'!D22 -> 203 | E23: ='Monthly operating and hiring fo'!E18-'Monthly operating and hiring fo'!E20-'Monthly operating and hiring fo'!E21-'Monthly operating and hiring fo'!E22 -> 387 | F23: ='Monthly operating and hiring fo'!F18-'Monthly operating and hiring fo'!F20-'Monthly operating and hiring fo'!F21-'Monthly operating and hiring fo'!F22 -> 571 | G23: ='Monthly operating and hiring fo'!G18-'Monthly operating and hiring fo'!G20-'Monthly operating and hiring fo'!G21-'Monthly operating and hiring fo'!G22 -> 755 | H23: ='Monthly operating and hiring fo'!H18-'Monthly operating and hiring fo'!H20-'Monthly operating and hiring fo'!H21-'Monthly operating and hiring fo'!H22 -> -2693 | I23: ='Monthly operating and hiring fo'!I18-'Monthly operating and hiring fo'!I20-'Monthly operating and hiring fo'!I21-'Monthly operating and hiring fo'!I22 -> -2141 | ... M23: ='Monthly operating and hiring fo'!M18-'Monthly operating and hiring fo'!M20-'Monthly operating and hiring fo'!M21-'Monthly operating and hiring fo'!M22 -> 1355
A24: Team contribution | B24: ='Pricing and operating assumptio'!B5-'Pricing and operating assumptio'!B6*'Pricing and operating assumptio'!B9 -> 184 | C24: ='Pricing and operating assumptio'!B5-'Pricing and operating assumptio'!B6*'Pricing and operating assumptio'!B9 -> 184 | D24: ='Pricing and operating assumptio'!B5-'Pricing and operating assumptio'!B6*'Pricing and operating assumptio'!B9 -> 184 | E24: ='Pricing and operating assumptio'!B5-'Pricing and operating assumptio'!B6*'Pricing and operating assumptio'!B9 -> 184 | F24: ='Pricing and operating assumptio'!B5-'Pricing and operating assumptio'!B6*'Pricing and operating assumptio'!B9 -> 184 | G24: ='Pricing and operating assumptio'!B5-'Pricing and operating assumptio'!B6*'Pricing and operating assumptio'!B9 -> 184 | H24: ='Pricing and operating assumptio'!B5-'Pricing and operating assumptio'!B6*'Pricing and operating assumptio'!B9 -> 184 | I24: ='Pricing and operating assumptio'!B5-'Pricing and operating assumptio'!B6*'Pricing and operating assumptio'!B9 -> 184 | J24: ='Pricing and operating assumptio'!B5-'Pricing and operating assumptio'!B6*'Pricing and operating assumptio'!B9 -> 184 | K24: ='Pricing and operating assumptio'!B5-'Pricing and operating assumptio'!B6*'Pricing and operating assumptio'!B9 -> 184 | L24: ='Pricing and operating assumptio'!B5-'Pricing and operating assumptio'!B6*'Pricing and operating assumptio'!B9 -> 184 | M24: ='Pricing and operating assumptio'!B5-'Pricing and operating assumptio'!B6*'Pricing and operating assumptio'!B9 -> 184
A25: Break-even teams | B25: =CEILING(('Monthly operating and hiring fo'!B21+'Monthly operating and hiring fo'!B20+'Monthly operating and hiring fo'!B22)/'Monthly operating and hiring fo'!B24,1) -> 1 | C25: =CEILING(('Monthly operating and hiring fo'!C21+'Monthly operating and hiring fo'!C20+'Monthly operating and hiring fo'!C22)/'Monthly operating and hiring fo'!C24,1) -> 1 | D25: =CEILING(('Monthly operating and hiring fo'!D21+'Monthly operating and hiring fo'!D20+'Monthly operating and hiring fo'!D22)/'Monthly operating and hiring fo'!D24,1) -> 1 | E25: =CEILING(('Monthly operating and hiring fo'!E21+'Monthly operating and hiring fo'!E20+'Monthly operating and hiring fo'!E22)/'Monthly operating and hiring fo'!E24,1) -> 1 | F25: =CEILING(('Monthly operating and hiring fo'!F21+'Monthly operating and hiring fo'!F20+'Monthly operating and hiring fo'!F22)/'Monthly operating and hiring fo'!F24,1) -> 1 | G25: =CEILING(('Monthly operating and hiring fo'!G21+'Monthly operating and hiring fo'!G20+'Monthly operating and hiring fo'!G22)/'Monthly operating and hiring fo'!G24,1) -> 1 | H25: =CEILING(('Monthly operating and hiring fo'!H21+'Monthly operating and hiring fo'!H20+'Monthly operating and hiring fo'!H22)/'Monthly operating and hiring fo'!H24,1) -> 23 | I25: =CEILING(('Monthly operating and hiring fo'!I21+'Monthly operating and hiring fo'!I20+'Monthly operating and hiring fo'!I22)/'Monthly operating and hiring fo'!I24,1) -> 23 | ... M25: =CEILING(('Monthly operating and hiring fo'!M21+'Monthly operating and hiring fo'!M20+'Monthly operating and hiring fo'!M22)/'Monthly operating and hiring fo'!M24,1) -> 23
A26: Teams needed with engineer | B26: =CEILING(('Monthly operating and hiring fo'!B21+'Monthly operating and hiring fo'!B20+'Monthly operating and hiring fo'!B22+'Pricing and operating assumptio'!B15)/'Monthly operating and hiring fo'!B24,1) -> 34 | C26: =CEILING(('Monthly operating and hiring fo'!C21+'Monthly operating and hiring fo'!C20+'Monthly operating and hiring fo'!C22+'Pricing and operating assumptio'!B15)/'Monthly operating and hiring fo'!C24,1) -> 34 | D26: =CEILING(('Monthly operating and hiring fo'!D21+'Monthly operating and hiring fo'!D20+'Monthly operating and hiring fo'!D22+'Pricing and operating assumptio'!B15)/'Monthly operating and hiring fo'!D24,1) -> 34 | E26: =CEILING(('Monthly operating and hiring fo'!E21+'Monthly operating and hiring fo'!E20+'Monthly operating and hiring fo'!E22+'Pricing and operating assumptio'!B15)/'Monthly operating and hiring fo'!E24,1) -> 34 | F26: =CEILING(('Monthly operating and hiring fo'!F21+'Monthly operating and hiring fo'!F20+'Monthly operating and hiring fo'!F22+'Pricing and operating assumptio'!B15)/'Monthly operating and hiring fo'!F24,1) -> 34 | G26: =CEILING(('Monthly operating and hiring fo'!G21+'Monthly operating and hiring fo'!G20+'Monthly operating and hiring fo'!G22+'Pricing and operating assumptio'!B15)/'Monthly operating and hiring fo'!G24,1) -> 34 | H26: =CEILING(('Monthly operating and hiring fo'!H21+'Monthly operating and hiring fo'!H20+'Monthly operating and hiring fo'!H22+'Pricing and operating assumptio'!B15)/'Monthly operating and hiring fo'!H24,1) -> 56 | I26: =CEILING(('Monthly operating and hiring fo'!I21+'Monthly operating and hiring fo'!I20+'Monthly operating and hiring fo'!I22+'Pricing and operating assumptio'!B15)/'Monthly operating and hiring fo'!I24,1) -> 56 | J26: =CEILING(('Monthly operating and hiring fo'!J21+'Monthly operating and hiring fo'!J20+'Monthly operating and hiring fo'!J22+'Pricing and operating assumptio'!B15)/'Monthly operating and hiring fo'!J24,1) -> 56 | K26: =CEILING(('Monthly operating and hiring fo'!K21+'Monthly operating and hiring fo'!K20+'Monthly operating and hiring fo'!K22+'Pricing and operating assumptio'!B15)/'Monthly operating and hiring fo'!K24,1) -> 56 | L26: =CEILING(('Monthly operating and hiring fo'!L21+'Monthly operating and hiring fo'!L20+'Monthly operating and hiring fo'!L22+'Pricing and operating assumptio'!B15)/'Monthly operating and hiring fo'!L24,1) -> 56 | M26: =CEILING(('Monthly operating and hiring fo'!M21+'Monthly operating and hiring fo'!M20+'Monthly operating and hiring fo'!M22+'Pricing and operating assumptio'!B15)/'Monthly operating and hiring fo'!M24,1) -> 56
A27: Engineer hired | B27: =IF(IF(IF(ISERROR('Monthly operating and hiring fo'!B9<'Pricing and operating assumptio'!B16),'Monthly operating and hiring fo'!B9<'Pricing and operating assumptio'!B16,IF(OR('Monthly operating and hiring fo'!B9="",'Pricing and operating assumptio'!B16=""),"",'Monthly operating and hiring fo'!B9<'Pricing and operating assumptio'!B16))="",FALSE,IF(ISERROR('Monthly operating and hiring fo'!B9<'Pricing and operating assumptio'!B16),'Monthly operating and hiring fo'!B9<'Pricing and operating assumptio'!B16,IF(OR('Monthly operating and hiring fo'!B9="",'Pricing and operating assumptio'!B16=""),"",'Monthly operating and hiring fo'!B9<'Pricing and operating assumptio'!B16))),0,IF(IF(IF(IFERROR(IF(ISERROR('Model inputs'!B24=1),'Model inputs'!B24=1,IF('Model inputs'!B24="","",'Model inputs'!B24=1))=TRUE,FALSE),TRUE,IF(IFERROR('Model inputs'!B167=TRUE,FALSE),TRUE,IF(OR(IF(ISERROR('Model inputs'!B24=1),'Model inputs'!B24=1,IF('Model inputs'!B24="","",'Model inputs'!B24=1))="",'Model inputs'!B167=""),"",OR(IF(ISERROR('Model inputs'!B24=1),'Model inputs'!B24=1,IF('Model inputs'!B24="","",'Model inputs'!B24=1)),'Model inputs'!B167))))="",FALSE,IF(IFERROR(IF(ISERROR('Model inputs'!B24=1),'Model inputs'!B24=1,IF('Model inputs'!B24="","",'Model inputs'!B24=1))=TRUE,FALSE),TRUE,IF(IFERROR('Model inputs'!B167=TRUE,FALSE),TRUE,IF(OR(IF(ISERROR('Model inputs'!B24=1),'Model inputs'!B24=1,IF('Model inputs'!B24="","",'Model inputs'!B24=1))="",'Model inputs'!B167=""),"",OR(IF(ISERROR('Model inputs'!B24=1),'Model inputs'!B24=1,IF('Model inputs'!B24="","",'Model inputs'!B24=1)),'Model inputs'!B167))))),1,0)) -> 0 | C27: =IF(IF(IF(ISERROR('Monthly operating and hiring fo'!C9<'Pricing and operating assumptio'!B16),'Monthly operating and hiring fo'!C9<'Pricing and operating assumptio'!B16,IF(OR('Monthly operating and hiring fo'!C9="",'Pricing and operating assumptio'!B16=""),"",'Monthly operating and hiring fo'!C9<'Pricing and operating assumptio'!B16))="",FALSE,IF(ISERROR('Monthly operating and hiring fo'!C9<'Pricing and operating assumptio'!B16),'Monthly operating and hiring fo'!C9<'Pricing and operating assumptio'!B16,IF(OR('Monthly operating and hiring fo'!C9="",'Pricing and operating assumptio'!B16=""),"",'Monthly operating and hiring fo'!C9<'Pricing and operating assumptio'!B16))),0,IF(IF(IF(IFERROR('Model inputs'!B168=TRUE,FALSE),TRUE,IF(IFERROR('Model inputs'!B169=TRUE,FALSE),TRUE,IF(OR('Model inputs'!B168="",'Model inputs'!B169=""),"",OR('Model inputs'!B168,'Model inputs'!B169))))="",FALSE,IF(IFERROR('Model inputs'!B168=TRUE,FALSE),TRUE,IF(IFERROR('Model inputs'!B169=TRUE,FALSE),TRUE,IF(OR('Model inputs'!B168="",'Model inputs'!B169=""),"",OR('Model inputs'!B168,'Model inputs'!B169))))),1,0)) -> 0 | D27: =IF(IF(IF(ISERROR('Monthly operating and hiring fo'!D9<'Pricing and operating assumptio'!B16),'Monthly operating and hiring fo'!D9<'Pricing and operating assumptio'!B16,IF(OR('Monthly operating and hiring fo'!D9="",'Pricing and operating assumptio'!B16=""),"",'Monthly operating and hiring fo'!D9<'Pricing and operating assumptio'!B16))="",FALSE,IF(ISERROR('Monthly operating and hiring fo'!D9<'Pricing and operating assumptio'!B16),'Monthly operating and hiring fo'!D9<'Pricing and operating assumptio'!B16,IF(OR('Monthly operating and hiring fo'!D9="",'Pricing and operating assumptio'!B16=""),"",'Monthly operating and hiring fo'!D9<'Pricing and operating assumptio'!B16))),0,IF(IF(IF(IFERROR('Model inputs'!B170=TRUE,FALSE),TRUE,IF(IFERROR('Model inputs'!B171=TRUE,FALSE),TRUE,IF(OR('Model inputs'!B170="",'Model inputs'!B171=""),"",OR('Model inputs'!B170,'Model inputs'!B171))))="",FALSE,IF(IFERROR('Model inputs'!B170=TRUE,FALSE),TRUE,IF(IFERROR('Model inputs'!B171=TRUE,FALSE),TRUE,IF(OR('Model inputs'!B170="",'Model inputs'!B171=""),"",OR('Model inputs'!B170,'Model inputs'!B171))))),1,0)) -> 0 | E27: =IF(IF(IF(ISERROR('Monthly operating and hiring fo'!E9<'Pricing and operating assumptio'!B16),'Monthly operating and hiring fo'!E9<'Pricing and operating assumptio'!B16,IF(OR('Monthly operating and hiring fo'!E9="",'Pricing and operating assumptio'!B16=""),"",'Monthly operating and hiring fo'!E9<'Pricing and operating assumptio'!B16))="",FALSE,IF(ISERROR('Monthly operating and hiring fo'!E9<'Pricing and operating assumptio'!B16),'Monthly operating and hiring fo'!E9<'Pricing and operating assumptio'!B16,IF(OR('Monthly operating and hiring fo'!E9="",'Pricing and operating assumptio'!B16=""),"",'Monthly operating and hiring fo'!E9<'Pricing and operating assumptio'!B16))),0,IF(IF(IF(IFERROR('Model inputs'!B172=TRUE,FALSE),TRUE,IF(IFERROR('Model inputs'!B173=TRUE,FALSE),TRUE,IF(OR('Model inputs'!B172="",'Model inputs'!B173=""),"",OR('Model inputs'!B172,'Model inputs'!B173))))="",FALSE,IF(IFERROR('Model inputs'!B172=TRUE,FALSE),TRUE,IF(IFERROR('Model inputs'!B173=TRUE,FALSE),TRUE,IF(OR('Model inputs'!B172="",'Model inputs'!B173=""),"",OR('Model inputs'!B172,'Model inputs'!B173))))),1,0)) -> 0 | F27: =IF(IF(IF(ISERROR('Monthly operating and hiring fo'!F9<'Pricing and operating assumptio'!B16),'Monthly operating and hiring fo'!F9<'Pricing and operating assumptio'!B16,IF(OR('Monthly operating and hiring fo'!F9="",'Pricing and operating assumptio'!B16=""),"",'Monthly operating and hiring fo'!F9<'Pricing and operating assumptio'!B16))="",FALSE,IF(ISERROR('Monthly operating and hiring fo'!F9<'Pricing and operating assumptio'!B16),'Monthly operating and hiring fo'!F9<'Pricing and operating assumptio'!B16,IF(OR('Monthly operating and hiring fo'!F9="",'Pricing and operating assumptio'!B16=""),"",'Monthly operating and hiring fo'!F9<'Pricing and operating assumptio'!B16))),0,IF(IF(IF(IFERROR('Model inputs'!B174=TRUE,FALSE),TRUE,IF(IFERROR('Model inputs'!B175=TRUE,FALSE),TRUE,IF(OR('Model inputs'!B174="",'Model inputs'!B175=""),"",OR('Model inputs'!B174,'Model inputs'!B175))))="",FALSE,IF(IFERROR('Model inputs'!B174=TRUE,FALSE),TRUE,IF(IFERROR('Model inputs'!B175=TRUE,FALSE),TRUE,IF(OR('Model inputs'!B174="",'Model inputs'!B175=""),"",OR('Model inputs'!B174,'Model inputs'!B175))))),1,0)) -> 0 | G27: =IF(IF(IF(ISERROR('Monthly operating and hiring fo'!G9<'Pricing and operating assumptio'!B16),'Monthly operating and hiring fo'!G9<'Pricing and operating assumptio'!B16,IF(OR('Monthly operating and hiring fo'!G9="",'Pricing and operating assumptio'!B16=""),"",'Monthly operating and hiring fo'!G9<'Pricing and operating assumptio'!B16))="",FALSE,IF(ISERROR('Monthly operating and hiring fo'!G9<'Pricing and operating assumptio'!B16),'Monthly operating and hiring fo'!G9<'Pricing and operating assumptio'!B16,IF(OR('Monthly operating and hiring fo'!G9="",'Pricing and operating assumptio'!B16=""),"",'Monthly operating and hiring fo'!G9<'Pricing and operating assumptio'!B16))),0,IF(IF(IF(IFERROR('Model inputs'!B176=TRUE,FALSE),TRUE,IF(IFERROR('Model inputs'!B177=TRUE,FALSE),TRUE,IF(OR('Model inputs'!B176="",'Model inputs'!B177=""),"",OR('Model inputs'!B176,'Model inputs'!B177))))="",FALSE,IF(IFERROR('Model inputs'!B176=TRUE,FALSE),TRUE,IF(IFERROR('Model inputs'!B177=TRUE,FALSE),TRUE,IF(OR('Model inputs'!B176="",'Model inputs'!B177=""),"",OR('Model inputs'!B176,'Model inputs'!B177))))),1,0)) -> 0 | H27: =IF(IF(IF(ISERROR('Monthly operating and hiring fo'!H9<'Pricing and operating assumptio'!B16),'Monthly operating and hiring fo'!H9<'Pricing and operating assumptio'!B16,IF(OR('Monthly operating and hiring fo'!H9="",'Pricing and operating assumptio'!B16=""),"",'Monthly operating and hiring fo'!H9<'Pricing and operating assumptio'!B16))="",FALSE,IF(ISERROR('Monthly operating and hiring fo'!H9<'Pricing and operating assumptio'!B16),'Monthly operating and hiring fo'!H9<'Pricing and operating assumptio'!B16,IF(OR('Monthly operating and hiring fo'!H9="",'Pricing and operating assumptio'!B16=""),"",'Monthly operating and hiring fo'!H9<'Pricing and operating assumptio'!B16))),0,IF(IF(IF(IFERROR('Model inputs'!B178=TRUE,FALSE),TRUE,IF(IFERROR('Model inputs'!B179=TRUE,FALSE),TRUE,IF(OR('Model inputs'!B178="",'Model inputs'!B179=""),"",OR('Model inputs'!B178,'Model inputs'!B179))))="",FALSE,IF(IFERROR('Model inputs'!B178=TRUE,FALSE),TRUE,IF(IFERROR('Model inputs'!B179=TRUE,FALSE),TRUE,IF(OR('Model inputs'!B178="",'Model inputs'!B179=""),"",OR('Model inputs'!B178,'Model inputs'!B179))))),1,0)) -> 0 | I27: =IF(IF(IF(ISERROR('Monthly operating and hiring fo'!I9<'Pricing and operating assumptio'!B16),'Monthly operating and hiring fo'!I9<'Pricing and operating assumptio'!B16,IF(OR('Monthly operating and hiring fo'!I9="",'Pricing and operating assumptio'!B16=""),"",'Monthly operating and hiring fo'!I9<'Pricing and operating assumptio'!B16))="",FALSE,IF(ISERROR('Monthly operating and hiring fo'!I9<'Pricing and operating assumptio'!B16),'Monthly operating and hiring fo'!I9<'Pricing and operating assumptio'!B16,IF(OR('Monthly operating and hiring fo'!I9="",'Pricing and operating assumptio'!B16=""),"",'Monthly operating and hiring fo'!I9<'Pricing and operating assumptio'!B16))),0,IF(IF(IF(IFERROR('Model inputs'!B180=TRUE,FALSE),TRUE,IF(IFERROR('Model inputs'!B181=TRUE,FALSE),TRUE,IF(OR('Model inputs'!B180="",'Model inputs'!B181=""),"",OR('Model inputs'!B180,'Model inputs'!B181))))="",FALSE,IF(IFERROR('Model inputs'!B180=TRUE,FALSE),TRUE,IF(IFERROR('Model inputs'!B181=TRUE,FALSE),TRUE,IF(OR('Model inputs'!B180="",'Model inputs'!B181=""),"",OR('Model inputs'!B180,'Model inputs'!B181))))),1,0)) -> 0 | J27: =IF(IF(IF(ISERROR('Monthly operating and hiring fo'!J9<'Pricing and operating assumptio'!B16),'Monthly operating and hiring fo'!J9<'Pricing and operating assumptio'!B16,IF(OR('Monthly operating and hiring fo'!J9="",'Pricing and operating assumptio'!B16=""),"",'Monthly operating and hiring fo'!J9<'Pricing and operating assumptio'!B16))="",FALSE,IF(ISERROR('Monthly operating and hiring fo'!J9<'Pricing and operating assumptio'!B16),'Monthly operating and hiring fo'!J9<'Pricing and operating assumptio'!B16,IF(OR('Monthly operating and hiring fo'!J9="",'Pricing and operating assumptio'!B16=""),"",'Monthly operating and hiring fo'!J9<'Pricing and operating assumptio'!B16))),0,IF(IF(IF(IFERROR('Model inputs'!B182=TRUE,FALSE),TRUE,IF(IFERROR('Model inputs'!B183=TRUE,FALSE),TRUE,IF(OR('Model inputs'!B182="",'Model inputs'!B183=""),"",OR('Model inputs'!B182,'Model inputs'!B183))))="",FALSE,IF(IFERROR('Model inputs'!B182=TRUE,FALSE),TRUE,IF(IFERROR('Model inputs'!B183=TRUE,FALSE),TRUE,IF(OR('Model inputs'!B182="",'Model inputs'!B183=""),"",OR('Model inputs'!B182,'Model inputs'!B183))))),1,0)) -> 0 | K27: =IF(IF(IF(ISERROR('Monthly operating and hiring fo'!K9<'Pricing and operating assumptio'!B16),'Monthly operating and hiring fo'!K9<'Pricing and operating assumptio'!B16,IF(OR('Monthly operating and hiring fo'!K9="",'Pricing and operating assumptio'!B16=""),"",'Monthly operating and hiring fo'!K9<'Pricing and operating assumptio'!B16))="",FALSE,IF(ISERROR('Monthly operating and hiring fo'!K9<'Pricing and operating assumptio'!B16),'Monthly operating and hiring fo'!K9<'Pricing and operating assumptio'!B16,IF(OR('Monthly operating and hiring fo'!K9="",'Pricing and operating assumptio'!B16=""),"",'Monthly operating and hiring fo'!K9<'Pricing and operating assumptio'!B16))),0,IF(IF(IF(IFERROR('Model inputs'!B184=TRUE,FALSE),TRUE,IF(IFERROR('Model inputs'!B185=TRUE,FALSE),TRUE,IF(OR('Model inputs'!B184="",'Model inputs'!B185=""),"",OR('Model inputs'!B184,'Model inputs'!B185))))="",FALSE,IF(IFERROR('Model inputs'!B184=TRUE,FALSE),TRUE,IF(IFERROR('Model inputs'!B185=TRUE,FALSE),TRUE,IF(OR('Model inputs'!B184="",'Model inputs'!B185=""),"",OR('Model inputs'!B184,'Model inputs'!B185))))),1,0)) -> 0 | L27: =IF(IF(IF(ISERROR('Monthly operating and hiring fo'!L9<'Pricing and operating assumptio'!B16),'Monthly operating and hiring fo'!L9<'Pricing and operating assumptio'!B16,IF(OR('Monthly operating and hiring fo'!L9="",'Pricing and operating assumptio'!B16=""),"",'Monthly operating and hiring fo'!L9<'Pricing and operating assumptio'!B16))="",FALSE,IF(ISERROR('Monthly operating and hiring fo'!L9<'Pricing and operating assumptio'!B16),'Monthly operating and hiring fo'!L9<'Pricing and operating assumptio'!B16,IF(OR('Monthly operating and hiring fo'!L9="",'Pricing and operating assumptio'!B16=""),"",'Monthly operating and hiring fo'!L9<'Pricing and operating assumptio'!B16))),0,IF(IF(IF(IFERROR('Model inputs'!B186=TRUE,FALSE),TRUE,IF(IFERROR('Model inputs'!B187=TRUE,FALSE),TRUE,IF(OR('Model inputs'!B186="",'Model inputs'!B187=""),"",OR('Model inputs'!B186,'Model inputs'!B187))))="",FALSE,IF(IFERROR('Model inputs'!B186=TRUE,FALSE),TRUE,IF(IFERROR('Model inputs'!B187=TRUE,FALSE),TRUE,IF(OR('Model inputs'!B186="",'Model inputs'!B187=""),"",OR('Model inputs'!B186,'Model inputs'!B187))))),1,0)) -> 0 | M27: =IF(IF(IF(ISERROR('Monthly operating and hiring fo'!M9<'Pricing and operating assumptio'!B16),'Monthly operating and hiring fo'!M9<'Pricing and operating assumptio'!B16,IF(OR('Monthly operating and hiring fo'!M9="",'Pricing and operating assumptio'!B16=""),"",'Monthly operating and hiring fo'!M9<'Pricing and operating assumptio'!B16))="",FALSE,IF(ISERROR('Monthly operating and hiring fo'!M9<'Pricing and operating assumptio'!B16),'Monthly operating and hiring fo'!M9<'Pricing and operating assumptio'!B16,IF(OR('Monthly operating and hiring fo'!M9="",'Pricing and operating assumptio'!B16=""),"",'Monthly operating and hiring fo'!M9<'Pricing and operating assumptio'!B16))),0,IF(IF(IF(IFERROR('Model inputs'!B188=TRUE,FALSE),TRUE,IF(IFERROR('Model inputs'!B189=TRUE,FALSE),TRUE,IF(OR('Model inputs'!B188="",'Model inputs'!B189=""),"",OR('Model inputs'!B188,'Model inputs'!B189))))="",FALSE,IF(IFERROR('Model inputs'!B188=TRUE,FALSE),TRUE,IF(IFERROR('Model inputs'!B189=TRUE,FALSE),TRUE,IF(OR('Model inputs'!B188="",'Model inputs'!B189=""),"",OR('Model inputs'!B188,'Model inputs'!B189))))),1,0)) -> 0
A28: Engineer cost | B28: ='Monthly operating and hiring fo'!B27*'Pricing and operating assumptio'!B15 -> 0 | C28: ='Monthly operating and hiring fo'!C27*'Pricing and operating assumptio'!B15 -> 0 | D28: ='Monthly operating and hiring fo'!D27*'Pricing and operating assumptio'!B15 -> 0 | E28: ='Monthly operating and hiring fo'!E27*'Pricing and operating assumptio'!B15 -> 0 | F28: ='Monthly operating and hiring fo'!F27*'Pricing and operating assumptio'!B15 -> 0 | G28: ='Monthly operating and hiring fo'!G27*'Pricing and operating assumptio'!B15 -> 0 | H28: ='Monthly operating and hiring fo'!H27*'Pricing and operating assumptio'!B15 -> 0 | I28: ='Monthly operating and hiring fo'!I27*'Pricing and operating assumptio'!B15 -> 0 | J28: ='Monthly operating and hiring fo'!J27*'Pricing and operating assumptio'!B15 -> 0 | K28: ='Monthly operating and hiring fo'!K27*'Pricing and operating assumptio'!B15 -> 0 | L28: ='Monthly operating and hiring fo'!L27*'Pricing and operating assumptio'!B15 -> 0 | M28: ='Monthly operating and hiring fo'!M27*'Pricing and operating assumptio'!B15 -> 0
A29: Operating cash flow | B29: ='Monthly operating and hiring fo'!B23-'Monthly operating and hiring fo'!B28 -> -154.5 | C29: ='Monthly operating and hiring fo'!C23-'Monthly operating and hiring fo'!C28 -> 25 | D29: ='Monthly operating and hiring fo'!D23-'Monthly operating and hiring fo'!D28 -> 203 | E29: ='Monthly operating and hiring fo'!E23-'Monthly operating and hiring fo'!E28 -> 387 | F29: ='Monthly operating and hiring fo'!F23-'Monthly operating and hiring fo'!F28 -> 571 | G29: ='Monthly operating and hiring fo'!G23-'Monthly operating and hiring fo'!G28 -> 755 | H29: ='Monthly operating and hiring fo'!H23-'Monthly operating and hiring fo'!H28 -> -2693 | I29: ='Monthly operating and hiring fo'!I23-'Monthly operating and hiring fo'!I28 -> -2141 | ... M29: ='Monthly operating and hiring fo'!M23-'Monthly operating and hiring fo'!M28 -> 1355
A30: Cumulative operating cash | B30: =IF(IF(IF(ISERROR('Monthly operating and hiring fo'!B9=1),'Monthly operating and hiring fo'!B9=1,IF('Monthly operating and hiring fo'!B9="","",'Monthly operating and hiring fo'!B9=1))="",FALSE,IF(ISERROR('Monthly operating and hiring fo'!B9=1),'Monthly operating and hiring fo'!B9=1,IF('Monthly operating and hiring fo'!B9="","",'Monthly operating and hiring fo'!B9=1))),IF('Monthly operating and hiring fo'!B29="","",'Monthly operating and hiring fo'!B29),'Model inputs'!B15+'Monthly operating and hiring fo'!B29) -> -154.5 | C30: =IF(IF(IF(ISERROR('Monthly operating and hiring fo'!C9=1),'Monthly operating and hiring fo'!C9=1,IF('Monthly operating and hiring fo'!C9="","",'Monthly operating and hiring fo'!C9=1))="",FALSE,IF(ISERROR('Monthly operating and hiring fo'!C9=1),'Monthly operating and hiring fo'!C9=1,IF('Monthly operating and hiring fo'!C9="","",'Monthly operating and hiring fo'!C9=1))),IF('Monthly operating and hiring fo'!C29="","",'Monthly operating and hiring fo'!C29),'Monthly operating and hiring fo'!B30+'Monthly operating and hiring fo'!C29) -> -129.5 | D30: =IF(IF(IF(ISERROR('Monthly operating and hiring fo'!D9=1),'Monthly operating and hiring fo'!D9=1,IF('Monthly operating and hiring fo'!D9="","",'Monthly operating and hiring fo'!D9=1))="",FALSE,IF(ISERROR('Monthly operating and hiring fo'!D9=1),'Monthly operating and hiring fo'!D9=1,IF('Monthly operating and hiring fo'!D9="","",'Monthly operating and hiring fo'!D9=1))),IF('Monthly operating and hiring fo'!D29="","",'Monthly operating and hiring fo'!D29),'Monthly operating and hiring fo'!C30+'Monthly operating and hiring fo'!D29) -> 73.5 | E30: =IF(IF(IF(ISERROR('Monthly operating and hiring fo'!E9=1),'Monthly operating and hiring fo'!E9=1,IF('Monthly operating and hiring fo'!E9="","",'Monthly operating and hiring fo'!E9=1))="",FALSE,IF(ISERROR('Monthly operating and hiring fo'!E9=1),'Monthly operating and hiring fo'!E9=1,IF('Monthly operating and hiring fo'!E9="","",'Monthly operating and hiring fo'!E9=1))),IF('Monthly operating and hiring fo'!E29="","",'Monthly operating and hiring fo'!E29),'Monthly operating and hiring fo'!D30+'Monthly operating and hiring fo'!E29) -> 460.5 | F30: =IF(IF(IF(ISERROR('Monthly operating and hiring fo'!F9=1),'Monthly operating and hiring fo'!F9=1,IF('Monthly operating and hiring fo'!F9="","",'Monthly operating and hiring fo'!F9=1))="",FALSE,IF(ISERROR('Monthly operating and hiring fo'!F9=1),'Monthly operating and hiring fo'!F9=1,IF('Monthly operating and hiring fo'!F9="","",'Monthly operating and hiring fo'!F9=1))),IF('Monthly operating and hiring fo'!F29="","",'Monthly operating and hiring fo'!F29),'Monthly operating and hiring fo'!E30+'Monthly operating and hiring fo'!F29) -> 1031.5 | G30: =IF(IF(IF(ISERROR('Monthly operating and hiring fo'!G9=1),'Monthly operating and hiring fo'!G9=1,IF('Monthly operating and hiring fo'!G9="","",'Monthly operating and hiring fo'!G9=1))="",FALSE,IF(ISERROR('Monthly operating and hiring fo'!G9=1),'Monthly operating and hiring fo'!G9=1,IF('Monthly operating and hiring fo'!G9="","",'Monthly operating and hiring fo'!G9=1))),IF('Monthly operating and hiring fo'!G29="","",'Monthly operating and hiring fo'!G29),'Monthly operating and hiring fo'!F30+'Monthly operating and hiring fo'!G29) -> 1786.5 | H30: =IF(IF(IF(ISERROR('Monthly operating and hiring fo'!H9=1),'Monthly operating and hiring fo'!H9=1,IF('Monthly operating and hiring fo'!H9="","",'Monthly operating and hiring fo'!H9=1))="",FALSE,IF(ISERROR('Monthly operating and hiring fo'!H9=1),'Monthly operating and hiring fo'!H9=1,IF('Monthly operating and hiring fo'!H9="","",'Monthly operating and hiring fo'!H9=1))),IF('Monthly operating and hiring fo'!H29="","",'Monthly operating and hiring fo'!H29),'Monthly operating and hiring fo'!G30+'Monthly operating and hiring fo'!H29) -> -906.5 | I30: =IF(IF(IF(ISERROR('Monthly operating and hiring fo'!I9=1),'Monthly operating and hiring fo'!I9=1,IF('Monthly operating and hiring fo'!I9="","",'Monthly operating and hiring fo'!I9=1))="",FALSE,IF(ISERROR('Monthly operating and hiring fo'!I9=1),'Monthly operating and hiring fo'!I9=1,IF('Monthly operating and hiring fo'!I9="","",'Monthly operating and hiring fo'!I9=1))),IF('Monthly operating and hiring fo'!I29="","",'Monthly operating and hiring fo'!I29),'Monthly operating and hiring fo'!H30+'Monthly operating and hiring fo'!I29) -> -3047.5 | J30: =IF(IF(IF(ISERROR('Monthly operating and hiring fo'!J9=1),'Monthly operating and hiring fo'!J9=1,IF('Monthly operating and hiring fo'!J9="","",'Monthly operating and hiring fo'!J9=1))="",FALSE,IF(ISERROR('Monthly operating and hiring fo'!J9=1),'Monthly operating and hiring fo'!J9=1,IF('Monthly operating and hiring fo'!J9="","",'Monthly operating and hiring fo'!J9=1))),IF('Monthly operating and hiring fo'!J29="","",'Monthly operating and hiring fo'!J29),'Monthly operating and hiring fo'!I30+'Monthly operating and hiring fo'!J29) -> -4452.5 | ... M30: =IF(IF(IF(ISERROR('Monthly operating and hiring fo'!M9=1),'Monthly operating and hiring fo'!M9=1,IF('Monthly operating and hiring fo'!M9="","",'Monthly operating and hiring fo'!M9=1))="",FALSE,IF(ISERROR('Monthly operating and hiring fo'!M9=1),'Monthly operating and hiring fo'!M9=1,IF('Monthly operating and hiring fo'!M9="","",'Monthly operating and hiring fo'!M9=1))),IF('Monthly operating and hiring fo'!M29="","",'Monthly operating and hiring fo'!M29),'Monthly operating and hiring fo'!L30+'Monthly operating and hiring fo'!M29) -> -3147.5
A31: Minimum funding to date | B31: =IF(IF(IF(ISERROR('Monthly operating and hiring fo'!B9=1),'Monthly operating and hiring fo'!B9=1,IF('Monthly operating and hiring fo'!B9="","",'Monthly operating and hiring fo'!B9=1))="",FALSE,IF(ISERROR('Monthly operating and hiring fo'!B9=1),'Monthly operating and hiring fo'!B9=1,IF('Monthly operating and hiring fo'!B9="","",'Monthly operating and hiring fo'!B9=1))),MAX(0,-'Monthly operating and hiring fo'!B30),MAX(0,-'Monthly operating and hiring fo'!B30,'Model inputs'!B44)) -> 154.5 | C31: =IF(IF(IF(ISERROR('Monthly operating and hiring fo'!C9=1),'Monthly operating and hiring fo'!C9=1,IF('Monthly operating and hiring fo'!C9="","",'Monthly operating and hiring fo'!C9=1))="",FALSE,IF(ISERROR('Monthly operating and hiring fo'!C9=1),'Monthly operating and hiring fo'!C9=1,IF('Monthly operating and hiring fo'!C9="","",'Monthly operating and hiring fo'!C9=1))),MAX(0,-'Monthly operating and hiring fo'!C30),MAX(0,-'Monthly operating and hiring fo'!C30,'Monthly operating and hiring fo'!B31)) -> 154.5 | D31: =IF(IF(IF(ISERROR('Monthly operating and hiring fo'!D9=1),'Monthly operating and hiring fo'!D9=1,IF('Monthly operating and hiring fo'!D9="","",'Monthly operating and hiring fo'!D9=1))="",FALSE,IF(ISERROR('Monthly operating and hiring fo'!D9=1),'Monthly operating and hiring fo'!D9=1,IF('Monthly operating and hiring fo'!D9="","",'Monthly operating and hiring fo'!D9=1))),MAX(0,-'Monthly operating and hiring fo'!D30),MAX(0,-'Monthly operating and hiring fo'!D30,'Monthly operating and hiring fo'!C31)) -> 154.5 | E31: =IF(IF(IF(ISERROR('Monthly operating and hiring fo'!E9=1),'Monthly operating and hiring fo'!E9=1,IF('Monthly operating and hiring fo'!E9="","",'Monthly operating and hiring fo'!E9=1))="",FALSE,IF(ISERROR('Monthly operating and hiring fo'!E9=1),'Monthly operating and hiring fo'!E9=1,IF('Monthly operating and hiring fo'!E9="","",'Monthly operating and hiring fo'!E9=1))),MAX(0,-'Monthly operating and hiring fo'!E30),MAX(0,-'Monthly operating and hiring fo'!E30,'Monthly operating and hiring fo'!D31)) -> 154.5 | F31: =IF(IF(IF(ISERROR('Monthly operating and hiring fo'!F9=1),'Monthly operating and hiring fo'!F9=1,IF('Monthly operating and hiring fo'!F9="","",'Monthly operating and hiring fo'!F9=1))="",FALSE,IF(ISERROR('Monthly operating and hiring fo'!F9=1),'Monthly operating and hiring fo'!F9=1,IF('Monthly operating and hiring fo'!F9="","",'Monthly operating and hiring fo'!F9=1))),MAX(0,-'Monthly operating and hiring fo'!F30),MAX(0,-'Monthly operating and hiring fo'!F30,'Monthly operating and hiring fo'!E31)) -> 154.5 | G31: =IF(IF(IF(ISERROR('Monthly operating and hiring fo'!G9=1),'Monthly operating and hiring fo'!G9=1,IF('Monthly operating and hiring fo'!G9="","",'Monthly operating and hiring fo'!G9=1))="",FALSE,IF(ISERROR('Monthly operating and hiring fo'!G9=1),'Monthly operating and hiring fo'!G9=1,IF('Monthly operating and hiring fo'!G9="","",'Monthly operating and hiring fo'!G9=1))),MAX(0,-'Monthly operating and hiring fo'!G30),MAX(0,-'Monthly operating and hiring fo'!G30,'Monthly operating and hiring fo'!F31)) -> 154.5 | H31: =IF(IF(IF(ISERROR('Monthly operating and hiring fo'!H9=1),'Monthly operating and hiring fo'!H9=1,IF('Monthly operating and hiring fo'!H9="","",'Monthly operating and hiring fo'!H9=1))="",FALSE,IF(ISERROR('Monthly operating and hiring fo'!H9=1),'Monthly operating and hiring fo'!H9=1,IF('Monthly operating and hiring fo'!H9="","",'Monthly operating and hiring fo'!H9=1))),MAX(0,-'Monthly operating and hiring fo'!H30),MAX(0,-'Monthly operating and hiring fo'!H30,'Monthly operating and hiring fo'!G31)) -> 906.5 | I31: =IF(IF(IF(ISERROR('Monthly operating and hiring fo'!I9=1),'Monthly operating and hiring fo'!I9=1,IF('Monthly operating and hiring fo'!I9="","",'Monthly operating and hiring fo'!I9=1))="",FALSE,IF(ISERROR('Monthly operating and hiring fo'!I9=1),'Monthly operating and hiring fo'!I9=1,IF('Monthly operating and hiring fo'!I9="","",'Monthly operating and hiring fo'!I9=1))),MAX(0,-'Monthly operating and hiring fo'!I30),MAX(0,-'Monthly operating and hiring fo'!I30,'Monthly operating and hiring fo'!H31)) -> 3047.5 | J31: =IF(IF(IF(ISERROR('Monthly operating and hiring fo'!J9=1),'Monthly operating and hiring fo'!J9=1,IF('Monthly operating and hiring fo'!J9="","",'Monthly operating and hiring fo'!J9=1))="",FALSE,IF(ISERROR('Monthly operating and hiring fo'!J9=1),'Monthly operating and hiring fo'!J9=1,IF('Monthly operating and hiring fo'!J9="","",'Monthly operating and hiring fo'!J9=1))),MAX(0,-'Monthly operating and hiring fo'!J30),MAX(0,-'Monthly operating and hiring fo'!J30,'Monthly operating and hiring fo'!I31)) -> 4452.5 | ... M31: =IF(IF(IF(ISERROR('Monthly operating and hiring fo'!M9=1),'Monthly operating and hiring fo'!M9=1,IF('Monthly operating and hiring fo'!M9="","",'Monthly operating and hiring fo'!M9=1))="",FALSE,IF(ISERROR('Monthly operating and hiring fo'!M9=1),'Monthly operating and hiring fo'!M9=1,IF('Monthly operating and hiring fo'!M9="","",'Monthly operating and hiring fo'!M9=1))),MAX(0,-'Monthly operating and hiring fo'!M30),MAX(0,-'Monthly operating and hiring fo'!M30,'Monthly operating and hiring fo'!L31)) -> 4937.5
A32: Minimum fix price at target margin | B32: ='Pricing and operating assumptio'!B9/(1-'Pricing and operating assumptio'!B10) -> 5 | C32: ='Pricing and operating assumptio'!B9/(1-'Pricing and operating assumptio'!B10) -> 5 | D32: ='Pricing and operating assumptio'!B9/(1-'Pricing and operating assumptio'!B10) -> 5 | E32: ='Pricing and operating assumptio'!B9/(1-'Pricing and operating assumptio'!B10) -> 5 | F32: ='Pricing and operating assumptio'!B9/(1-'Pricing and operating assumptio'!B10) -> 5 | G32: ='Pricing and operating assumptio'!B9/(1-'Pricing and operating assumptio'!B10) -> 5 | H32: ='Pricing and operating assumptio'!B9/(1-'Pricing and operating assumptio'!B10) -> 5 | I32: ='Pricing and operating assumptio'!B9/(1-'Pricing and operating assumptio'!B10) -> 5 | J32: ='Pricing and operating assumptio'!B9/(1-'Pricing and operating assumptio'!B10) -> 5 | K32: ='Pricing and operating assumptio'!B9/(1-'Pricing and operating assumptio'!B10) -> 5 | L32: ='Pricing and operating assumptio'!B9/(1-'Pricing and operating assumptio'!B10) -> 5 | M32: ='Pricing and operating assumptio'!B9/(1-'Pricing and operating assumptio'!B10) -> 5
A33: Full allowance team margin | B33: =1-'Pricing and operating assumptio'!B6*'Pricing and operating assumptio'!B9/'Pricing and operating assumptio'!B5 -> 0.92462312 | C33: =1-'Pricing and operating assumptio'!B6*'Pricing and operating assumptio'!B9/'Pricing and operating assumptio'!B5 -> 0.92462312 | D33: =1-'Pricing and operating assumptio'!B6*'Pricing and operating assumptio'!B9/'Pricing and operating assumptio'!B5 -> 0.92462312 | E33: =1-'Pricing and operating assumptio'!B6*'Pricing and operating assumptio'!B9/'Pricing and operating assumptio'!B5 -> 0.92462312 | F33: =1-'Pricing and operating assumptio'!B6*'Pricing and operating assumptio'!B9/'Pricing and operating assumptio'!B5 -> 0.92462312 | G33: =1-'Pricing and operating assumptio'!B6*'Pricing and operating assumptio'!B9/'Pricing and operating assumptio'!B5 -> 0.92462312 | H33: =1-'Pricing and operating assumptio'!B6*'Pricing and operating assumptio'!B9/'Pricing and operating assumptio'!B5 -> 0.92462312 | I33: =1-'Pricing and operating assumptio'!B6*'Pricing and operating assumptio'!B9/'Pricing and operating assumptio'!B5 -> 0.92462312 | J33: =1-'Pricing and operating assumptio'!B6*'Pricing and operating assumptio'!B9/'Pricing and operating assumptio'!B5 -> 0.92462312 | K33: =1-'Pricing and operating assumptio'!B6*'Pricing and operating assumptio'!B9/'Pricing and operating assumptio'!B5 -> 0.92462312 | L33: =1-'Pricing and operating assumptio'!B6*'Pricing and operating assumptio'!B9/'Pricing and operating assumptio'!B5 -> 0.92462312 | M33: =1-'Pricing and operating assumptio'!B6*'Pricing and operating assumptio'!B9/'Pricing and operating assumptio'!B5 -> 0.92462312
A34: Pay per fix gross margin | B34: =1-'Pricing and operating assumptio'!B9/'Pricing and operating assumptio'!B8 -> 0.96938776 | C34: =1-'Pricing and operating assumptio'!B9/'Pricing and operating assumptio'!B8 -> 0.96938776 | D34: =1-'Pricing and operating assumptio'!B9/'Pricing and operating assumptio'!B8 -> 0.96938776 | E34: =1-'Pricing and operating assumptio'!B9/'Pricing and operating assumptio'!B8 -> 0.96938776 | F34: =1-'Pricing and operating assumptio'!B9/'Pricing and operating assumptio'!B8 -> 0.96938776 | G34: =1-'Pricing and operating assumptio'!B9/'Pricing and operating assumptio'!B8 -> 0.96938776 | H34: =1-'Pricing and operating assumptio'!B9/'Pricing and operating assumptio'!B8 -> 0.96938776 | I34: =1-'Pricing and operating assumptio'!B9/'Pricing and operating assumptio'!B8 -> 0.96938776 | J34: =1-'Pricing and operating assumptio'!B9/'Pricing and operating assumptio'!B8 -> 0.96938776 | K34: =1-'Pricing and operating assumptio'!B9/'Pricing and operating assumptio'!B8 -> 0.96938776 | L34: =1-'Pricing and operating assumptio'!B9/'Pricing and operating assumptio'!B8 -> 0.96938776 | M34: =1-'Pricing and operating assumptio'!B9/'Pricing and operating assumptio'!B8 -> 0.96938776

Sheet Scenario comparison
A1: Scenario comparison
A2: Wincheck | 12-month plan · Main Scenario
A4: Variable / dimension | B4: 2026-10 | C4: 2026-10 > Upside | D4: 2026-10 > Downside | E4: 2026-11 | F4: 2026-11 > Upside | G4: 2026-11 > Downside | H4: 2026-12 | I4: 2026-12 > Upside | J4: 2026-12 > Downside | K4: 2027-01 | L4: 2027-01 > Upside | M4: 2027-01 > Downside | N4: 2027-02 | O4: 2027-02 > Upside | P4: 2027-02 > Downside | Q4: 2027-03 | R4: 2027-03 > Upside | S4: 2027-03 > Downside | T4: 2027-04 | U4: 2027-04 > Upside | V4: 2027-04 > Downside | W4: 2027-05 | X4: 2027-05 > Upside | Y4: 2027-05 > Downside | Z4: 2027-06 | AA4: 2027-06 > Upside | AB4: 2027-06 > Downside | AC4: 2027-07 | AD4: 2027-07 > Upside | AE4: 2027-07 > Downside | AF4: 2027-08 | AG4: 2027-08 > Upside | AH4: 2027-08 > Downside | AI4: 2027-09 | AJ4: 2027-09 > Upside | AK4: 2027-09 > Downside
A5: Paying teams | B5: ='Monthly operating and hiring fo'!B5 -> 0 | C5: =1 -> 1 | D5: ='Monthly operating and hiring fo'!B5 -> 0 | E5: ='Monthly operating and hiring fo'!C5 -> 1 | F5: =2 -> 2 | G5: =0 -> 0 | H5: ='Monthly operating and hiring fo'!D5 -> 2 | I5: =4 -> 4 | J5: =1 -> 1 | K5: ='Monthly operating and hiring fo'!E5 -> 3 | L5: =6 -> 6 | M5: =1 -> 1 | N5: ='Monthly operating and hiring fo'!F5 -> 4 | O5: =9 -> 9 | P5: =2 -> 2 | Q5: ='Monthly operating and hiring fo'!G5 -> 5 | R5: =12 -> 12 | S5: =2 -> 2 | T5: ='Monthly operating and hiring fo'!H5 -> 8 | U5: =17 -> 17 | V5: =3 -> 3 | W5: ='Monthly operating and hiring fo'!I5 -> 11 | X5: =23 -> 23 | Y5: =4 -> 4 | Z5: ='Monthly operating and hiring fo'!J5 -> 15 | AA5: =30 -> 30 | AB5: =5 -> 5 | AC5: ='Monthly operating and hiring fo'!K5 -> 20 | AD5: =40 -> 40 | AE5: =7 -> 7 | AF5: ='Monthly operating and hiring fo'!L5 -> 25 | AG5: =50 -> 50 | AH5: =9 -> 9 | AI5: ='Monthly operating and hiring fo'!M5 -> 30 | AJ5: =60 -> 60 | AK5: =12 -> 12
A6: Revenue | B6: ='Monthly operating and hiring fo'!B13+'Monthly operating and hiring fo'!B14+'Monthly operating and hiring fo'!B15 -> 0 | C6: ='Model inputs'!C66+'Model inputs'!C29+'Model inputs'!C56 -> 199 | D6: ='Model inputs'!C67+'Model inputs'!C30+'Model inputs'!C57 -> 0 | E6: ='Monthly operating and hiring fo'!C13+'Monthly operating and hiring fo'!C14+'Monthly operating and hiring fo'!C15 -> 199 | F6: ='Model inputs'!D66+'Model inputs'!D29+'Model inputs'!D56 -> 398 | G6: ='Model inputs'!D67+'Model inputs'!D30+'Model inputs'!D57 -> 0 | H6: ='Monthly operating and hiring fo'!D13+'Monthly operating and hiring fo'!D14+'Monthly operating and hiring fo'!D15 -> 398 | I6: ='Model inputs'!E66+'Model inputs'!E29+'Model inputs'!E56 -> 796 | J6: ='Model inputs'!E67+'Model inputs'!E30+'Model inputs'!E57 -> 199 | K6: ='Monthly operating and hiring fo'!E13+'Monthly operating and hiring fo'!E14+'Monthly operating and hiring fo'!E15 -> 597 | L6: ='Model inputs'!F66+'Model inputs'!F29+'Model inputs'!F56 -> 1194 | M6: ='Model inputs'!F67+'Model inputs'!F30+'Model inputs'!F57 -> 199 | N6: ='Monthly operating and hiring fo'!F13+'Monthly operating and hiring fo'!F14+'Monthly operating and hiring fo'!F15 -> 796 | O6: ='Model inputs'!G66+'Model inputs'!G29+'Model inputs'!G56 -> 1791 | P6: ='Model inputs'!G67+'Model inputs'!G30+'Model inputs'!G57 -> 398 | Q6: ='Monthly operating and hiring fo'!G13+'Monthly operating and hiring fo'!G14+'Monthly operating and hiring fo'!G15 -> 995 | R6: ='Model inputs'!H66+'Model inputs'!H29+'Model inputs'!H56 -> 2388 | S6: ='Model inputs'!H67+'Model inputs'!H30+'Model inputs'!H57 -> 398 | T6: ='Monthly operating and hiring fo'!H13+'Monthly operating and hiring fo'!H14+'Monthly operating and hiring fo'!H15 -> 1592 | U6: ='Model inputs'!I66+'Model inputs'!I29+'Model inputs'!I56 -> 3383 | V6: ='Model inputs'!I67+'Model inputs'!I30+'Model inputs'!I57 -> 597 | W6: ='Monthly operating and hiring fo'!I13+'Monthly operating and hiring fo'!I14+'Monthly operating and hiring fo'!I15 -> 2189 | X6: ='Model inputs'!J66+'Model inputs'!J29+'Model inputs'!J56 -> 4577 | Y6: ='Model inputs'!J67+'Model inputs'!J30+'Model inputs'!J57 -> 796 | Z6: ='Monthly operating and hiring fo'!J13+'Monthly operating and hiring fo'!J14+'Monthly operating and hiring fo'!J15 -> 2985 | AA6: ='Model inputs'!K66+'Model inputs'!K29+'Model inputs'!K56 -> 5970 | AB6: ='Model inputs'!K67+'Model inputs'!K30+'Model inputs'!K57 -> 995 | AC6: ='Monthly operating and hiring fo'!K13+'Monthly operating and hiring fo'!K14+'Monthly operating and hiring fo'!K15 -> 3980 | AD6: ='Model inputs'!L66+'Model inputs'!L29+'Model inputs'!L56 -> 7960 | AE6: ='Model inputs'!L67+'Model inputs'!L30+'Model inputs'!L57 -> 1393 | AF6: ='Monthly operating and hiring fo'!L13+'Monthly operating and hiring fo'!L14+'Monthly operating and hiring fo'!L15 -> 4975 | AG6: ='Model inputs'!M66+'Model inputs'!M29+'Model inputs'!M56 -> 9950 | AH6: ='Model inputs'!M67+'Model inputs'!M30+'Model inputs'!M57 -> 1791 | AI6: ='Monthly operating and hiring fo'!M13+'Monthly operating and hiring fo'!M14+'Monthly operating and hiring fo'!M15 -> 5970 | AJ6: ='Model inputs'!N66+'Model inputs'!N29+'Model inputs'!N56 -> 11940 | AK6: ='Model inputs'!N67+'Model inputs'!N30+'Model inputs'!N57 -> 2388
A7: Operating cash flow | B7: ='Monthly operating and hiring fo'!B23-'Monthly operating and hiring fo'!B28 -> -154.5 | C7: ='Model inputs'!C7-'Model inputs'!C22 -> 29.5 | D7: ='Model inputs'!C8-'Model inputs'!C23 -> -154.5 | E7: ='Monthly operating and hiring fo'!C23-'Monthly operating and hiring fo'!C28 -> 25 | F7: ='Model inputs'!D7-'Model inputs'!D22 -> 209 | G7: ='Model inputs'!D8-'Model inputs'!D23 -> -159 | H7: ='Monthly operating and hiring fo'!D23-'Monthly operating and hiring fo'!D28 -> 203 | I7: ='Model inputs'!E7-'Model inputs'!E22 -> 571 | J7: ='Model inputs'!E8-'Model inputs'!E23 -> 19 | K7: ='Monthly operating and hiring fo'!E23-'Monthly operating and hiring fo'!E28 -> 387 | L7: ='Model inputs'!F7-'Model inputs'!F22 -> 939 | M7: ='Model inputs'!F8-'Model inputs'!F23 -> 19 | N7: ='Monthly operating and hiring fo'!F23-'Monthly operating and hiring fo'!F28 -> 571 | O7: ='Model inputs'!G7-'Model inputs'!G22 -> 1491 | P7: ='Model inputs'!G8-'Model inputs'!G23 -> 203 | Q7: ='Monthly operating and hiring fo'!G23-'Monthly operating and hiring fo'!G28 -> 755 | R7: ='Model inputs'!H7-'Model inputs'!H22 -> 2043 | S7: ='Model inputs'!H8-'Model inputs'!H23 -> 203 | T7: ='Monthly operating and hiring fo'!H23-'Monthly operating and hiring fo'!H28 -> -2693 | U7: ='Model inputs'!I7-'Model inputs'!I22 -> -1037 | V7: ='Model inputs'!I8-'Model inputs'!I23 -> -3613 | W7: ='Monthly operating and hiring fo'!I23-'Monthly operating and hiring fo'!I28 -> -2141 | X7: ='Model inputs'!J7-'Model inputs'!J22 -> 67 | Y7: ='Model inputs'!J8-'Model inputs'!J23 -> -3429 | Z7: ='Monthly operating and hiring fo'!J23-'Monthly operating and hiring fo'!J28 -> -1405 | AA7: ='Model inputs'!K7-'Model inputs'!K22 -> 1355 | AB7: ='Model inputs'!K8-'Model inputs'!K23 -> -3245 | AC7: ='Monthly operating and hiring fo'!K23-'Monthly operating and hiring fo'!K28 -> -485 | AD7: ='Model inputs'!L7-'Model inputs'!L22 -> 3195 | AE7: ='Model inputs'!L8-'Model inputs'!L23 -> -2877 | AF7: ='Monthly operating and hiring fo'!L23-'Monthly operating and hiring fo'!L28 -> 435 | AG7: ='Model inputs'!M7-'Model inputs'!M22 -> 5035 | AH7: ='Model inputs'!M8-'Model inputs'!M23 -> -2509 | AI7: ='Monthly operating and hiring fo'!M23-'Monthly operating and hiring fo'!M28 -> 1355 | AJ7: ='Model inputs'!N7-'Model inputs'!N22 -> 875 | AK7: ='Model inputs'!N8-'Model inputs'!N23 -> -1957
A8: Engineer hired | B8: =IF(IF(IF(ISERROR('Monthly operating and hiring fo'!B9<'Pricing and operating assumptio'!B16),'Monthly operating and hiring fo'!B9<'Pricing and operating assumptio'!B16,IF(OR('Monthly operating and hiring fo'!B9="",'Pricing and operating assumptio'!B16=""),"",'Monthly operating and hiring fo'!B9<'Pricing and operating assumptio'!B16))="",FALSE,IF(ISERROR('Monthly operating and hiring fo'!B9<'Pricing and operating assumptio'!B16),'Monthly operating and hiring fo'!B9<'Pricing and operating assumptio'!B16,IF(OR('Monthly operating and hiring fo'!B9="",'Pricing and operating assumptio'!B16=""),"",'Monthly operating and hiring fo'!B9<'Pricing and operating assumptio'!B16))),0,IF(IF(IF(IFERROR(IF(ISERROR('Model inputs'!B24=1),'Model inputs'!B24=1,IF('Model inputs'!B24="","",'Model inputs'!B24=1))=TRUE,FALSE),TRUE,IF(IFERROR('Model inputs'!B167=TRUE,FALSE),TRUE,IF(OR(IF(ISERROR('Model inputs'!B24=1),'Model inputs'!B24=1,IF('Model inputs'!B24="","",'Model inputs'!B24=1))="",'Model inputs'!B167=""),"",OR(IF(ISERROR('Model inputs'!B24=1),'Model inputs'!B24=1,IF('Model inputs'!B24="","",'Model inputs'!B24=1)),'Model inputs'!B167))))="",FALSE,IF(IFERROR(IF(ISERROR('Model inputs'!B24=1),'Model inputs'!B24=1,IF('Model inputs'!B24="","",'Model inputs'!B24=1))=TRUE,FALSE),TRUE,IF(IFERROR('Model inputs'!B167=TRUE,FALSE),TRUE,IF(OR(IF(ISERROR('Model inputs'!B24=1),'Model inputs'!B24=1,IF('Model inputs'!B24="","",'Model inputs'!B24=1))="",'Model inputs'!B167=""),"",OR(IF(ISERROR('Model inputs'!B24=1),'Model inputs'!B24=1,IF('Model inputs'!B24="","",'Model inputs'!B24=1)),'Model inputs'!B167))))),1,0)) -> 0 | C8: =IF(IF(IF(ISERROR('Model inputs'!C60<'Model inputs'!O19),'Model inputs'!C60<'Model inputs'!O19,IF(OR('Model inputs'!C60="",'Model inputs'!O19=""),"",'Model inputs'!C60<'Model inputs'!O19))="",FALSE,IF(ISERROR('Model inputs'!C60<'Model inputs'!O19),'Model inputs'!C60<'Model inputs'!O19,IF(OR('Model inputs'!C60="",'Model inputs'!O19=""),"",'Model inputs'!C60<'Model inputs'!O19))),0,IF(IF(IF(IFERROR(IF(ISERROR('Model inputs'!B25=1),'Model inputs'!B25=1,IF('Model inputs'!B25="","",'Model inputs'!B25=1))=TRUE,FALSE),TRUE,IF(IFERROR('Model inputs'!B190=TRUE,FALSE),TRUE,IF(OR(IF(ISERROR('Model inputs'!B25=1),'Model inputs'!B25=1,IF('Model inputs'!B25="","",'Model inputs'!B25=1))="",'Model inputs'!B190=""),"",OR(IF(ISERROR('Model inputs'!B25=1),'Model inputs'!B25=1,IF('Model inputs'!B25="","",'Model inputs'!B25=1)),'Model inputs'!B190))))="",FALSE,IF(IFERROR(IF(ISERROR('Model inputs'!B25=1),'Model inputs'!B25=1,IF('Model inputs'!B25="","",'Model inputs'!B25=1))=TRUE,FALSE),TRUE,IF(IFERROR('Model inputs'!B190=TRUE,FALSE),TRUE,IF(OR(IF(ISERROR('Model inputs'!B25=1),'Model inputs'!B25=1,IF('Model inputs'!B25="","",'Model inputs'!B25=1))="",'Model inputs'!B190=""),"",OR(IF(ISERROR('Model inputs'!B25=1),'Model inputs'!B25=1,IF('Model inputs'!B25="","",'Model inputs'!B25=1)),'Model inputs'!B190))))),1,0)) -> 0 | D8: =IF(IF(IF(ISERROR('Model inputs'!C61<'Model inputs'!O20),'Model inputs'!C61<'Model inputs'!O20,IF(OR('Model inputs'!C61="",'Model inputs'!O20=""),"",'Model inputs'!C61<'Model inputs'!O20))="",FALSE,IF(ISERROR('Model inputs'!C61<'Model inputs'!O20),'Model inputs'!C61<'Model inputs'!O20,IF(OR('Model inputs'!C61="",'Model inputs'!O20=""),"",'Model inputs'!C61<'Model inputs'!O20))),0,IF(IF(IF(IFERROR(IF(ISERROR('Model inputs'!B26=1),'Model inputs'!B26=1,IF('Model inputs'!B26="","",'Model inputs'!B26=1))=TRUE,FALSE),TRUE,IF(IFERROR('Model inputs'!B191=TRUE,FALSE),TRUE,IF(OR(IF(ISERROR('Model inputs'!B26=1),'Model inputs'!B26=1,IF('Model inputs'!B26="","",'Model inputs'!B26=1))="",'Model inputs'!B191=""),"",OR(IF(ISERROR('Model inputs'!B26=1),'Model inputs'!B26=1,IF('Model inputs'!B26="","",'Model inputs'!B26=1)),'Model inputs'!B191))))="",FALSE,IF(IFERROR(IF(ISERROR('Model inputs'!B26=1),'Model inputs'!B26=1,IF('Model inputs'!B26="","",'Model inputs'!B26=1))=TRUE,FALSE),TRUE,IF(IFERROR('Model inputs'!B191=TRUE,FALSE),TRUE,IF(OR(IF(ISERROR('Model inputs'!B26=1),'Model inputs'!B26=1,IF('Model inputs'!B26="","",'Model inputs'!B26=1))="",'Model inputs'!B191=""),"",OR(IF(ISERROR('Model inputs'!B26=1),'Model inputs'!B26=1,IF('Model inputs'!B26="","",'Model inputs'!B26=1)),'Model inputs'!B191))))),1,0)) -> 0 | E8: =IF(IF(IF(ISERROR('Monthly operating and hiring fo'!C9<'Pricing and operating assumptio'!B16),'Monthly operating and hiring fo'!C9<'Pricing and operating assumptio'!B16,IF(OR('Monthly operating and hiring fo'!C9="",'Pricing and operating assumptio'!B16=""),"",'Monthly operating and hiring fo'!C9<'Pricing and operating assumptio'!B16))="",FALSE,IF(ISERROR('Monthly operating and hiring fo'!C9<'Pricing and operating assumptio'!B16),'Monthly operating and hiring fo'!C9<'Pricing and operating assumptio'!B16,IF(OR('Monthly operating and hiring fo'!C9="",'Pricing and operating assumptio'!B16=""),"",'Monthly operating and hiring fo'!C9<'Pricing and operating assumptio'!B16))),0,IF(IF(IF(IFERROR(IF(ISERROR('Scenario comparison'!B8=1),'Scenario comparison'!B8=1,IF('Scenario comparison'!B8="","",'Scenario comparison'!B8=1))=TRUE,FALSE),TRUE,IF(IFERROR('Model inputs'!B169=TRUE,FALSE),TRUE,IF(OR(IF(ISERROR('Scenario comparison'!B8=1),'Scenario comparison'!B8=1,IF('Scenario comparison'!B8="","",'Scenario comparison'!B8=1))="",'Model inputs'!B169=""),"",OR(IF(ISERROR('Scenario comparison'!B8=1),'Scenario comparison'!B8=1,IF('Scenario comparison'!B8="","",'Scenario comparison'!B8=1)),'Model inputs'!B169))))="",FALSE,IF(IFERROR(IF(ISERROR('Scenario comparison'!B8=1),'Scenario comparison'!B8=1,IF('Scenario comparison'!B8="","",'Scenario comparison'!B8=1))=TRUE,FALSE),TRUE,IF(IFERROR('Model inputs'!B169=TRUE,FALSE),TRUE,IF(OR(IF(ISERROR('Scenario comparison'!B8=1),'Scenario comparison'!B8=1,IF('Scenario comparison'!B8="","",'Scenario comparison'!B8=1))="",'Model inputs'!B169=""),"",OR(IF(ISERROR('Scenario comparison'!B8=1),'Scenario comparison'!B8=1,IF('Scenario comparison'!B8="","",'Scenario comparison'!B8=1)),'Model inputs'!B169))))),1,0)) -> 0 | F8: =IF(IF(IF(ISERROR('Model inputs'!D60<'Model inputs'!O19),'Model inputs'!D60<'Model inputs'!O19,IF(OR('Model inputs'!D60="",'Model inputs'!O19=""),"",'Model inputs'!D60<'Model inputs'!O19))="",FALSE,IF(ISERROR('Model inputs'!D60<'Model inputs'!O19),'Model inputs'!D60<'Model inputs'!O19,IF(OR('Model inputs'!D60="",'Model inputs'!O19=""),"",'Model inputs'!D60<'Model inputs'!O19))),0,IF(IF(IF(IFERROR(IF(ISERROR('Scenario comparison'!C8=1),'Scenario comparison'!C8=1,IF('Scenario comparison'!C8="","",'Scenario comparison'!C8=1))=TRUE,FALSE),TRUE,IF(IFERROR('Model inputs'!B192=TRUE,FALSE),TRUE,IF(OR(IF(ISERROR('Scenario comparison'!C8=1),'Scenario comparison'!C8=1,IF('Scenario comparison'!C8="","",'Scenario comparison'!C8=1))="",'Model inputs'!B192=""),"",OR(IF(ISERROR('Scenario comparison'!C8=1),'Scenario comparison'!C8=1,IF('Scenario comparison'!C8="","",'Scenario comparison'!C8=1)),'Model inputs'!B192))))="",FALSE,IF(IFERROR(IF(ISERROR('Scenario comparison'!C8=1),'Scenario comparison'!C8=1,IF('Scenario comparison'!C8="","",'Scenario comparison'!C8=1))=TRUE,FALSE),TRUE,IF(IFERROR('Model inputs'!B192=TRUE,FALSE),TRUE,IF(OR(IF(ISERROR('Scenario comparison'!C8=1),'Scenario comparison'!C8=1,IF('Scenario comparison'!C8="","",'Scenario comparison'!C8=1))="",'Model inputs'!B192=""),"",OR(IF(ISERROR('Scenario comparison'!C8=1),'Scenario comparison'!C8=1,IF('Scenario comparison'!C8="","",'Scenario comparison'!C8=1)),'Model inputs'!B192))))),1,0)) -> 0 | G8: =IF(IF(IF(ISERROR('Model inputs'!D61<'Model inputs'!O20),'Model inputs'!D61<'Model inputs'!O20,IF(OR('Model inputs'!D61="",'Model inputs'!O20=""),"",'Model inputs'!D61<'Model inputs'!O20))="",FALSE,IF(ISERROR('Model inputs'!D61<'Model inputs'!O20),'Model inputs'!D61<'Model inputs'!O20,IF(OR('Model inputs'!D61="",'Model inputs'!O20=""),"",'Model inputs'!D61<'Model inputs'!O20))),0,IF(IF(IF(IFERROR(IF(ISERROR('Scenario comparison'!D8=1),'Scenario comparison'!D8=1,IF('Scenario comparison'!D8="","",'Scenario comparison'!D8=1))=TRUE,FALSE),TRUE,IF(IFERROR('Model inputs'!B193=TRUE,FALSE),TRUE,IF(OR(IF(ISERROR('Scenario comparison'!D8=1),'Scenario comparison'!D8=1,IF('Scenario comparison'!D8="","",'Scenario comparison'!D8=1))="",'Model inputs'!B193=""),"",OR(IF(ISERROR('Scenario comparison'!D8=1),'Scenario comparison'!D8=1,IF('Scenario comparison'!D8="","",'Scenario comparison'!D8=1)),'Model inputs'!B193))))="",FALSE,IF(IFERROR(IF(ISERROR('Scenario comparison'!D8=1),'Scenario comparison'!D8=1,IF('Scenario comparison'!D8="","",'Scenario comparison'!D8=1))=TRUE,FALSE),TRUE,IF(IFERROR('Model inputs'!B193=TRUE,FALSE),TRUE,IF(OR(IF(ISERROR('Scenario comparison'!D8=1),'Scenario comparison'!D8=1,IF('Scenario comparison'!D8="","",'Scenario comparison'!D8=1))="",'Model inputs'!B193=""),"",OR(IF(ISERROR('Scenario comparison'!D8=1),'Scenario comparison'!D8=1,IF('Scenario comparison'!D8="","",'Scenario comparison'!D8=1)),'Model inputs'!B193))))),1,0)) -> 0 | H8: =IF(IF(IF(ISERROR('Monthly operating and hiring fo'!D9<'Pricing and operating assumptio'!B16),'Monthly operating and hiring fo'!D9<'Pricing and operating assumptio'!B16,IF(OR('Monthly operating and hiring fo'!D9="",'Pricing and operating assumptio'!B16=""),"",'Monthly operating and hiring fo'!D9<'Pricing and operating assumptio'!B16))="",FALSE,IF(ISERROR('Monthly operating and hiring fo'!D9<'Pricing and operating assumptio'!B16),'Monthly operating and hiring fo'!D9<'Pricing and operating assumptio'!B16,IF(OR('Monthly operating and hiring fo'!D9="",'Pricing and operating assumptio'!B16=""),"",'Monthly operating and hiring fo'!D9<'Pricing and operating assumptio'!B16))),0,IF(IF(IF(IFERROR(IF(ISERROR('Scenario comparison'!E8=1),'Scenario comparison'!E8=1,IF('Scenario comparison'!E8="","",'Scenario comparison'!E8=1))=TRUE,FALSE),TRUE,IF(IFERROR('Model inputs'!B171=TRUE,FALSE),TRUE,IF(OR(IF(ISERROR('Scenario comparison'!E8=1),'Scenario comparison'!E8=1,IF('Scenario comparison'!E8="","",'Scenario comparison'!E8=1))="",'Model inputs'!B171=""),"",OR(IF(ISERROR('Scenario comparison'!E8=1),'Scenario comparison'!E8=1,IF('Scenario comparison'!E8="","",'Scenario comparison'!E8=1)),'Model inputs'!B171))))="",FALSE,IF(IFERROR(IF(ISERROR('Scenario comparison'!E8=1),'Scenario comparison'!E8=1,IF('Scenario comparison'!E8="","",'Scenario comparison'!E8=1))=TRUE,FALSE),TRUE,IF(IFERROR('Model inputs'!B171=TRUE,FALSE),TRUE,IF(OR(IF(ISERROR('Scenario comparison'!E8=1),'Scenario comparison'!E8=1,IF('Scenario comparison'!E8="","",'Scenario comparison'!E8=1))="",'Model inputs'!B171=""),"",OR(IF(ISERROR('Scenario comparison'!E8=1),'Scenario comparison'!E8=1,IF('Scenario comparison'!E8="","",'Scenario comparison'!E8=1)),'Model inputs'!B171))))),1,0)) -> 0 | I8: =IF(IF(IF(ISERROR('Model inputs'!E60<'Model inputs'!O19),'Model inputs'!E60<'Model inputs'!O19,IF(OR('Model inputs'!E60="",'Model inputs'!O19=""),"",'Model inputs'!E60<'Model inputs'!O19))="",FALSE,IF(ISERROR('Model inputs'!E60<'Model inputs'!O19),'Model inputs'!E60<'Model inputs'!O19,IF(OR('Model inputs'!E60="",'Model inputs'!O19=""),"",'Model inputs'!E60<'Model inputs'!O19))),0,IF(IF(IF(IFERROR(IF(ISERROR('Scenario comparison'!F8=1),'Scenario comparison'!F8=1,IF('Scenario comparison'!F8="","",'Scenario comparison'!F8=1))=TRUE,FALSE),TRUE,IF(IFERROR('Model inputs'!B194=TRUE,FALSE),TRUE,IF(OR(IF(ISERROR('Scenario comparison'!F8=1),'Scenario comparison'!F8=1,IF('Scenario comparison'!F8="","",'Scenario comparison'!F8=1))="",'Model inputs'!B194=""),"",OR(IF(ISERROR('Scenario comparison'!F8=1),'Scenario comparison'!F8=1,IF('Scenario comparison'!F8="","",'Scenario comparison'!F8=1)),'Model inputs'!B194))))="",FALSE,IF(IFERROR(IF(ISERROR('Scenario comparison'!F8=1),'Scenario comparison'!F8=1,IF('Scenario comparison'!F8="","",'Scenario comparison'!F8=1))=TRUE,FALSE),TRUE,IF(IFERROR('Model inputs'!B194=TRUE,FALSE),TRUE,IF(OR(IF(ISERROR('Scenario comparison'!F8=1),'Scenario comparison'!F8=1,IF('Scenario comparison'!F8="","",'Scenario comparison'!F8=1))="",'Model inputs'!B194=""),"",OR(IF(ISERROR('Scenario comparison'!F8=1),'Scenario comparison'!F8=1,IF('Scenario comparison'!F8="","",'Scenario comparison'!F8=1)),'Model inputs'!B194))))),1,0)) -> 0 | J8: =IF(IF(IF(ISERROR('Model inputs'!E61<'Model inputs'!O20),'Model inputs'!E61<'Model inputs'!O20,IF(OR('Model inputs'!E61="",'Model inputs'!O20=""),"",'Model inputs'!E61<'Model inputs'!O20))="",FALSE,IF(ISERROR('Model inputs'!E61<'Model inputs'!O20),'Model inputs'!E61<'Model inputs'!O20,IF(OR('Model inputs'!E61="",'Model inputs'!O20=""),"",'Model inputs'!E61<'Model inputs'!O20))),0,IF(IF(IF(IFERROR(IF(ISERROR('Scenario comparison'!G8=1),'Scenario comparison'!G8=1,IF('Scenario comparison'!G8="","",'Scenario comparison'!G8=1))=TRUE,FALSE),TRUE,IF(IFERROR('Model inputs'!B195=TRUE,FALSE),TRUE,IF(OR(IF(ISERROR('Scenario comparison'!G8=1),'Scenario comparison'!G8=1,IF('Scenario comparison'!G8="","",'Scenario comparison'!G8=1))="",'Model inputs'!B195=""),"",OR(IF(ISERROR('Scenario comparison'!G8=1),'Scenario comparison'!G8=1,IF('Scenario comparison'!G8="","",'Scenario comparison'!G8=1)),'Model inputs'!B195))))="",FALSE,IF(IFERROR(IF(ISERROR('Scenario comparison'!G8=1),'Scenario comparison'!G8=1,IF('Scenario comparison'!G8="","",'Scenario comparison'!G8=1))=TRUE,FALSE),TRUE,IF(IFERROR('Model inputs'!B195=TRUE,FALSE),TRUE,IF(OR(IF(ISERROR('Scenario comparison'!G8=1),'Scenario comparison'!G8=1,IF('Scenario comparison'!G8="","",'Scenario comparison'!G8=1))="",'Model inputs'!B195=""),"",OR(IF(ISERROR('Scenario comparison'!G8=1),'Scenario comparison'!G8=1,IF('Scenario comparison'!G8="","",'Scenario comparison'!G8=1)),'Model inputs'!B195))))),1,0)) -> 0 | K8: =IF(IF(IF(ISERROR('Monthly operating and hiring fo'!E9<'Pricing and operating assumptio'!B16),'Monthly operating and hiring fo'!E9<'Pricing and operating assumptio'!B16,IF(OR('Monthly operating and hiring fo'!E9="",'Pricing and operating assumptio'!B16=""),"",'Monthly operating and hiring fo'!E9<'Pricing and operating assumptio'!B16))="",FALSE,IF(ISERROR('Monthly operating and hiring fo'!E9<'Pricing and operating assumptio'!B16),'Monthly operating and hiring fo'!E9<'Pricing and operating assumptio'!B16,IF(OR('Monthly operating and hiring fo'!E9="",'Pricing and operating assumptio'!B16=""),"",'Monthly operating and hiring fo'!E9<'Pricing and operating assumptio'!B16))),0,IF(IF(IF(IFERROR(IF(ISERROR('Scenario comparison'!H8=1),'Scenario comparison'!H8=1,IF('Scenario comparison'!H8="","",'Scenario comparison'!H8=1))=TRUE,FALSE),TRUE,IF(IFERROR('Model inputs'!B173=TRUE,FALSE),TRUE,IF(OR(IF(ISERROR('Scenario comparison'!H8=1),'Scenario comparison'!H8=1,IF('Scenario comparison'!H8="","",'Scenario comparison'!H8=1))="",'Model inputs'!B173=""),"",OR(IF(ISERROR('Scenario comparison'!H8=1),'Scenario comparison'!H8=1,IF('Scenario comparison'!H8="","",'Scenario comparison'!H8=1)),'Model inputs'!B173))))="",FALSE,IF(IFERROR(IF(ISERROR('Scenario comparison'!H8=1),'Scenario comparison'!H8=1,IF('Scenario comparison'!H8="","",'Scenario comparison'!H8=1))=TRUE,FALSE),TRUE,IF(IFERROR('Model inputs'!B173=TRUE,FALSE),TRUE,IF(OR(IF(ISERROR('Scenario comparison'!H8=1),'Scenario comparison'!H8=1,IF('Scenario comparison'!H8="","",'Scenario comparison'!H8=1))="",'Model inputs'!B173=""),"",OR(IF(ISERROR('Scenario comparison'!H8=1),'Scenario comparison'!H8=1,IF('Scenario comparison'!H8="","",'Scenario comparison'!H8=1)),'Model inputs'!B173))))),1,0)) -> 0 | L8: =IF(IF(IF(ISERROR('Model inputs'!F60<'Model inputs'!O19),'Model inputs'!F60<'Model inputs'!O19,IF(OR('Model inputs'!F60="",'Model inputs'!O19=""),"",'Model inputs'!F60<'Model inputs'!O19))="",FALSE,IF(ISERROR('Model inputs'!F60<'Model inputs'!O19),'Model inputs'!F60<'Model inputs'!O19,IF(OR('Model inputs'!F60="",'Model inputs'!O19=""),"",'Model inputs'!F60<'Model inputs'!O19))),0,IF(IF(IF(IFERROR(IF(ISERROR('Scenario comparison'!I8=1),'Scenario comparison'!I8=1,IF('Scenario comparison'!I8="","",'Scenario comparison'!I8=1))=TRUE,FALSE),TRUE,IF(IFERROR('Model inputs'!B196=TRUE,FALSE),TRUE,IF(OR(IF(ISERROR('Scenario comparison'!I8=1),'Scenario comparison'!I8=1,IF('Scenario comparison'!I8="","",'Scenario comparison'!I8=1))="",'Model inputs'!B196=""),"",OR(IF(ISERROR('Scenario comparison'!I8=1),'Scenario comparison'!I8=1,IF('Scenario comparison'!I8="","",'Scenario comparison'!I8=1)),'Model inputs'!B196))))="",FALSE,IF(IFERROR(IF(ISERROR('Scenario comparison'!I8=1),'Scenario comparison'!I8=1,IF('Scenario comparison'!I8="","",'Scenario comparison'!I8=1))=TRUE,FALSE),TRUE,IF(IFERROR('Model inputs'!B196=TRUE,FALSE),TRUE,IF(OR(IF(ISERROR('Scenario comparison'!I8=1),'Scenario comparison'!I8=1,IF('Scenario comparison'!I8="","",'Scenario comparison'!I8=1))="",'Model inputs'!B196=""),"",OR(IF(ISERROR('Scenario comparison'!I8=1),'Scenario comparison'!I8=1,IF('Scenario comparison'!I8="","",'Scenario comparison'!I8=1)),'Model inputs'!B196))))),1,0)) -> 0 | M8: =IF(IF(IF(ISERROR('Model inputs'!F61<'Model inputs'!O20),'Model inputs'!F61<'Model inputs'!O20,IF(OR('Model inputs'!F61="",'Model inputs'!O20=""),"",'Model inputs'!F61<'Model inputs'!O20))="",FALSE,IF(ISERROR('Model inputs'!F61<'Model inputs'!O20),'Model inputs'!F61<'Model inputs'!O20,IF(OR('Model inputs'!F61="",'Model inputs'!O20=""),"",'Model inputs'!F61<'Model inputs'!O20))),0,IF(IF(IF(IFERROR(IF(ISERROR('Scenario comparison'!J8=1),'Scenario comparison'!J8=1,IF('Scenario comparison'!J8="","",'Scenario comparison'!J8=1))=TRUE,FALSE),TRUE,IF(IFERROR('Model inputs'!B197=TRUE,FALSE),TRUE,IF(OR(IF(ISERROR('Scenario comparison'!J8=1),'Scenario comparison'!J8=1,IF('Scenario comparison'!J8="","",'Scenario comparison'!J8=1))="",'Model inputs'!B197=""),"",OR(IF(ISERROR('Scenario comparison'!J8=1),'Scenario comparison'!J8=1,IF('Scenario comparison'!J8="","",'Scenario comparison'!J8=1)),'Model inputs'!B197))))="",FALSE,IF(IFERROR(IF(ISERROR('Scenario comparison'!J8=1),'Scenario comparison'!J8=1,IF('Scenario comparison'!J8="","",'Scenario comparison'!J8=1))=TRUE,FALSE),TRUE,IF(IFERROR('Model inputs'!B197=TRUE,FALSE),TRUE,IF(OR(IF(ISERROR('Scenario comparison'!J8=1),'Scenario comparison'!J8=1,IF('Scenario comparison'!J8="","",'Scenario comparison'!J8=1))="",'Model inputs'!B197=""),"",OR(IF(ISERROR('Scenario comparison'!J8=1),'Scenario comparison'!J8=1,IF('Scenario comparison'!J8="","",'Scenario comparison'!J8=1)),'Model inputs'!B197))))),1,0)) -> 0 | N8: =IF(IF(IF(ISERROR('Monthly operating and hiring fo'!F9<'Pricing and operating assumptio'!B16),'Monthly operating and hiring fo'!F9<'Pricing and operating assumptio'!B16,IF(OR('Monthly operating and hiring fo'!F9="",'Pricing and operating assumptio'!B16=""),"",'Monthly operating and hiring fo'!F9<'Pricing and operating assumptio'!B16))="",FALSE,IF(ISERROR('Monthly operating and hiring fo'!F9<'Pricing and operating assumptio'!B16),'Monthly operating and hiring fo'!F9<'Pricing and operating assumptio'!B16,IF(OR('Monthly operating and hiring fo'!F9="",'Pricing and operating assumptio'!B16=""),"",'Monthly operating and hiring fo'!F9<'Pricing and operating assumptio'!B16))),0,IF(IF(IF(IFERROR(IF(ISERROR('Scenario comparison'!K8=1),'Scenario comparison'!K8=1,IF('Scenario comparison'!K8="","",'Scenario comparison'!K8=1))=TRUE,FALSE),TRUE,IF(IFERROR('Model inputs'!B175=TRUE,FALSE),TRUE,IF(OR(IF(ISERROR('Scenario comparison'!K8=1),'Scenario comparison'!K8=1,IF('Scenario comparison'!K8="","",'Scenario comparison'!K8=1))="",'Model inputs'!B175=""),"",OR(IF(ISERROR('Scenario comparison'!K8=1),'Scenario comparison'!K8=1,IF('Scenario comparison'!K8="","",'Scenario comparison'!K8=1)),'Model inputs'!B175))))="",FALSE,IF(IFERROR(IF(ISERROR('Scenario comparison'!K8=1),'Scenario comparison'!K8=1,IF('Scenario comparison'!K8="","",'Scenario comparison'!K8=1))=TRUE,FALSE),TRUE,IF(IFERROR('Model inputs'!B175=TRUE,FALSE),TRUE,IF(OR(IF(ISERROR('Scenario comparison'!K8=1),'Scenario comparison'!K8=1,IF('Scenario comparison'!K8="","",'Scenario comparison'!K8=1))="",'Model inputs'!B175=""),"",OR(IF(ISERROR('Scenario comparison'!K8=1),'Scenario comparison'!K8=1,IF('Scenario comparison'!K8="","",'Scenario comparison'!K8=1)),'Model inputs'!B175))))),1,0)) -> 0 | O8: =IF(IF(IF(ISERROR('Model inputs'!G60<'Model inputs'!O19),'Model inputs'!G60<'Model inputs'!O19,IF(OR('Model inputs'!G60="",'Model inputs'!O19=""),"",'Model inputs'!G60<'Model inputs'!O19))="",FALSE,IF(ISERROR('Model inputs'!G60<'Model inputs'!O19),'Model inputs'!G60<'Model inputs'!O19,IF(OR('Model inputs'!G60="",'Model inputs'!O19=""),"",'Model inputs'!G60<'Model inputs'!O19))),0,IF(IF(IF(IFERROR(IF(ISERROR('Scenario comparison'!L8=1),'Scenario comparison'!L8=1,IF('Scenario comparison'!L8="","",'Scenario comparison'!L8=1))=TRUE,FALSE),TRUE,IF(IFERROR('Model inputs'!B198=TRUE,FALSE),TRUE,IF(OR(IF(ISERROR('Scenario comparison'!L8=1),'Scenario comparison'!L8=1,IF('Scenario comparison'!L8="","",'Scenario comparison'!L8=1))="",'Model inputs'!B198=""),"",OR(IF(ISERROR('Scenario comparison'!L8=1),'Scenario comparison'!L8=1,IF('Scenario comparison'!L8="","",'Scenario comparison'!L8=1)),'Model inputs'!B198))))="",FALSE,IF(IFERROR(IF(ISERROR('Scenario comparison'!L8=1),'Scenario comparison'!L8=1,IF('Scenario comparison'!L8="","",'Scenario comparison'!L8=1))=TRUE,FALSE),TRUE,IF(IFERROR('Model inputs'!B198=TRUE,FALSE),TRUE,IF(OR(IF(ISERROR('Scenario comparison'!L8=1),'Scenario comparison'!L8=1,IF('Scenario comparison'!L8="","",'Scenario comparison'!L8=1))="",'Model inputs'!B198=""),"",OR(IF(ISERROR('Scenario comparison'!L8=1),'Scenario comparison'!L8=1,IF('Scenario comparison'!L8="","",'Scenario comparison'!L8=1)),'Model inputs'!B198))))),1,0)) -> 0 | P8: =IF(IF(IF(ISERROR('Model inputs'!G61<'Model inputs'!O20),'Model inputs'!G61<'Model inputs'!O20,IF(OR('Model inputs'!G61="",'Model inputs'!O20=""),"",'Model inputs'!G61<'Model inputs'!O20))="",FALSE,IF(ISERROR('Model inputs'!G61<'Model inputs'!O20),'Model inputs'!G61<'Model inputs'!O20,IF(OR('Model inputs'!G61="",'Model inputs'!O20=""),"",'Model inputs'!G61<'Model inputs'!O20))),0,IF(IF(IF(IFERROR(IF(ISERROR('Scenario comparison'!M8=1),'Scenario comparison'!M8=1,IF('Scenario comparison'!M8="","",'Scenario comparison'!M8=1))=TRUE,FALSE),TRUE,IF(IFERROR('Model inputs'!B199=TRUE,FALSE),TRUE,IF(OR(IF(ISERROR('Scenario comparison'!M8=1),'Scenario comparison'!M8=1,IF('Scenario comparison'!M8="","",'Scenario comparison'!M8=1))="",'Model inputs'!B199=""),"",OR(IF(ISERROR('Scenario comparison'!M8=1),'Scenario comparison'!M8=1,IF('Scenario comparison'!M8="","",'Scenario comparison'!M8=1)),'Model inputs'!B199))))="",FALSE,IF(IFERROR(IF(ISERROR('Scenario comparison'!M8=1),'Scenario comparison'!M8=1,IF('Scenario comparison'!M8="","",'Scenario comparison'!M8=1))=TRUE,FALSE),TRUE,IF(IFERROR('Model inputs'!B199=TRUE,FALSE),TRUE,IF(OR(IF(ISERROR('Scenario comparison'!M8=1),'Scenario comparison'!M8=1,IF('Scenario comparison'!M8="","",'Scenario comparison'!M8=1))="",'Model inputs'!B199=""),"",OR(IF(ISERROR('Scenario comparison'!M8=1),'Scenario comparison'!M8=1,IF('Scenario comparison'!M8="","",'Scenario comparison'!M8=1)),'Model inputs'!B199))))),1,0)) -> 0 | Q8: =IF(IF(IF(ISERROR('Monthly operating and hiring fo'!G9<'Pricing and operating assumptio'!B16),'Monthly operating and hiring fo'!G9<'Pricing and operating assumptio'!B16,IF(OR('Monthly operating and hiring fo'!G9="",'Pricing and operating assumptio'!B16=""),"",'Monthly operating and hiring fo'!G9<'Pricing and operating assumptio'!B16))="",FALSE,IF(ISERROR('Monthly operating and hiring fo'!G9<'Pricing and operating assumptio'!B16),'Monthly operating and hiring fo'!G9<'Pricing and operating assumptio'!B16,IF(OR('Monthly operating and hiring fo'!G9="",'Pricing and operating assumptio'!B16=""),"",'Monthly operating and hiring fo'!G9<'Pricing and operating assumptio'!B16))),0,IF(IF(IF(IFERROR(IF(ISERROR('Scenario comparison'!N8=1),'Scenario comparison'!N8=1,IF('Scenario comparison'!N8="","",'Scenario comparison'!N8=1))=TRUE,FALSE),TRUE,IF(IFERROR('Model inputs'!B177=TRUE,FALSE),TRUE,IF(OR(IF(ISERROR('Scenario comparison'!N8=1),'Scenario comparison'!N8=1,IF('Scenario comparison'!N8="","",'Scenario comparison'!N8=1))="",'Model inputs'!B177=""),"",OR(IF(ISERROR('Scenario comparison'!N8=1),'Scenario comparison'!N8=1,IF('Scenario comparison'!N8="","",'Scenario comparison'!N8=1)),'Model inputs'!B177))))="",FALSE,IF(IFERROR(IF(ISERROR('Scenario comparison'!N8=1),'Scenario comparison'!N8=1,IF('Scenario comparison'!N8="","",'Scenario comparison'!N8=1))=TRUE,FALSE),TRUE,IF(IFERROR('Model inputs'!B177=TRUE,FALSE),TRUE,IF(OR(IF(ISERROR('Scenario comparison'!N8=1),'Scenario comparison'!N8=1,IF('Scenario comparison'!N8="","",'Scenario comparison'!N8=1))="",'Model inputs'!B177=""),"",OR(IF(ISERROR('Scenario comparison'!N8=1),'Scenario comparison'!N8=1,IF('Scenario comparison'!N8="","",'Scenario comparison'!N8=1)),'Model inputs'!B177))))),1,0)) -> 0 | R8: =IF(IF(IF(ISERROR('Model inputs'!H60<'Model inputs'!O19),'Model inputs'!H60<'Model inputs'!O19,IF(OR('Model inputs'!H60="",'Model inputs'!O19=""),"",'Model inputs'!H60<'Model inputs'!O19))="",FALSE,IF(ISERROR('Model inputs'!H60<'Model inputs'!O19),'Model inputs'!H60<'Model inputs'!O19,IF(OR('Model inputs'!H60="",'Model inputs'!O19=""),"",'Model inputs'!H60<'Model inputs'!O19))),0,IF(IF(IF(IFERROR(IF(ISERROR('Scenario comparison'!O8=1),'Scenario comparison'!O8=1,IF('Scenario comparison'!O8="","",'Scenario comparison'!O8=1))=TRUE,FALSE),TRUE,IF(IFERROR('Model inputs'!B200=TRUE,FALSE),TRUE,IF(OR(IF(ISERROR('Scenario comparison'!O8=1),'Scenario comparison'!O8=1,IF('Scenario comparison'!O8="","",'Scenario comparison'!O8=1))="",'Model inputs'!B200=""),"",OR(IF(ISERROR('Scenario comparison'!O8=1),'Scenario comparison'!O8=1,IF('Scenario comparison'!O8="","",'Scenario comparison'!O8=1)),'Model inputs'!B200))))="",FALSE,IF(IFERROR(IF(ISERROR('Scenario comparison'!O8=1),'Scenario comparison'!O8=1,IF('Scenario comparison'!O8="","",'Scenario comparison'!O8=1))=TRUE,FALSE),TRUE,IF(IFERROR('Model inputs'!B200=TRUE,FALSE),TRUE,IF(OR(IF(ISERROR('Scenario comparison'!O8=1),'Scenario comparison'!O8=1,IF('Scenario comparison'!O8="","",'Scenario comparison'!O8=1))="",'Model inputs'!B200=""),"",OR(IF(ISERROR('Scenario comparison'!O8=1),'Scenario comparison'!O8=1,IF('Scenario comparison'!O8="","",'Scenario comparison'!O8=1)),'Model inputs'!B200))))),1,0)) -> 0 | S8: =IF(IF(IF(ISERROR('Model inputs'!H61<'Model inputs'!O20),'Model inputs'!H61<'Model inputs'!O20,IF(OR('Model inputs'!H61="",'Model inputs'!O20=""),"",'Model inputs'!H61<'Model inputs'!O20))="",FALSE,IF(ISERROR('Model inputs'!H61<'Model inputs'!O20),'Model inputs'!H61<'Model inputs'!O20,IF(OR('Model inputs'!H61="",'Model inputs'!O20=""),"",'Model inputs'!H61<'Model inputs'!O20))),0,IF(IF(IF(IFERROR(IF(ISERROR('Scenario comparison'!P8=1),'Scenario comparison'!P8=1,IF('Scenario comparison'!P8="","",'Scenario comparison'!P8=1))=TRUE,FALSE),TRUE,IF(IFERROR('Model inputs'!B201=TRUE,FALSE),TRUE,IF(OR(IF(ISERROR('Scenario comparison'!P8=1),'Scenario comparison'!P8=1,IF('Scenario comparison'!P8="","",'Scenario comparison'!P8=1))="",'Model inputs'!B201=""),"",OR(IF(ISERROR('Scenario comparison'!P8=1),'Scenario comparison'!P8=1,IF('Scenario comparison'!P8="","",'Scenario comparison'!P8=1)),'Model inputs'!B201))))="",FALSE,IF(IFERROR(IF(ISERROR('Scenario comparison'!P8=1),'Scenario comparison'!P8=1,IF('Scenario comparison'!P8="","",'Scenario comparison'!P8=1))=TRUE,FALSE),TRUE,IF(IFERROR('Model inputs'!B201=TRUE,FALSE),TRUE,IF(OR(IF(ISERROR('Scenario comparison'!P8=1),'Scenario comparison'!P8=1,IF('Scenario comparison'!P8="","",'Scenario comparison'!P8=1))="",'Model inputs'!B201=""),"",OR(IF(ISERROR('Scenario comparison'!P8=1),'Scenario comparison'!P8=1,IF('Scenario comparison'!P8="","",'Scenario comparison'!P8=1)),'Model inputs'!B201))))),1,0)) -> 0 | T8: =IF(IF(IF(ISERROR('Monthly operating and hiring fo'!H9<'Pricing and operating assumptio'!B16),'Monthly operating and hiring fo'!H9<'Pricing and operating assumptio'!B16,IF(OR('Monthly operating and hiring fo'!H9="",'Pricing and operating assumptio'!B16=""),"",'Monthly operating and hiring fo'!H9<'Pricing and operating assumptio'!B16))="",FALSE,IF(ISERROR('Monthly operating and hiring fo'!H9<'Pricing and operating assumptio'!B16),'Monthly operating and hiring fo'!H9<'Pricing and operating assumptio'!B16,IF(OR('Monthly operating and hiring fo'!H9="",'Pricing and operating assumptio'!B16=""),"",'Monthly operating and hiring fo'!H9<'Pricing and operating assumptio'!B16))),0,IF(IF(IF(IFERROR(IF(ISERROR('Scenario comparison'!Q8=1),'Scenario comparison'!Q8=1,IF('Scenario comparison'!Q8="","",'Scenario comparison'!Q8=1))=TRUE,FALSE),TRUE,IF(IFERROR('Model inputs'!B179=TRUE,FALSE),TRUE,IF(OR(IF(ISERROR('Scenario comparison'!Q8=1),'Scenario comparison'!Q8=1,IF('Scenario comparison'!Q8="","",'Scenario comparison'!Q8=1))="",'Model inputs'!B179=""),"",OR(IF(ISERROR('Scenario comparison'!Q8=1),'Scenario comparison'!Q8=1,IF('Scenario comparison'!Q8="","",'Scenario comparison'!Q8=1)),'Model inputs'!B179))))="",FALSE,IF(IFERROR(IF(ISERROR('Scenario comparison'!Q8=1),'Scenario comparison'!Q8=1,IF('Scenario comparison'!Q8="","",'Scenario comparison'!Q8=1))=TRUE,FALSE),TRUE,IF(IFERROR('Model inputs'!B179=TRUE,FALSE),TRUE,IF(OR(IF(ISERROR('Scenario comparison'!Q8=1),'Scenario comparison'!Q8=1,IF('Scenario comparison'!Q8="","",'Scenario comparison'!Q8=1))="",'Model inputs'!B179=""),"",OR(IF(ISERROR('Scenario comparison'!Q8=1),'Scenario comparison'!Q8=1,IF('Scenario comparison'!Q8="","",'Scenario comparison'!Q8=1)),'Model inputs'!B179))))),1,0)) -> 0 | U8: =IF(IF(IF(ISERROR('Model inputs'!I60<'Model inputs'!O19),'Model inputs'!I60<'Model inputs'!O19,IF(OR('Model inputs'!I60="",'Model inputs'!O19=""),"",'Model inputs'!I60<'Model inputs'!O19))="",FALSE,IF(ISERROR('Model inputs'!I60<'Model inputs'!O19),'Model inputs'!I60<'Model inputs'!O19,IF(OR('Model inputs'!I60="",'Model inputs'!O19=""),"",'Model inputs'!I60<'Model inputs'!O19))),0,IF(IF(IF(IFERROR(IF(ISERROR('Scenario comparison'!R8=1),'Scenario comparison'!R8=1,IF('Scenario comparison'!R8="","",'Scenario comparison'!R8=1))=TRUE,FALSE),TRUE,IF(IFERROR('Model inputs'!B202=TRUE,FALSE),TRUE,IF(OR(IF(ISERROR('Scenario comparison'!R8=1),'Scenario comparison'!R8=1,IF('Scenario comparison'!R8="","",'Scenario comparison'!R8=1))="",'Model inputs'!B202=""),"",OR(IF(ISERROR('Scenario comparison'!R8=1),'Scenario comparison'!R8=1,IF('Scenario comparison'!R8="","",'Scenario comparison'!R8=1)),'Model inputs'!B202))))="",FALSE,IF(IFERROR(IF(ISERROR('Scenario comparison'!R8=1),'Scenario comparison'!R8=1,IF('Scenario comparison'!R8="","",'Scenario comparison'!R8=1))=TRUE,FALSE),TRUE,IF(IFERROR('Model inputs'!B202=TRUE,FALSE),TRUE,IF(OR(IF(ISERROR('Scenario comparison'!R8=1),'Scenario comparison'!R8=1,IF('Scenario comparison'!R8="","",'Scenario comparison'!R8=1))="",'Model inputs'!B202=""),"",OR(IF(ISERROR('Scenario comparison'!R8=1),'Scenario comparison'!R8=1,IF('Scenario comparison'!R8="","",'Scenario comparison'!R8=1)),'Model inputs'!B202))))),1,0)) -> 0 | V8: =IF(IF(IF(ISERROR('Model inputs'!I61<'Model inputs'!O20),'Model inputs'!I61<'Model inputs'!O20,IF(OR('Model inputs'!I61="",'Model inputs'!O20=""),"",'Model inputs'!I61<'Model inputs'!O20))="",FALSE,IF(ISERROR('Model inputs'!I61<'Model inputs'!O20),'Model inputs'!I61<'Model inputs'!O20,IF(OR('Model inputs'!I61="",'Model inputs'!O20=""),"",'Model inputs'!I61<'Model inputs'!O20))),0,IF(IF(IF(IFERROR(IF(ISERROR('Scenario comparison'!S8=1),'Scenario comparison'!S8=1,IF('Scenario comparison'!S8="","",'Scenario comparison'!S8=1))=TRUE,FALSE),TRUE,IF(IFERROR('Model inputs'!B203=TRUE,FALSE),TRUE,IF(OR(IF(ISERROR('Scenario comparison'!S8=1),'Scenario comparison'!S8=1,IF('Scenario comparison'!S8="","",'Scenario comparison'!S8=1))="",'Model inputs'!B203=""),"",OR(IF(ISERROR('Scenario comparison'!S8=1),'Scenario comparison'!S8=1,IF('Scenario comparison'!S8="","",'Scenario comparison'!S8=1)),'Model inputs'!B203))))="",FALSE,IF(IFERROR(IF(ISERROR('Scenario comparison'!S8=1),'Scenario comparison'!S8=1,IF('Scenario comparison'!S8="","",'Scenario comparison'!S8=1))=TRUE,FALSE),TRUE,IF(IFERROR('Model inputs'!B203=TRUE,FALSE),TRUE,IF(OR(IF(ISERROR('Scenario comparison'!S8=1),'Scenario comparison'!S8=1,IF('Scenario comparison'!S8="","",'Scenario comparison'!S8=1))="",'Model inputs'!B203=""),"",OR(IF(ISERROR('Scenario comparison'!S8=1),'Scenario comparison'!S8=1,IF('Scenario comparison'!S8="","",'Scenario comparison'!S8=1)),'Model inputs'!B203))))),1,0)) -> 0 | W8: =IF(IF(IF(ISERROR('Monthly operating and hiring fo'!I9<'Pricing and operating assumptio'!B16),'Monthly operating and hiring fo'!I9<'Pricing and operating assumptio'!B16,IF(OR('Monthly operating and hiring fo'!I9="",'Pricing and operating assumptio'!B16=""),"",'Monthly operating and hiring fo'!I9<'Pricing and operating assumptio'!B16))="",FALSE,IF(ISERROR('Monthly operating and hiring fo'!I9<'Pricing and operating assumptio'!B16),'Monthly operating and hiring fo'!I9<'Pricing and operating assumptio'!B16,IF(OR('Monthly operating and hiring fo'!I9="",'Pricing and operating assumptio'!B16=""),"",'Monthly operating and hiring fo'!I9<'Pricing and operating assumptio'!B16))),0,IF(IF(IF(IFERROR(IF(ISERROR('Scenario comparison'!T8=1),'Scenario comparison'!T8=1,IF('Scenario comparison'!T8="","",'Scenario comparison'!T8=1))=TRUE,FALSE),TRUE,IF(IFERROR('Model inputs'!B181=TRUE,FALSE),TRUE,IF(OR(IF(ISERROR('Scenario comparison'!T8=1),'Scenario comparison'!T8=1,IF('Scenario comparison'!T8="","",'Scenario comparison'!T8=1))="",'Model inputs'!B181=""),"",OR(IF(ISERROR('Scenario comparison'!T8=1),'Scenario comparison'!T8=1,IF('Scenario comparison'!T8="","",'Scenario comparison'!T8=1)),'Model inputs'!B181))))="",FALSE,IF(IFERROR(IF(ISERROR('Scenario comparison'!T8=1),'Scenario comparison'!T8=1,IF('Scenario comparison'!T8="","",'Scenario comparison'!T8=1))=TRUE,FALSE),TRUE,IF(IFERROR('Model inputs'!B181=TRUE,FALSE),TRUE,IF(OR(IF(ISERROR('Scenario comparison'!T8=1),'Scenario comparison'!T8=1,IF('Scenario comparison'!T8="","",'Scenario comparison'!T8=1))="",'Model inputs'!B181=""),"",OR(IF(ISERROR('Scenario comparison'!T8=1),'Scenario comparison'!T8=1,IF('Scenario comparison'!T8="","",'Scenario comparison'!T8=1)),'Model inputs'!B181))))),1,0)) -> 0 | X8: =IF(IF(IF(ISERROR('Model inputs'!J60<'Model inputs'!O19),'Model inputs'!J60<'Model inputs'!O19,IF(OR('Model inputs'!J60="",'Model inputs'!O19=""),"",'Model inputs'!J60<'Model inputs'!O19))="",FALSE,IF(ISERROR('Model inputs'!J60<'Model inputs'!O19),'Model inputs'!J60<'Model inputs'!O19,IF(OR('Model inputs'!J60="",'Model inputs'!O19=""),"",'Model inputs'!J60<'Model inputs'!O19))),0,IF(IF(IF(IFERROR(IF(ISERROR('Scenario comparison'!U8=1),'Scenario comparison'!U8=1,IF('Scenario comparison'!U8="","",'Scenario comparison'!U8=1))=TRUE,FALSE),TRUE,IF(IFERROR('Model inputs'!B204=TRUE,FALSE),TRUE,IF(OR(IF(ISERROR('Scenario comparison'!U8=1),'Scenario comparison'!U8=1,IF('Scenario comparison'!U8="","",'Scenario comparison'!U8=1))="",'Model inputs'!B204=""),"",OR(IF(ISERROR('Scenario comparison'!U8=1),'Scenario comparison'!U8=1,IF('Scenario comparison'!U8="","",'Scenario comparison'!U8=1)),'Model inputs'!B204))))="",FALSE,IF(IFERROR(IF(ISERROR('Scenario comparison'!U8=1),'Scenario comparison'!U8=1,IF('Scenario comparison'!U8="","",'Scenario comparison'!U8=1))=TRUE,FALSE),TRUE,IF(IFERROR('Model inputs'!B204=TRUE,FALSE),TRUE,IF(OR(IF(ISERROR('Scenario comparison'!U8=1),'Scenario comparison'!U8=1,IF('Scenario comparison'!U8="","",'Scenario comparison'!U8=1))="",'Model inputs'!B204=""),"",OR(IF(ISERROR('Scenario comparison'!U8=1),'Scenario comparison'!U8=1,IF('Scenario comparison'!U8="","",'Scenario comparison'!U8=1)),'Model inputs'!B204))))),1,0)) -> 0 | Y8: =IF(IF(IF(ISERROR('Model inputs'!J61<'Model inputs'!O20),'Model inputs'!J61<'Model inputs'!O20,IF(OR('Model inputs'!J61="",'Model inputs'!O20=""),"",'Model inputs'!J61<'Model inputs'!O20))="",FALSE,IF(ISERROR('Model inputs'!J61<'Model inputs'!O20),'Model inputs'!J61<'Model inputs'!O20,IF(OR('Model inputs'!J61="",'Model inputs'!O20=""),"",'Model inputs'!J61<'Model inputs'!O20))),0,IF(IF(IF(IFERROR(IF(ISERROR('Scenario comparison'!V8=1),'Scenario comparison'!V8=1,IF('Scenario comparison'!V8="","",'Scenario comparison'!V8=1))=TRUE,FALSE),TRUE,IF(IFERROR('Model inputs'!B205=TRUE,FALSE),TRUE,IF(OR(IF(ISERROR('Scenario comparison'!V8=1),'Scenario comparison'!V8=1,IF('Scenario comparison'!V8="","",'Scenario comparison'!V8=1))="",'Model inputs'!B205=""),"",OR(IF(ISERROR('Scenario comparison'!V8=1),'Scenario comparison'!V8=1,IF('Scenario comparison'!V8="","",'Scenario comparison'!V8=1)),'Model inputs'!B205))))="",FALSE,IF(IFERROR(IF(ISERROR('Scenario comparison'!V8=1),'Scenario comparison'!V8=1,IF('Scenario comparison'!V8="","",'Scenario comparison'!V8=1))=TRUE,FALSE),TRUE,IF(IFERROR('Model inputs'!B205=TRUE,FALSE),TRUE,IF(OR(IF(ISERROR('Scenario comparison'!V8=1),'Scenario comparison'!V8=1,IF('Scenario comparison'!V8="","",'Scenario comparison'!V8=1))="",'Model inputs'!B205=""),"",OR(IF(ISERROR('Scenario comparison'!V8=1),'Scenario comparison'!V8=1,IF('Scenario comparison'!V8="","",'Scenario comparison'!V8=1)),'Model inputs'!B205))))),1,0)) -> 0 | Z8: =IF(IF(IF(ISERROR('Monthly operating and hiring fo'!J9<'Pricing and operating assumptio'!B16),'Monthly operating and hiring fo'!J9<'Pricing and operating assumptio'!B16,IF(OR('Monthly operating and hiring fo'!J9="",'Pricing and operating assumptio'!B16=""),"",'Monthly operating and hiring fo'!J9<'Pricing and operating assumptio'!B16))="",FALSE,IF(ISERROR('Monthly operating and hiring fo'!J9<'Pricing and operating assumptio'!B16),'Monthly operating and hiring fo'!J9<'Pricing and operating assumptio'!B16,IF(OR('Monthly operating and hiring fo'!J9="",'Pricing and operating assumptio'!B16=""),"",'Monthly operating and hiring fo'!J9<'Pricing and operating assumptio'!B16))),0,IF(IF(IF(IFERROR(IF(ISERROR('Scenario comparison'!W8=1),'Scenario comparison'!W8=1,IF('Scenario comparison'!W8="","",'Scenario comparison'!W8=1))=TRUE,FALSE),TRUE,IF(IFERROR('Model inputs'!B183=TRUE,FALSE),TRUE,IF(OR(IF(ISERROR('Scenario comparison'!W8=1),'Scenario comparison'!W8=1,IF('Scenario comparison'!W8="","",'Scenario comparison'!W8=1))="",'Model inputs'!B183=""),"",OR(IF(ISERROR('Scenario comparison'!W8=1),'Scenario comparison'!W8=1,IF('Scenario comparison'!W8="","",'Scenario comparison'!W8=1)),'Model inputs'!B183))))="",FALSE,IF(IFERROR(IF(ISERROR('Scenario comparison'!W8=1),'Scenario comparison'!W8=1,IF('Scenario comparison'!W8="","",'Scenario comparison'!W8=1))=TRUE,FALSE),TRUE,IF(IFERROR('Model inputs'!B183=TRUE,FALSE),TRUE,IF(OR(IF(ISERROR('Scenario comparison'!W8=1),'Scenario comparison'!W8=1,IF('Scenario comparison'!W8="","",'Scenario comparison'!W8=1))="",'Model inputs'!B183=""),"",OR(IF(ISERROR('Scenario comparison'!W8=1),'Scenario comparison'!W8=1,IF('Scenario comparison'!W8="","",'Scenario comparison'!W8=1)),'Model inputs'!B183))))),1,0)) -> 0 | AA8: =IF(IF(IF(ISERROR('Model inputs'!K60<'Model inputs'!O19),'Model inputs'!K60<'Model inputs'!O19,IF(OR('Model inputs'!K60="",'Model inputs'!O19=""),"",'Model inputs'!K60<'Model inputs'!O19))="",FALSE,IF(ISERROR('Model inputs'!K60<'Model inputs'!O19),'Model inputs'!K60<'Model inputs'!O19,IF(OR('Model inputs'!K60="",'Model inputs'!O19=""),"",'Model inputs'!K60<'Model inputs'!O19))),0,IF(IF(IF(IFERROR(IF(ISERROR('Scenario comparison'!X8=1),'Scenario comparison'!X8=1,IF('Scenario comparison'!X8="","",'Scenario comparison'!X8=1))=TRUE,FALSE),TRUE,IF(IFERROR('Model inputs'!B206=TRUE,FALSE),TRUE,IF(OR(IF(ISERROR('Scenario comparison'!X8=1),'Scenario comparison'!X8=1,IF('Scenario comparison'!X8="","",'Scenario comparison'!X8=1))="",'Model inputs'!B206=""),"",OR(IF(ISERROR('Scenario comparison'!X8=1),'Scenario comparison'!X8=1,IF('Scenario comparison'!X8="","",'Scenario comparison'!X8=1)),'Model inputs'!B206))))="",FALSE,IF(IFERROR(IF(ISERROR('Scenario comparison'!X8=1),'Scenario comparison'!X8=1,IF('Scenario comparison'!X8="","",'Scenario comparison'!X8=1))=TRUE,FALSE),TRUE,IF(IFERROR('Model inputs'!B206=TRUE,FALSE),TRUE,IF(OR(IF(ISERROR('Scenario comparison'!X8=1),'Scenario comparison'!X8=1,IF('Scenario comparison'!X8="","",'Scenario comparison'!X8=1))="",'Model inputs'!B206=""),"",OR(IF(ISERROR('Scenario comparison'!X8=1),'Scenario comparison'!X8=1,IF('Scenario comparison'!X8="","",'Scenario comparison'!X8=1)),'Model inputs'!B206))))),1,0)) -> 0 | AB8: =IF(IF(IF(ISERROR('Model inputs'!K61<'Model inputs'!O20),'Model inputs'!K61<'Model inputs'!O20,IF(OR('Model inputs'!K61="",'Model inputs'!O20=""),"",'Model inputs'!K61<'Model inputs'!O20))="",FALSE,IF(ISERROR('Model inputs'!K61<'Model inputs'!O20),'Model inputs'!K61<'Model inputs'!O20,IF(OR('Model inputs'!K61="",'Model inputs'!O20=""),"",'Model inputs'!K61<'Model inputs'!O20))),0,IF(IF(IF(IFERROR(IF(ISERROR('Scenario comparison'!Y8=1),'Scenario comparison'!Y8=1,IF('Scenario comparison'!Y8="","",'Scenario comparison'!Y8=1))=TRUE,FALSE),TRUE,IF(IFERROR('Model inputs'!B207=TRUE,FALSE),TRUE,IF(OR(IF(ISERROR('Scenario comparison'!Y8=1),'Scenario comparison'!Y8=1,IF('Scenario comparison'!Y8="","",'Scenario comparison'!Y8=1))="",'Model inputs'!B207=""),"",OR(IF(ISERROR('Scenario comparison'!Y8=1),'Scenario comparison'!Y8=1,IF('Scenario comparison'!Y8="","",'Scenario comparison'!Y8=1)),'Model inputs'!B207))))="",FALSE,IF(IFERROR(IF(ISERROR('Scenario comparison'!Y8=1),'Scenario comparison'!Y8=1,IF('Scenario comparison'!Y8="","",'Scenario comparison'!Y8=1))=TRUE,FALSE),TRUE,IF(IFERROR('Model inputs'!B207=TRUE,FALSE),TRUE,IF(OR(IF(ISERROR('Scenario comparison'!Y8=1),'Scenario comparison'!Y8=1,IF('Scenario comparison'!Y8="","",'Scenario comparison'!Y8=1))="",'Model inputs'!B207=""),"",OR(IF(ISERROR('Scenario comparison'!Y8=1),'Scenario comparison'!Y8=1,IF('Scenario comparison'!Y8="","",'Scenario comparison'!Y8=1)),'Model inputs'!B207))))),1,0)) -> 0 | AC8: =IF(IF(IF(ISERROR('Monthly operating and hiring fo'!K9<'Pricing and operating assumptio'!B16),'Monthly operating and hiring fo'!K9<'Pricing and operating assumptio'!B16,IF(OR('Monthly operating and hiring fo'!K9="",'Pricing and operating assumptio'!B16=""),"",'Monthly operating and hiring fo'!K9<'Pricing and operating assumptio'!B16))="",FALSE,IF(ISERROR('Monthly operating and hiring fo'!K9<'Pricing and operating assumptio'!B16),'Monthly operating and hiring fo'!K9<'Pricing and operating assumptio'!B16,IF(OR('Monthly operating and hiring fo'!K9="",'Pricing and operating assumptio'!B16=""),"",'Monthly operating and hiring fo'!K9<'Pricing and operating assumptio'!B16))),0,IF(IF(IF(IFERROR(IF(ISERROR('Scenario comparison'!Z8=1),'Scenario comparison'!Z8=1,IF('Scenario comparison'!Z8="","",'Scenario comparison'!Z8=1))=TRUE,FALSE),TRUE,IF(IFERROR('Model inputs'!B185=TRUE,FALSE),TRUE,IF(OR(IF(ISERROR('Scenario comparison'!Z8=1),'Scenario comparison'!Z8=1,IF('Scenario comparison'!Z8="","",'Scenario comparison'!Z8=1))="",'Model inputs'!B185=""),"",OR(IF(ISERROR('Scenario comparison'!Z8=1),'Scenario comparison'!Z8=1,IF('Scenario comparison'!Z8="","",'Scenario comparison'!Z8=1)),'Model inputs'!B185))))="",FALSE,IF(IFERROR(IF(ISERROR('Scenario comparison'!Z8=1),'Scenario comparison'!Z8=1,IF('Scenario comparison'!Z8="","",'Scenario comparison'!Z8=1))=TRUE,FALSE),TRUE,IF(IFERROR('Model inputs'!B185=TRUE,FALSE),TRUE,IF(OR(IF(ISERROR('Scenario comparison'!Z8=1),'Scenario comparison'!Z8=1,IF('Scenario comparison'!Z8="","",'Scenario comparison'!Z8=1))="",'Model inputs'!B185=""),"",OR(IF(ISERROR('Scenario comparison'!Z8=1),'Scenario comparison'!Z8=1,IF('Scenario comparison'!Z8="","",'Scenario comparison'!Z8=1)),'Model inputs'!B185))))),1,0)) -> 0 | AD8: =IF(IF(IF(ISERROR('Model inputs'!L60<'Model inputs'!O19),'Model inputs'!L60<'Model inputs'!O19,IF(OR('Model inputs'!L60="",'Model inputs'!O19=""),"",'Model inputs'!L60<'Model inputs'!O19))="",FALSE,IF(ISERROR('Model inputs'!L60<'Model inputs'!O19),'Model inputs'!L60<'Model inputs'!O19,IF(OR('Model inputs'!L60="",'Model inputs'!O19=""),"",'Model inputs'!L60<'Model inputs'!O19))),0,IF(IF(IF(IFERROR('Model inputs'!B208=TRUE,FALSE),TRUE,IF(IFERROR('Model inputs'!B209=TRUE,FALSE),TRUE,IF(OR('Model inputs'!B208="",'Model inputs'!B209=""),"",OR('Model inputs'!B208,'Model inputs'!B209))))="",FALSE,IF(IFERROR('Model inputs'!B208=TRUE,FALSE),TRUE,IF(IFERROR('Model inputs'!B209=TRUE,FALSE),TRUE,IF(OR('Model inputs'!B208="",'Model inputs'!B209=""),"",OR('Model inputs'!B208,'Model inputs'!B209))))),1,0)) -> 0 | AE8: =IF(IF(IF(ISERROR('Model inputs'!L61<'Model inputs'!O20),'Model inputs'!L61<'Model inputs'!O20,IF(OR('Model inputs'!L61="",'Model inputs'!O20=""),"",'Model inputs'!L61<'Model inputs'!O20))="",FALSE,IF(ISERROR('Model inputs'!L61<'Model inputs'!O20),'Model inputs'!L61<'Model inputs'!O20,IF(OR('Model inputs'!L61="",'Model inputs'!O20=""),"",'Model inputs'!L61<'Model inputs'!O20))),0,IF(IF(IF(IFERROR('Model inputs'!B210=TRUE,FALSE),TRUE,IF(IFERROR('Model inputs'!B211=TRUE,FALSE),TRUE,IF(OR('Model inputs'!B210="",'Model inputs'!B211=""),"",OR('Model inputs'!B210,'Model inputs'!B211))))="",FALSE,IF(IFERROR('Model inputs'!B210=TRUE,FALSE),TRUE,IF(IFERROR('Model inputs'!B211=TRUE,FALSE),TRUE,IF(OR('Model inputs'!B210="",'Model inputs'!B211=""),"",OR('Model inputs'!B210,'Model inputs'!B211))))),1,0)) -> 0 | AF8: =IF(IF(IF(ISERROR('Monthly operating and hiring fo'!L9<'Pricing and operating assumptio'!B16),'Monthly operating and hiring fo'!L9<'Pricing and operating assumptio'!B16,IF(OR('Monthly operating and hiring fo'!L9="",'Pricing and operating assumptio'!B16=""),"",'Monthly operating and hiring fo'!L9<'Pricing and operating assumptio'!B16))="",FALSE,IF(ISERROR('Monthly operating and hiring fo'!L9<'Pricing and operating assumptio'!B16),'Monthly operating and hiring fo'!L9<'Pricing and operating assumptio'!B16,IF(OR('Monthly operating and hiring fo'!L9="",'Pricing and operating assumptio'!B16=""),"",'Monthly operating and hiring fo'!L9<'Pricing and operating assumptio'!B16))),0,IF(IF(IF(IFERROR('Model inputs'!B212=TRUE,FALSE),TRUE,IF(IFERROR('Model inputs'!B187=TRUE,FALSE),TRUE,IF(OR('Model inputs'!B212="",'Model inputs'!B187=""),"",OR('Model inputs'!B212,'Model inputs'!B187))))="",FALSE,IF(IFERROR('Model inputs'!B212=TRUE,FALSE),TRUE,IF(IFERROR('Model inputs'!B187=TRUE,FALSE),TRUE,IF(OR('Model inputs'!B212="",'Model inputs'!B187=""),"",OR('Model inputs'!B212,'Model inputs'!B187))))),1,0)) -> 0 | AG8: =IF(IF(IF(ISERROR('Model inputs'!M60<'Model inputs'!O19),'Model inputs'!M60<'Model inputs'!O19,IF(OR('Model inputs'!M60="",'Model inputs'!O19=""),"",'Model inputs'!M60<'Model inputs'!O19))="",FALSE,IF(ISERROR('Model inputs'!M60<'Model inputs'!O19),'Model inputs'!M60<'Model inputs'!O19,IF(OR('Model inputs'!M60="",'Model inputs'!O19=""),"",'Model inputs'!M60<'Model inputs'!O19))),0,IF(IF(IF(IFERROR('Model inputs'!B213=TRUE,FALSE),TRUE,IF(IFERROR('Model inputs'!B214=TRUE,FALSE),TRUE,IF(OR('Model inputs'!B213="",'Model inputs'!B214=""),"",OR('Model inputs'!B213,'Model inputs'!B214))))="",FALSE,IF(IFERROR('Model inputs'!B213=TRUE,FALSE),TRUE,IF(IFERROR('Model inputs'!B214=TRUE,FALSE),TRUE,IF(OR('Model inputs'!B213="",'Model inputs'!B214=""),"",OR('Model inputs'!B213,'Model inputs'!B214))))),1,0)) -> 0 | AH8: =IF(IF(IF(ISERROR('Model inputs'!M61<'Model inputs'!O20),'Model inputs'!M61<'Model inputs'!O20,IF(OR('Model inputs'!M61="",'Model inputs'!O20=""),"",'Model inputs'!M61<'Model inputs'!O20))="",FALSE,IF(ISERROR('Model inputs'!M61<'Model inputs'!O20),'Model inputs'!M61<'Model inputs'!O20,IF(OR('Model inputs'!M61="",'Model inputs'!O20=""),"",'Model inputs'!M61<'Model inputs'!O20))),0,IF(IF(IF(IFERROR('Model inputs'!B215=TRUE,FALSE),TRUE,IF(IFERROR('Model inputs'!B216=TRUE,FALSE),TRUE,IF(OR('Model inputs'!B215="",'Model inputs'!B216=""),"",OR('Model inputs'!B215,'Model inputs'!B216))))="",FALSE,IF(IFERROR('Model inputs'!B215=TRUE,FALSE),TRUE,IF(IFERROR('Model inputs'!B216=TRUE,FALSE),TRUE,IF(OR('Model inputs'!B215="",'Model inputs'!B216=""),"",OR('Model inputs'!B215,'Model inputs'!B216))))),1,0)) -> 0 | AI8: =IF(IF(IF(ISERROR('Monthly operating and hiring fo'!M9<'Pricing and operating assumptio'!B16),'Monthly operating and hiring fo'!M9<'Pricing and operating assumptio'!B16,IF(OR('Monthly operating and hiring fo'!M9="",'Pricing and operating assumptio'!B16=""),"",'Monthly operating and hiring fo'!M9<'Pricing and operating assumptio'!B16))="",FALSE,IF(ISERROR('Monthly operating and hiring fo'!M9<'Pricing and operating assumptio'!B16),'Monthly operating and hiring fo'!M9<'Pricing and operating assumptio'!B16,IF(OR('Monthly operating and hiring fo'!M9="",'Pricing and operating assumptio'!B16=""),"",'Monthly operating and hiring fo'!M9<'Pricing and operating assumptio'!B16))),0,IF(IF(IF(IFERROR('Model inputs'!B217=TRUE,FALSE),TRUE,IF(IFERROR('Model inputs'!B189=TRUE,FALSE),TRUE,IF(OR('Model inputs'!B217="",'Model inputs'!B189=""),"",OR('Model inputs'!B217,'Model inputs'!B189))))="",FALSE,IF(IFERROR('Model inputs'!B217=TRUE,FALSE),TRUE,IF(IFERROR('Model inputs'!B189=TRUE,FALSE),TRUE,IF(OR('Model inputs'!B217="",'Model inputs'!B189=""),"",OR('Model inputs'!B217,'Model inputs'!B189))))),1,0)) -> 0 | AJ8: =IF(IF(IF(ISERROR('Model inputs'!N60<'Model inputs'!O19),'Model inputs'!N60<'Model inputs'!O19,IF(OR('Model inputs'!N60="",'Model inputs'!O19=""),"",'Model inputs'!N60<'Model inputs'!O19))="",FALSE,IF(ISERROR('Model inputs'!N60<'Model inputs'!O19),'Model inputs'!N60<'Model inputs'!O19,IF(OR('Model inputs'!N60="",'Model inputs'!O19=""),"",'Model inputs'!N60<'Model inputs'!O19))),0,IF(IF(IF(IFERROR('Model inputs'!B218=TRUE,FALSE),TRUE,IF(IFERROR('Model inputs'!B219=TRUE,FALSE),TRUE,IF(OR('Model inputs'!B218="",'Model inputs'!B219=""),"",OR('Model inputs'!B218,'Model inputs'!B219))))="",FALSE,IF(IFERROR('Model inputs'!B218=TRUE,FALSE),TRUE,IF(IFERROR('Model inputs'!B219=TRUE,FALSE),TRUE,IF(OR('Model inputs'!B218="",'Model inputs'!B219=""),"",OR('Model inputs'!B218,'Model inputs'!B219))))),1,0)) -> 1 | AK8: =IF(IF(IF(ISERROR('Model inputs'!N61<'Model inputs'!O20),'Model inputs'!N61<'Model inputs'!O20,IF(OR('Model inputs'!N61="",'Model inputs'!O20=""),"",'Model inputs'!N61<'Model inputs'!O20))="",FALSE,IF(ISERROR('Model inputs'!N61<'Model inputs'!O20),'Model inputs'!N61<'Model inputs'!O20,IF(OR('Model inputs'!N61="",'Model inputs'!O20=""),"",'Model inputs'!N61<'Model inputs'!O20))),0,IF(IF(IF(IFERROR('Model inputs'!B220=TRUE,FALSE),TRUE,IF(IFERROR('Model inputs'!B221=TRUE,FALSE),TRUE,IF(OR('Model inputs'!B220="",'Model inputs'!B221=""),"",OR('Model inputs'!B220,'Model inputs'!B221))))="",FALSE,IF(IFERROR('Model inputs'!B220=TRUE,FALSE),TRUE,IF(IFERROR('Model inputs'!B221=TRUE,FALSE),TRUE,IF(OR('Model inputs'!B220="",'Model inputs'!B221=""),"",OR('Model inputs'!B220,'Model inputs'!B221))))),1,0)) -> 0
A9: Cumulative operating cash | B9: =IF(IF(IF(ISERROR('Monthly operating and hiring fo'!B9=1),'Monthly operating and hiring fo'!B9=1,IF('Monthly operating and hiring fo'!B9="","",'Monthly operating and hiring fo'!B9=1))="",FALSE,IF(ISERROR('Monthly operating and hiring fo'!B9=1),'Monthly operating and hiring fo'!B9=1,IF('Monthly operating and hiring fo'!B9="","",'Monthly operating and hiring fo'!B9=1))),IF('Scenario comparison'!B7="","",'Scenario comparison'!B7),'Model inputs'!B15+'Scenario comparison'!B7) -> -154.5 | C9: =IF(IF(IF(ISERROR('Model inputs'!C60=1),'Model inputs'!C60=1,IF('Model inputs'!C60="","",'Model inputs'!C60=1))="",FALSE,IF(ISERROR('Model inputs'!C60=1),'Model inputs'!C60=1,IF('Model inputs'!C60="","",'Model inputs'!C60=1))),IF('Scenario comparison'!C7="","",'Scenario comparison'!C7),'Model inputs'!B16+'Scenario comparison'!C7) -> 29.5 | D9: =IF(IF(IF(ISERROR('Model inputs'!C61=1),'Model inputs'!C61=1,IF('Model inputs'!C61="","",'Model inputs'!C61=1))="",FALSE,IF(ISERROR('Model inputs'!C61=1),'Model inputs'!C61=1,IF('Model inputs'!C61="","",'Model inputs'!C61=1))),IF('Scenario comparison'!D7="","",'Scenario comparison'!D7),'Model inputs'!B17+'Scenario comparison'!D7) -> -154.5 | E9: =IF(IF(IF(ISERROR('Monthly operating and hiring fo'!C9=1),'Monthly operating and hiring fo'!C9=1,IF('Monthly operating and hiring fo'!C9="","",'Monthly operating and hiring fo'!C9=1))="",FALSE,IF(ISERROR('Monthly operating and hiring fo'!C9=1),'Monthly operating and hiring fo'!C9=1,IF('Monthly operating and hiring fo'!C9="","",'Monthly operating and hiring fo'!C9=1))),IF('Scenario comparison'!E7="","",'Scenario comparison'!E7),'Scenario comparison'!B9+'Scenario comparison'!E7) -> -129.5 | F9: =IF(IF(IF(ISERROR('Model inputs'!D60=1),'Model inputs'!D60=1,IF('Model inputs'!D60="","",'Model inputs'!D60=1))="",FALSE,IF(ISERROR('Model inputs'!D60=1),'Model inputs'!D60=1,IF('Model inputs'!D60="","",'Model inputs'!D60=1))),IF('Scenario comparison'!F7="","",'Scenario comparison'!F7),'Scenario comparison'!C9+'Scenario comparison'!F7) -> 238.5 | G9: =IF(IF(IF(ISERROR('Model inputs'!D61=1),'Model inputs'!D61=1,IF('Model inputs'!D61="","",'Model inputs'!D61=1))="",FALSE,IF(ISERROR('Model inputs'!D61=1),'Model inputs'!D61=1,IF('Model inputs'!D61="","",'Model inputs'!D61=1))),IF('Scenario comparison'!G7="","",'Scenario comparison'!G7),'Scenario comparison'!D9+'Scenario comparison'!G7) -> -313.5 | H9: =IF(IF(IF(ISERROR('Monthly operating and hiring fo'!D9=1),'Monthly operating and hiring fo'!D9=1,IF('Monthly operating and hiring fo'!D9="","",'Monthly operating and hiring fo'!D9=1))="",FALSE,IF(ISERROR('Monthly operating and hiring fo'!D9=1),'Monthly operating and hiring fo'!D9=1,IF('Monthly operating and hiring fo'!D9="","",'Monthly operating and hiring fo'!D9=1))),IF('Scenario comparison'!H7="","",'Scenario comparison'!H7),'Scenario comparison'!E9+'Scenario comparison'!H7) -> 73.5 | I9: =IF(IF(IF(ISERROR('Model inputs'!E60=1),'Model inputs'!E60=1,IF('Model inputs'!E60="","",'Model inputs'!E60=1))="",FALSE,IF(ISERROR('Model inputs'!E60=1),'Model inputs'!E60=1,IF('Model inputs'!E60="","",'Model inputs'!E60=1))),IF('Scenario comparison'!I7="","",'Scenario comparison'!I7),'Scenario comparison'!F9+'Scenario comparison'!I7) -> 809.5 | J9: =IF(IF(IF(ISERROR('Model inputs'!E61=1),'Model inputs'!E61=1,IF('Model inputs'!E61="","",'Model inputs'!E61=1))="",FALSE,IF(ISERROR('Model inputs'!E61=1),'Model inputs'!E61=1,IF('Model inputs'!E61="","",'Model inputs'!E61=1))),IF('Scenario comparison'!J7="","",'Scenario comparison'!J7),'Scenario comparison'!G9+'Scenario comparison'!J7) -> -294.5 | K9: =IF(IF(IF(ISERROR('Monthly operating and hiring fo'!E9=1),'Monthly operating and hiring fo'!E9=1,IF('Monthly operating and hiring fo'!E9="","",'Monthly operating and hiring fo'!E9=1))="",FALSE,IF(ISERROR('Monthly operating and hiring fo'!E9=1),'Monthly operating and hiring fo'!E9=1,IF('Monthly operating and hiring fo'!E9="","",'Monthly operating and hiring fo'!E9=1))),IF('Scenario comparison'!K7="","",'Scenario comparison'!K7),'Scenario comparison'!H9+'Scenario comparison'!K7) -> 460.5 | L9: =IF(IF(IF(ISERROR('Model inputs'!F60=1),'Model inputs'!F60=1,IF('Model inputs'!F60="","",'Model inputs'!F60=1))="",FALSE,IF(ISERROR('Model inputs'!F60=1),'Model inputs'!F60=1,IF('Model inputs'!F60="","",'Model inputs'!F60=1))),IF('Scenario comparison'!L7="","",'Scenario comparison'!L7),'Scenario comparison'!I9+'Scenario comparison'!L7) -> 1748.5 | M9: =IF(IF(IF(ISERROR('Model inputs'!F61=1),'Model inputs'!F61=1,IF('Model inputs'!F61="","",'Model inputs'!F61=1))="",FALSE,IF(ISERROR('Model inputs'!F61=1),'Model inputs'!F61=1,IF('Model inputs'!F61="","",'Model inputs'!F61=1))),IF('Scenario comparison'!M7="","",'Scenario comparison'!M7),'Scenario comparison'!J9+'Scenario comparison'!M7) -> -275.5 | N9: =IF(IF(IF(ISERROR('Monthly operating and hiring fo'!F9=1),'Monthly operating and hiring fo'!F9=1,IF('Monthly operating and hiring fo'!F9="","",'Monthly operating and hiring fo'!F9=1))="",FALSE,IF(ISERROR('Monthly operating and hiring fo'!F9=1),'Monthly operating and hiring fo'!F9=1,IF('Monthly operating and hiring fo'!F9="","",'Monthly operating and hiring fo'!F9=1))),IF('Scenario comparison'!N7="","",'Scenario comparison'!N7),'Scenario comparison'!K9+'Scenario comparison'!N7) -> 1031.5 | O9: =IF(IF(IF(ISERROR('Model inputs'!G60=1),'Model inputs'!G60=1,IF('Model inputs'!G60="","",'Model inputs'!G60=1))="",FALSE,IF(ISERROR('Model inputs'!G60=1),'Model inputs'!G60=1,IF('Model inputs'!G60="","",'Model inputs'!G60=1))),IF('Scenario comparison'!O7="","",'Scenario comparison'!O7),'Scenario comparison'!L9+'Scenario comparison'!O7) -> 3239.5 | P9: =IF(IF(IF(ISERROR('Model inputs'!G61=1),'Model inputs'!G61=1,IF('Model inputs'!G61="","",'Model inputs'!G61=1))="",FALSE,IF(ISERROR('Model inputs'!G61=1),'Model inputs'!G61=1,IF('Model inputs'!G61="","",'Model inputs'!G61=1))),IF('Scenario comparison'!P7="","",'Scenario comparison'!P7),'Scenario comparison'!M9+'Scenario comparison'!P7) -> -72.5 | Q9: =IF(IF(IF(ISERROR('Monthly operating and hiring fo'!G9=1),'Monthly operating and hiring fo'!G9=1,IF('Monthly operating and hiring fo'!G9="","",'Monthly operating and hiring fo'!G9=1))="",FALSE,IF(ISERROR('Monthly operating and hiring fo'!G9=1),'Monthly operating and hiring fo'!G9=1,IF('Monthly operating and hiring fo'!G9="","",'Monthly operating and hiring fo'!G9=1))),IF('Scenario comparison'!Q7="","",'Scenario comparison'!Q7),'Scenario comparison'!N9+'Scenario comparison'!Q7) -> 1786.5 | R9: =IF(IF(IF(ISERROR('Model inputs'!H60=1),'Model inputs'!H60=1,IF('Model inputs'!H60="","",'Model inputs'!H60=1))="",FALSE,IF(ISERROR('Model inputs'!H60=1),'Model inputs'!H60=1,IF('Model inputs'!H60="","",'Model inputs'!H60=1))),IF('Scenario comparison'!R7="","",'Scenario comparison'!R7),'Scenario comparison'!O9+'Scenario comparison'!R7) -> 5282.5 | S9: =IF(IF(IF(ISERROR('Model inputs'!H61=1),'Model inputs'!H61=1,IF('Model inputs'!H61="","",'Model inputs'!H61=1))="",FALSE,IF(ISERROR('Model inputs'!H61=1),'Model inputs'!H61=1,IF('Model inputs'!H61="","",'Model inputs'!H61=1))),IF('Scenario comparison'!S7="","",'Scenario comparison'!S7),'Scenario comparison'!P9+'Scenario comparison'!S7) -> 130.5 | T9: =IF(IF(IF(ISERROR('Monthly operating and hiring fo'!H9=1),'Monthly operating and hiring fo'!H9=1,IF('Monthly operating and hiring fo'!H9="","",'Monthly operating and hiring fo'!H9=1))="",FALSE,IF(ISERROR('Monthly operating and hiring fo'!H9=1),'Monthly operating and hiring fo'!H9=1,IF('Monthly operating and hiring fo'!H9="","",'Monthly operating and hiring fo'!H9=1))),IF('Scenario comparison'!T7="","",'Scenario comparison'!T7),'Scenario comparison'!Q9+'Scenario comparison'!T7) -> -906.5 | U9: =IF(IF(IF(ISERROR('Model inputs'!I60=1),'Model inputs'!I60=1,IF('Model inputs'!I60="","",'Model inputs'!I60=1))="",FALSE,IF(ISERROR('Model inputs'!I60=1),'Model inputs'!I60=1,IF('Model inputs'!I60="","",'Model inputs'!I60=1))),IF('Scenario comparison'!U7="","",'Scenario comparison'!U7),'Scenario comparison'!R9+'Scenario comparison'!U7) -> 4245.5 | V9: =IF(IF(IF(ISERROR('Model inputs'!I61=1),'Model inputs'!I61=1,IF('Model inputs'!I61="","",'Model inputs'!I61=1))="",FALSE,IF(ISERROR('Model inputs'!I61=1),'Model inputs'!I61=1,IF('Model inputs'!I61="","",'Model inputs'!I61=1))),IF('Scenario comparison'!V7="","",'Scenario comparison'!V7),'Scenario comparison'!S9+'Scenario comparison'!V7) -> -3482.5 | W9: =IF(IF(IF(ISERROR('Monthly operating and hiring fo'!I9=1),'Monthly operating and hiring fo'!I9=1,IF('Monthly operating and hiring fo'!I9="","",'Monthly operating and hiring fo'!I9=1))="",FALSE,IF(ISERROR('Monthly operating and hiring fo'!I9=1),'Monthly operating and hiring fo'!I9=1,IF('Monthly operating and hiring fo'!I9="","",'Monthly operating and hiring fo'!I9=1))),IF('Scenario comparison'!W7="","",'Scenario comparison'!W7),'Scenario comparison'!T9+'Scenario comparison'!W7) -> -3047.5 | X9: =IF(IF(IF(ISERROR('Model inputs'!J60=1),'Model inputs'!J60=1,IF('Model inputs'!J60="","",'Model inputs'!J60=1))="",FALSE,IF(ISERROR('Model inputs'!J60=1),'Model inputs'!J60=1,IF('Model inputs'!J60="","",'Model inputs'!J60=1))),IF('Scenario comparison'!X7="","",'Scenario comparison'!X7),'Scenario comparison'!U9+'Scenario comparison'!X7) -> 4312.5 | Y9: =IF(IF(IF(ISERROR('Model inputs'!J61=1),'Model inputs'!J61=1,IF('Model inputs'!J61="","",'Model inputs'!J61=1))="",FALSE,IF(ISERROR('Model inputs'!J61=1),'Model inputs'!J61=1,IF('Model inputs'!J61="","",'Model inputs'!J61=1))),IF('Scenario comparison'!Y7="","",'Scenario comparison'!Y7),'Scenario comparison'!V9+'Scenario comparison'!Y7) -> -6911.5 | Z9: =IF(IF(IF(ISERROR('Monthly operating and hiring fo'!J9=1),'Monthly operating and hiring fo'!J9=1,IF('Monthly operating and hiring fo'!J9="","",'Monthly operating and hiring fo'!J9=1))="",FALSE,IF(ISERROR('Monthly operating and hiring fo'!J9=1),'Monthly operating and hiring fo'!J9=1,IF('Monthly operating and hiring fo'!J9="","",'Monthly operating and hiring fo'!J9=1))),IF('Scenario comparison'!Z7="","",'Scenario comparison'!Z7),'Scenario comparison'!W9+'Scenario comparison'!Z7) -> -4452.5 | AA9: =IF(IF(IF(ISERROR('Model inputs'!K60=1),'Model inputs'!K60=1,IF('Model inputs'!K60="","",'Model inputs'!K60=1))="",FALSE,IF(ISERROR('Model inputs'!K60=1),'Model inputs'!K60=1,IF('Model inputs'!K60="","",'Model inputs'!K60=1))),IF('Scenario comparison'!AA7="","",'Scenario comparison'!AA7),'Scenario comparison'!X9+'Scenario comparison'!AA7) -> 5667.5 | AB9: =IF(IF(IF(ISERROR('Model inputs'!K61=1),'Model inputs'!K61=1,IF('Model inputs'!K61="","",'Model inputs'!K61=1))="",FALSE,IF(ISERROR('Model inputs'!K61=1),'Model inputs'!K61=1,IF('Model inputs'!K61="","",'Model inputs'!K61=1))),IF('Scenario comparison'!AB7="","",'Scenario comparison'!AB7),'Scenario comparison'!Y9+'Scenario comparison'!AB7) -> -10156.5 | AC9: =IF(IF(IF(ISERROR('Monthly operating and hiring fo'!K9=1),'Monthly operating and hiring fo'!K9=1,IF('Monthly operating and hiring fo'!K9="","",'Monthly operating and hiring fo'!K9=1))="",FALSE,IF(ISERROR('Monthly operating and hiring fo'!K9=1),'Monthly operating and hiring fo'!K9=1,IF('Monthly operating and hiring fo'!K9="","",'Monthly operating and hiring fo'!K9=1))),IF('Scenario comparison'!AC7="","",'Scenario comparison'!AC7),'Scenario comparison'!Z9+'Scenario comparison'!AC7) -> -4937.5 | AD9: =IF(IF(IF(ISERROR('Model inputs'!L60=1),'Model inputs'!L60=1,IF('Model inputs'!L60="","",'Model inputs'!L60=1))="",FALSE,IF(ISERROR('Model inputs'!L60=1),'Model inputs'!L60=1,IF('Model inputs'!L60="","",'Model inputs'!L60=1))),IF('Scenario comparison'!AD7="","",'Scenario comparison'!AD7),'Scenario comparison'!AA9+'Scenario comparison'!AD7) -> 8862.5 | AE9: =IF(IF(IF(ISERROR('Model inputs'!L61=1),'Model inputs'!L61=1,IF('Model inputs'!L61="","",'Model inputs'!L61=1))="",FALSE,IF(ISERROR('Model inputs'!L61=1),'Model inputs'!L61=1,IF('Model inputs'!L61="","",'Model inputs'!L61=1))),IF('Scenario comparison'!AE7="","",'Scenario comparison'!AE7),'Scenario comparison'!AB9+'Scenario comparison'!AE7) -> -13033.5 | AF9: =IF(IF(IF(ISERROR('Monthly operating and hiring fo'!L9=1),'Monthly operating and hiring fo'!L9=1,IF('Monthly operating and hiring fo'!L9="","",'Monthly operating and hiring fo'!L9=1))="",FALSE,IF(ISERROR('Monthly operating and hiring fo'!L9=1),'Monthly operating and hiring fo'!L9=1,IF('Monthly operating and hiring fo'!L9="","",'Monthly operating and hiring fo'!L9=1))),IF('Scenario comparison'!AF7="","",'Scenario comparison'!AF7),'Scenario comparison'!AC9+'Scenario comparison'!AF7) -> -4502.5 | AG9: =IF(IF(IF(ISERROR('Model inputs'!M60=1),'Model inputs'!M60=1,IF('Model inputs'!M60="","",'Model inputs'!M60=1))="",FALSE,IF(ISERROR('Model inputs'!M60=1),'Model inputs'!M60=1,IF('Model inputs'!M60="","",'Model inputs'!M60=1))),IF('Scenario comparison'!AG7="","",'Scenario comparison'!AG7),'Scenario comparison'!AD9+'Scenario comparison'!AG7) -> 13897.5 | AH9: =IF(IF(IF(ISERROR('Model inputs'!M61=1),'Model inputs'!M61=1,IF('Model inputs'!M61="","",'Model inputs'!M61=1))="",FALSE,IF(ISERROR('Model inputs'!M61=1),'Model inputs'!M61=1,IF('Model inputs'!M61="","",'Model inputs'!M61=1))),IF('Scenario comparison'!AH7="","",'Scenario comparison'!AH7),'Scenario comparison'!AE9+'Scenario comparison'!AH7) -> -15542.5 | AI9: =IF(IF(IF(ISERROR('Monthly operating and hiring fo'!M9=1),'Monthly operating and hiring fo'!M9=1,IF('Monthly operating and hiring fo'!M9="","",'Monthly operating and hiring fo'!M9=1))="",FALSE,IF(ISERROR('Monthly operating and hiring fo'!M9=1),'Monthly operating and hiring fo'!M9=1,IF('Monthly operating and hiring fo'!M9="","",'Monthly operating and hiring fo'!M9=1))),IF('Scenario comparison'!AI7="","",'Scenario comparison'!AI7),'Scenario comparison'!AF9+'Scenario comparison'!AI7) -> -3147.5 | AJ9: =IF(IF(IF(ISERROR('Model inputs'!N60=1),'Model inputs'!N60=1,IF('Model inputs'!N60="","",'Model inputs'!N60=1))="",FALSE,IF(ISERROR('Model inputs'!N60=1),'Model inputs'!N60=1,IF('Model inputs'!N60="","",'Model inputs'!N60=1))),IF('Scenario comparison'!AJ7="","",'Scenario comparison'!AJ7),'Scenario comparison'!AG9+'Scenario comparison'!AJ7) -> 14772.5 | AK9: =IF(IF(IF(ISERROR('Model inputs'!N61=1),'Model inputs'!N61=1,IF('Model inputs'!N61="","",'Model inputs'!N61=1))="",FALSE,IF(ISERROR('Model inputs'!N61=1),'Model inputs'!N61=1,IF('Model inputs'!N61="","",'Model inputs'!N61=1))),IF('Scenario comparison'!AK7="","",'Scenario comparison'!AK7),'Scenario comparison'!AH9+'Scenario comparison'!AK7) -> -17499.5
A10: Minimum funding to date | B10: =IF(IF(IF(ISERROR('Monthly operating and hiring fo'!B9=1),'Monthly operating and hiring fo'!B9=1,IF('Monthly operating and hiring fo'!B9="","",'Monthly operating and hiring fo'!B9=1))="",FALSE,IF(ISERROR('Monthly operating and hiring fo'!B9=1),'Monthly operating and hiring fo'!B9=1,IF('Monthly operating and hiring fo'!B9="","",'Monthly operating and hiring fo'!B9=1))),MAX(0,-'Scenario comparison'!B9),MAX(0,-'Scenario comparison'!B9,'Model inputs'!B44)) -> 154.5 | C10: =IF(IF(IF(ISERROR('Model inputs'!C60=1),'Model inputs'!C60=1,IF('Model inputs'!C60="","",'Model inputs'!C60=1))="",FALSE,IF(ISERROR('Model inputs'!C60=1),'Model inputs'!C60=1,IF('Model inputs'!C60="","",'Model inputs'!C60=1))),MAX(0,-'Scenario comparison'!C9),MAX(0,-'Scenario comparison'!C9,'Model inputs'!B45)) -> 0 | D10: =IF(IF(IF(ISERROR('Model inputs'!C61=1),'Model inputs'!C61=1,IF('Model inputs'!C61="","",'Model inputs'!C61=1))="",FALSE,IF(ISERROR('Model inputs'!C61=1),'Model inputs'!C61=1,IF('Model inputs'!C61="","",'Model inputs'!C61=1))),MAX(0,-'Scenario comparison'!D9),MAX(0,-'Scenario comparison'!D9,'Model inputs'!B46)) -> 154.5 | E10: =IF(IF(IF(ISERROR('Monthly operating and hiring fo'!C9=1),'Monthly operating and hiring fo'!C9=1,IF('Monthly operating and hiring fo'!C9="","",'Monthly operating and hiring fo'!C9=1))="",FALSE,IF(ISERROR('Monthly operating and hiring fo'!C9=1),'Monthly operating and hiring fo'!C9=1,IF('Monthly operating and hiring fo'!C9="","",'Monthly operating and hiring fo'!C9=1))),MAX(0,-'Scenario comparison'!E9),MAX(0,-'Scenario comparison'!E9,'Scenario comparison'!B10)) -> 154.5 | F10: =IF(IF(IF(ISERROR('Model inputs'!D60=1),'Model inputs'!D60=1,IF('Model inputs'!D60="","",'Model inputs'!D60=1))="",FALSE,IF(ISERROR('Model inputs'!D60=1),'Model inputs'!D60=1,IF('Model inputs'!D60="","",'Model inputs'!D60=1))),MAX(0,-'Scenario comparison'!F9),MAX(0,-'Scenario comparison'!F9,'Scenario comparison'!C10)) -> 0 | G10: =IF(IF(IF(ISERROR('Model inputs'!D61=1),'Model inputs'!D61=1,IF('Model inputs'!D61="","",'Model inputs'!D61=1))="",FALSE,IF(ISERROR('Model inputs'!D61=1),'Model inputs'!D61=1,IF('Model inputs'!D61="","",'Model inputs'!D61=1))),MAX(0,-'Scenario comparison'!G9),MAX(0,-'Scenario comparison'!G9,'Scenario comparison'!D10)) -> 313.5 | H10: =IF(IF(IF(ISERROR('Monthly operating and hiring fo'!D9=1),'Monthly operating and hiring fo'!D9=1,IF('Monthly operating and hiring fo'!D9="","",'Monthly operating and hiring fo'!D9=1))="",FALSE,IF(ISERROR('Monthly operating and hiring fo'!D9=1),'Monthly operating and hiring fo'!D9=1,IF('Monthly operating and hiring fo'!D9="","",'Monthly operating and hiring fo'!D9=1))),MAX(0,-'Scenario comparison'!H9),MAX(0,-'Scenario comparison'!H9,'Scenario comparison'!E10)) -> 154.5 | I10: =IF(IF(IF(ISERROR('Model inputs'!E60=1),'Model inputs'!E60=1,IF('Model inputs'!E60="","",'Model inputs'!E60=1))="",FALSE,IF(ISERROR('Model inputs'!E60=1),'Model inputs'!E60=1,IF('Model inputs'!E60="","",'Model inputs'!E60=1))),MAX(0,-'Scenario comparison'!I9),MAX(0,-'Scenario comparison'!I9,'Scenario comparison'!F10)) -> 0 | J10: =IF(IF(IF(ISERROR('Model inputs'!E61=1),'Model inputs'!E61=1,IF('Model inputs'!E61="","",'Model inputs'!E61=1))="",FALSE,IF(ISERROR('Model inputs'!E61=1),'Model inputs'!E61=1,IF('Model inputs'!E61="","",'Model inputs'!E61=1))),MAX(0,-'Scenario comparison'!J9),MAX(0,-'Scenario comparison'!J9,'Scenario comparison'!G10)) -> 313.5 | K10: =IF(IF(IF(ISERROR('Monthly operating and hiring fo'!E9=1),'Monthly operating and hiring fo'!E9=1,IF('Monthly operating and hiring fo'!E9="","",'Monthly operating and hiring fo'!E9=1))="",FALSE,IF(ISERROR('Monthly operating and hiring fo'!E9=1),'Monthly operating and hiring fo'!E9=1,IF('Monthly operating and hiring fo'!E9="","",'Monthly operating and hiring fo'!E9=1))),MAX(0,-'Scenario comparison'!K9),MAX(0,-'Scenario comparison'!K9,'Scenario comparison'!H10)) -> 154.5 | L10: =IF(IF(IF(ISERROR('Model inputs'!F60=1),'Model inputs'!F60=1,IF('Model inputs'!F60="","",'Model inputs'!F60=1))="",FALSE,IF(ISERROR('Model inputs'!F60=1),'Model inputs'!F60=1,IF('Model inputs'!F60="","",'Model inputs'!F60=1))),MAX(0,-'Scenario comparison'!L9),MAX(0,-'Scenario comparison'!L9,'Scenario comparison'!I10)) -> 0 | M10: =IF(IF(IF(ISERROR('Model inputs'!F61=1),'Model inputs'!F61=1,IF('Model inputs'!F61="","",'Model inputs'!F61=1))="",FALSE,IF(ISERROR('Model inputs'!F61=1),'Model inputs'!F61=1,IF('Model inputs'!F61="","",'Model inputs'!F61=1))),MAX(0,-'Scenario comparison'!M9),MAX(0,-'Scenario comparison'!M9,'Scenario comparison'!J10)) -> 313.5 | N10: =IF(IF(IF(ISERROR('Monthly operating and hiring fo'!F9=1),'Monthly operating and hiring fo'!F9=1,IF('Monthly operating and hiring fo'!F9="","",'Monthly operating and hiring fo'!F9=1))="",FALSE,IF(ISERROR('Monthly operating and hiring fo'!F9=1),'Monthly operating and hiring fo'!F9=1,IF('Monthly operating and hiring fo'!F9="","",'Monthly operating and hiring fo'!F9=1))),MAX(0,-'Scenario comparison'!N9),MAX(0,-'Scenario comparison'!N9,'Scenario comparison'!K10)) -> 154.5 | O10: =IF(IF(IF(ISERROR('Model inputs'!G60=1),'Model inputs'!G60=1,IF('Model inputs'!G60="","",'Model inputs'!G60=1))="",FALSE,IF(ISERROR('Model inputs'!G60=1),'Model inputs'!G60=1,IF('Model inputs'!G60="","",'Model inputs'!G60=1))),MAX(0,-'Scenario comparison'!O9),MAX(0,-'Scenario comparison'!O9,'Scenario comparison'!L10)) -> 0 | P10: =IF(IF(IF(ISERROR('Model inputs'!G61=1),'Model inputs'!G61=1,IF('Model inputs'!G61="","",'Model inputs'!G61=1))="",FALSE,IF(ISERROR('Model inputs'!G61=1),'Model inputs'!G61=1,IF('Model inputs'!G61="","",'Model inputs'!G61=1))),MAX(0,-'Scenario comparison'!P9),MAX(0,-'Scenario comparison'!P9,'Scenario comparison'!M10)) -> 313.5 | Q10: =IF(IF(IF(ISERROR('Monthly operating and hiring fo'!G9=1),'Monthly operating and hiring fo'!G9=1,IF('Monthly operating and hiring fo'!G9="","",'Monthly operating and hiring fo'!G9=1))="",FALSE,IF(ISERROR('Monthly operating and hiring fo'!G9=1),'Monthly operating and hiring fo'!G9=1,IF('Monthly operating and hiring fo'!G9="","",'Monthly operating and hiring fo'!G9=1))),MAX(0,-'Scenario comparison'!Q9),MAX(0,-'Scenario comparison'!Q9,'Scenario comparison'!N10)) -> 154.5 | R10: =IF(IF(IF(ISERROR('Model inputs'!H60=1),'Model inputs'!H60=1,IF('Model inputs'!H60="","",'Model inputs'!H60=1))="",FALSE,IF(ISERROR('Model inputs'!H60=1),'Model inputs'!H60=1,IF('Model inputs'!H60="","",'Model inputs'!H60=1))),MAX(0,-'Scenario comparison'!R9),MAX(0,-'Scenario comparison'!R9,'Scenario comparison'!O10)) -> 0 | S10: =IF(IF(IF(ISERROR('Model inputs'!H61=1),'Model inputs'!H61=1,IF('Model inputs'!H61="","",'Model inputs'!H61=1))="",FALSE,IF(ISERROR('Model inputs'!H61=1),'Model inputs'!H61=1,IF('Model inputs'!H61="","",'Model inputs'!H61=1))),MAX(0,-'Scenario comparison'!S9),MAX(0,-'Scenario comparison'!S9,'Scenario comparison'!P10)) -> 313.5 | T10: =IF(IF(IF(ISERROR('Monthly operating and hiring fo'!H9=1),'Monthly operating and hiring fo'!H9=1,IF('Monthly operating and hiring fo'!H9="","",'Monthly operating and hiring fo'!H9=1))="",FALSE,IF(ISERROR('Monthly operating and hiring fo'!H9=1),'Monthly operating and hiring fo'!H9=1,IF('Monthly operating and hiring fo'!H9="","",'Monthly operating and hiring fo'!H9=1))),MAX(0,-'Scenario comparison'!T9),MAX(0,-'Scenario comparison'!T9,'Scenario comparison'!Q10)) -> 906.5 | U10: =IF(IF(IF(ISERROR('Model inputs'!I60=1),'Model inputs'!I60=1,IF('Model inputs'!I60="","",'Model inputs'!I60=1))="",FALSE,IF(ISERROR('Model inputs'!I60=1),'Model inputs'!I60=1,IF('Model inputs'!I60="","",'Model inputs'!I60=1))),MAX(0,-'Scenario comparison'!U9),MAX(0,-'Scenario comparison'!U9,'Scenario comparison'!R10)) -> 0 | V10: =IF(IF(IF(ISERROR('Model inputs'!I61=1),'Model inputs'!I61=1,IF('Model inputs'!I61="","",'Model inputs'!I61=1))="",FALSE,IF(ISERROR('Model inputs'!I61=1),'Model inputs'!I61=1,IF('Model inputs'!I61="","",'Model inputs'!I61=1))),MAX(0,-'Scenario comparison'!V9),MAX(0,-'Scenario comparison'!V9,'Scenario comparison'!S10)) -> 3482.5 | W10: =IF(IF(IF(ISERROR('Monthly operating and hiring fo'!I9=1),'Monthly operating and hiring fo'!I9=1,IF('Monthly operating and hiring fo'!I9="","",'Monthly operating and hiring fo'!I9=1))="",FALSE,IF(ISERROR('Monthly operating and hiring fo'!I9=1),'Monthly operating and hiring fo'!I9=1,IF('Monthly operating and hiring fo'!I9="","",'Monthly operating and hiring fo'!I9=1))),MAX(0,-'Scenario comparison'!W9),MAX(0,-'Scenario comparison'!W9,'Scenario comparison'!T10)) -> 3047.5 | X10: =IF(IF(IF(ISERROR('Model inputs'!J60=1),'Model inputs'!J60=1,IF('Model inputs'!J60="","",'Model inputs'!J60=1))="",FALSE,IF(ISERROR('Model inputs'!J60=1),'Model inputs'!J60=1,IF('Model inputs'!J60="","",'Model inputs'!J60=1))),MAX(0,-'Scenario comparison'!X9),MAX(0,-'Scenario comparison'!X9,'Scenario comparison'!U10)) -> 0 | Y10: =IF(IF(IF(ISERROR('Model inputs'!J61=1),'Model inputs'!J61=1,IF('Model inputs'!J61="","",'Model inputs'!J61=1))="",FALSE,IF(ISERROR('Model inputs'!J61=1),'Model inputs'!J61=1,IF('Model inputs'!J61="","",'Model inputs'!J61=1))),MAX(0,-'Scenario comparison'!Y9),MAX(0,-'Scenario comparison'!Y9,'Scenario comparison'!V10)) -> 6911.5 | Z10: =IF(IF(IF(ISERROR('Monthly operating and hiring fo'!J9=1),'Monthly operating and hiring fo'!J9=1,IF('Monthly operating and hiring fo'!J9="","",'Monthly operating and hiring fo'!J9=1))="",FALSE,IF(ISERROR('Monthly operating and hiring fo'!J9=1),'Monthly operating and hiring fo'!J9=1,IF('Monthly operating and hiring fo'!J9="","",'Monthly operating and hiring fo'!J9=1))),MAX(0,-'Scenario comparison'!Z9),MAX(0,-'Scenario comparison'!Z9,'Scenario comparison'!W10)) -> 4452.5 | AA10: =IF(IF(IF(ISERROR('Model inputs'!K60=1),'Model inputs'!K60=1,IF('Model inputs'!K60="","",'Model inputs'!K60=1))="",FALSE,IF(ISERROR('Model inputs'!K60=1),'Model inputs'!K60=1,IF('Model inputs'!K60="","",'Model inputs'!K60=1))),MAX(0,-'Scenario comparison'!AA9),MAX(0,-'Scenario comparison'!AA9,'Scenario comparison'!X10)) -> 0 | AB10: =IF(IF(IF(ISERROR('Model inputs'!K61=1),'Model inputs'!K61=1,IF('Model inputs'!K61="","",'Model inputs'!K61=1))="",FALSE,IF(ISERROR('Model inputs'!K61=1),'Model inputs'!K61=1,IF('Model inputs'!K61="","",'Model inputs'!K61=1))),MAX(0,-'Scenario comparison'!AB9),MAX(0,-'Scenario comparison'!AB9,'Scenario comparison'!Y10)) -> 10156.5 | AC10: =IF(IF(IF(ISERROR('Monthly operating and hiring fo'!K9=1),'Monthly operating and hiring fo'!K9=1,IF('Monthly operating and hiring fo'!K9="","",'Monthly operating and hiring fo'!K9=1))="",FALSE,IF(ISERROR('Monthly operating and hiring fo'!K9=1),'Monthly operating and hiring fo'!K9=1,IF('Monthly operating and hiring fo'!K9="","",'Monthly operating and hiring fo'!K9=1))),MAX(0,-'Scenario comparison'!AC9),MAX(0,-'Scenario comparison'!AC9,'Scenario comparison'!Z10)) -> 4937.5 | AD10: =IF(IF(IF(ISERROR('Model inputs'!L60=1),'Model inputs'!L60=1,IF('Model inputs'!L60="","",'Model inputs'!L60=1))="",FALSE,IF(ISERROR('Model inputs'!L60=1),'Model inputs'!L60=1,IF('Model inputs'!L60="","",'Model inputs'!L60=1))),MAX(0,-'Scenario comparison'!AD9),MAX(0,-'Scenario comparison'!AD9,'Scenario comparison'!AA10)) -> 0 | AE10: =IF(IF(IF(ISERROR('Model inputs'!L61=1),'Model inputs'!L61=1,IF('Model inputs'!L61="","",'Model inputs'!L61=1))="",FALSE,IF(ISERROR('Model inputs'!L61=1),'Model inputs'!L61=1,IF('Model inputs'!L61="","",'Model inputs'!L61=1))),MAX(0,-'Scenario comparison'!AE9),MAX(0,-'Scenario comparison'!AE9,'Scenario comparison'!AB10)) -> 13033.5 | AF10: =IF(IF(IF(ISERROR('Monthly operating and hiring fo'!L9=1),'Monthly operating and hiring fo'!L9=1,IF('Monthly operating and hiring fo'!L9="","",'Monthly operating and hiring fo'!L9=1))="",FALSE,IF(ISERROR('Monthly operating and hiring fo'!L9=1),'Monthly operating and hiring fo'!L9=1,IF('Monthly operating and hiring fo'!L9="","",'Monthly operating and hiring fo'!L9=1))),MAX(0,-'Scenario comparison'!AF9),MAX(0,-'Scenario comparison'!AF9,'Scenario comparison'!AC10)) -> 4937.5 | AG10: =IF(IF(IF(ISERROR('Model inputs'!M60=1),'Model inputs'!M60=1,IF('Model inputs'!M60="","",'Model inputs'!M60=1))="",FALSE,IF(ISERROR('Model inputs'!M60=1),'Model inputs'!M60=1,IF('Model inputs'!M60="","",'Model inputs'!M60=1))),MAX(0,-'Scenario comparison'!AG9),MAX(0,-'Scenario comparison'!AG9,'Scenario comparison'!AD10)) -> 0 | AH10: =IF(IF(IF(ISERROR('Model inputs'!M61=1),'Model inputs'!M61=1,IF('Model inputs'!M61="","",'Model inputs'!M61=1))="",FALSE,IF(ISERROR('Model inputs'!M61=1),'Model inputs'!M61=1,IF('Model inputs'!M61="","",'Model inputs'!M61=1))),MAX(0,-'Scenario comparison'!AH9),MAX(0,-'Scenario comparison'!AH9,'Scenario comparison'!AE10)) -> 15542.5 | AI10: =IF(IF(IF(ISERROR('Monthly operating and hiring fo'!M9=1),'Monthly operating and hiring fo'!M9=1,IF('Monthly operating and hiring fo'!M9="","",'Monthly operating and hiring fo'!M9=1))="",FALSE,IF(ISERROR('Monthly operating and hiring fo'!M9=1),'Monthly operating and hiring fo'!M9=1,IF('Monthly operating and hiring fo'!M9="","",'Monthly operating and hiring fo'!M9=1))),MAX(0,-'Scenario comparison'!AI9),MAX(0,-'Scenario comparison'!AI9,'Scenario comparison'!AF10)) -> 4937.5 | AJ10: =IF(IF(IF(ISERROR('Model inputs'!N60=1),'Model inputs'!N60=1,IF('Model inputs'!N60="","",'Model inputs'!N60=1))="",FALSE,IF(ISERROR('Model inputs'!N60=1),'Model inputs'!N60=1,IF('Model inputs'!N60="","",'Model inputs'!N60=1))),MAX(0,-'Scenario comparison'!AJ9),MAX(0,-'Scenario comparison'!AJ9,'Scenario comparison'!AG10)) -> 0 | AK10: =IF(IF(IF(ISERROR('Model inputs'!N61=1),'Model inputs'!N61=1,IF('Model inputs'!N61="","",'Model inputs'!N61=1))="",FALSE,IF(ISERROR('Model inputs'!N61=1),'Model inputs'!N61=1,IF('Model inputs'!N61="","",'Model inputs'!N61=1))),MAX(0,-'Scenario comparison'!AK9),MAX(0,-'Scenario comparison'!AK9,'Scenario comparison'!AH10)) -> 17499.5

Sheet Pricing and early-hire stress t
A1: Pricing and early-hire stress tests
A2: Wincheck | 12-month plan · Main Scenario
A4: Variable / dimension | B4: 2026-10 | C4: 2026-11 | D4: 2026-12 | E4: 2027-01 | F4: 2027-02 | G4: 2027-03 | H4: 2027-04 | I4: 2027-05 | J4: 2027-06 | K4: 2027-07 | L4: 2027-08 | M4: 2027-09
A5: Gross profit after hosting | B5: ='Monthly operating and hiring fo'!B18-'Pricing and operating assumptio'!B11 -> -50 | C5: ='Monthly operating and hiring fo'!C18-'Pricing and operating assumptio'!B11 -> 134 | D5: ='Monthly operating and hiring fo'!D18-'Pricing and operating assumptio'!B11 -> 318 | E5: ='Monthly operating and hiring fo'!E18-'Pricing and operating assumptio'!B11 -> 502 | F5: ='Monthly operating and hiring fo'!F18-'Pricing and operating assumptio'!B11 -> 686 | G5: ='Monthly operating and hiring fo'!G18-'Pricing and operating assumptio'!B11 -> 870 | H5: ='Monthly operating and hiring fo'!H18-'Pricing and operating assumptio'!B11 -> 1422 | I5: ='Monthly operating and hiring fo'!I18-'Pricing and operating assumptio'!B11 -> 1974 | J5: ='Monthly operating and hiring fo'!J18-'Pricing and operating assumptio'!B11 -> 2710 | K5: ='Monthly operating and hiring fo'!K18-'Pricing and operating assumptio'!B11 -> 3630 | L5: ='Monthly operating and hiring fo'!L18-'Pricing and operating assumptio'!B11 -> 4550 | M5: ='Monthly operating and hiring fo'!M18-'Pricing and operating assumptio'!B11 -> 5470
A6: Gross margin after hosting | B6: =IFERROR('Pricing and early-hire stress t'!B5/'Monthly operating and hiring fo'!B16,"") | C6: =IFERROR('Pricing and early-hire stress t'!C5/'Monthly operating and hiring fo'!C16,"") -> 0.67336683 | D6: =IFERROR('Pricing and early-hire stress t'!D5/'Monthly operating and hiring fo'!D16,"") -> 0.79899497 | E6: =IFERROR('Pricing and early-hire stress t'!E5/'Monthly operating and hiring fo'!E16,"") -> 0.84087102 | F6: =IFERROR('Pricing and early-hire stress t'!F5/'Monthly operating and hiring fo'!F16,"") -> 0.86180905 | G6: =IFERROR('Pricing and early-hire stress t'!G5/'Monthly operating and hiring fo'!G16,"") -> 0.87437186 | H6: =IFERROR('Pricing and early-hire stress t'!H5/'Monthly operating and hiring fo'!H16,"") -> 0.89321608 | I6: =IFERROR('Pricing and early-hire stress t'!I5/'Monthly operating and hiring fo'!I16,"") -> 0.90178164 | ... M6: =IFERROR('Pricing and early-hire stress t'!M5/'Monthly operating and hiring fo'!M16,"") -> 0.91624791
A7: Cash flow if hired at earliest month | B7: ='Monthly operating and hiring fo'!B23-IF(IF(IF(IF(ISERROR('Monthly operating and hiring fo'!B9>='Pricing and operating assumptio'!B16),'Monthly operating and hiring fo'!B9>='Pricing and operating assumptio'!B16,IF(OR('Monthly operating and hiring fo'!B9="",'Pricing and operating assumptio'!B16=""),"",'Monthly operating and hiring fo'!B9>='Pricing and operating assumptio'!B16))="",FALSE,IF(ISERROR('Monthly operating and hiring fo'!B9>='Pricing and operating assumptio'!B16),'Monthly operating and hiring fo'!B9>='Pricing and operating assumptio'!B16,IF(OR('Monthly operating and hiring fo'!B9="",'Pricing and operating assumptio'!B16=""),"",'Monthly operating and hiring fo'!B9>='Pricing and operating assumptio'!B16))),IF('Pricing and operating assumptio'!B15="","",'Pricing and operating assumptio'!B15),0)="",0,IF(IF(IF(ISERROR('Monthly operating and hiring fo'!B9>='Pricing and operating assumptio'!B16),'Monthly operating and hiring fo'!B9>='Pricing and operating assumptio'!B16,IF(OR('Monthly operating and hiring fo'!B9="",'Pricing and operating assumptio'!B16=""),"",'Monthly operating and hiring fo'!B9>='Pricing and operating assumptio'!B16))="",FALSE,IF(ISERROR('Monthly operating and hiring fo'!B9>='Pricing and operating assumptio'!B16),'Monthly operating and hiring fo'!B9>='Pricing and operating assumptio'!B16,IF(OR('Monthly operating and hiring fo'!B9="",'Pricing and operating assumptio'!B16=""),"",'Monthly operating and hiring fo'!B9>='Pricing and operating assumptio'!B16))),IF('Pricing and operating assumptio'!B15="","",'Pricing and operating assumptio'!B15),0)) -> -154.5 | C7: ='Monthly operating and hiring fo'!C23-IF(IF(IF(IF(ISERROR('Monthly operating and hiring fo'!C9>='Pricing and operating assumptio'!B16),'Monthly operating and hiring fo'!C9>='Pricing and operating assumptio'!B16,IF(OR('Monthly operating and hiring fo'!C9="",'Pricing and operating assumptio'!B16=""),"",'Monthly operating and hiring fo'!C9>='Pricing and operating assumptio'!B16))="",FALSE,IF(ISERROR('Monthly operating and hiring fo'!C9>='Pricing and operating assumptio'!B16),'Monthly operating and hiring fo'!C9>='Pricing and operating assumptio'!B16,IF(OR('Monthly operating and hiring fo'!C9="",'Pricing and operating assumptio'!B16=""),"",'Monthly operating and hiring fo'!C9>='Pricing and operating assumptio'!B16))),IF('Pricing and operating assumptio'!B15="","",'Pricing and operating assumptio'!B15),0)="",0,IF(IF(IF(ISERROR('Monthly operating and hiring fo'!C9>='Pricing and operating assumptio'!B16),'Monthly operating and hiring fo'!C9>='Pricing and operating assumptio'!B16,IF(OR('Monthly operating and hiring fo'!C9="",'Pricing and operating assumptio'!B16=""),"",'Monthly operating and hiring fo'!C9>='Pricing and operating assumptio'!B16))="",FALSE,IF(ISERROR('Monthly operating and hiring fo'!C9>='Pricing and operating assumptio'!B16),'Monthly operating and hiring fo'!C9>='Pricing and operating assumptio'!B16,IF(OR('Monthly operating and hiring fo'!C9="",'Pricing and operating assumptio'!B16=""),"",'Monthly operating and hiring fo'!C9>='Pricing and operating assumptio'!B16))),IF('Pricing and operating assumptio'!B15="","",'Pricing and operating assumptio'!B15),0)) -> 25 | D7: ='Monthly operating and hiring fo'!D23-IF(IF(IF(IF(ISERROR('Monthly operating and hiring fo'!D9>='Pricing and operating assumptio'!B16),'Monthly operating and hiring fo'!D9>='Pricing and operating assumptio'!B16,IF(OR('Monthly operating and hiring fo'!D9="",'Pricing and operating assumptio'!B16=""),"",'Monthly operating and hiring fo'!D9>='Pricing and operating assumptio'!B16))="",FALSE,IF(ISERROR('Monthly operating and hiring fo'!D9>='Pricing and operating assumptio'!B16),'Monthly operating and hiring fo'!D9>='Pricing and operating assumptio'!B16,IF(OR('Monthly operating and hiring fo'!D9="",'Pricing and operating assumptio'!B16=""),"",'Monthly operating and hiring fo'!D9>='Pricing and operating assumptio'!B16))),IF('Pricing and operating assumptio'!B15="","",'Pricing and operating assumptio'!B15),0)="",0,IF(IF(IF(ISERROR('Monthly operating and hiring fo'!D9>='Pricing and operating assumptio'!B16),'Monthly operating and hiring fo'!D9>='Pricing and operating assumptio'!B16,IF(OR('Monthly operating and hiring fo'!D9="",'Pricing and operating assumptio'!B16=""),"",'Monthly operating and hiring fo'!D9>='Pricing and operating assumptio'!B16))="",FALSE,IF(ISERROR('Monthly operating and hiring fo'!D9>='Pricing and operating assumptio'!B16),'Monthly operating and hiring fo'!D9>='Pricing and operating assumptio'!B16,IF(OR('Monthly operating and hiring fo'!D9="",'Pricing and operating assumptio'!B16=""),"",'Monthly operating and hiring fo'!D9>='Pricing and operating assumptio'!B16))),IF('Pricing and operating assumptio'!B15="","",'Pricing and operating assumptio'!B15),0)) -> 203 | E7: ='Monthly operating and hiring fo'!E23-IF(IF(IF(IF(ISERROR('Monthly operating and hiring fo'!E9>='Pricing and operating assumptio'!B16),'Monthly operating and hiring fo'!E9>='Pricing and operating assumptio'!B16,IF(OR('Monthly operating and hiring fo'!E9="",'Pricing and operating assumptio'!B16=""),"",'Monthly operating and hiring fo'!E9>='Pricing and operating assumptio'!B16))="",FALSE,IF(ISERROR('Monthly operating and hiring fo'!E9>='Pricing and operating assumptio'!B16),'Monthly operating and hiring fo'!E9>='Pricing and operating assumptio'!B16,IF(OR('Monthly operating and hiring fo'!E9="",'Pricing and operating assumptio'!B16=""),"",'Monthly operating and hiring fo'!E9>='Pricing and operating assumptio'!B16))),IF('Pricing and operating assumptio'!B15="","",'Pricing and operating assumptio'!B15),0)="",0,IF(IF(IF(ISERROR('Monthly operating and hiring fo'!E9>='Pricing and operating assumptio'!B16),'Monthly operating and hiring fo'!E9>='Pricing and operating assumptio'!B16,IF(OR('Monthly operating and hiring fo'!E9="",'Pricing and operating assumptio'!B16=""),"",'Monthly operating and hiring fo'!E9>='Pricing and operating assumptio'!B16))="",FALSE,IF(ISERROR('Monthly operating and hiring fo'!E9>='Pricing and operating assumptio'!B16),'Monthly operating and hiring fo'!E9>='Pricing and operating assumptio'!B16,IF(OR('Monthly operating and hiring fo'!E9="",'Pricing and operating assumptio'!B16=""),"",'Monthly operating and hiring fo'!E9>='Pricing and operating assumptio'!B16))),IF('Pricing and operating assumptio'!B15="","",'Pricing and operating assumptio'!B15),0)) -> 387 | F7: ='Monthly operating and hiring fo'!F23-IF(IF(IF(IF(ISERROR('Monthly operating and hiring fo'!F9>='Pricing and operating assumptio'!B16),'Monthly operating and hiring fo'!F9>='Pricing and operating assumptio'!B16,IF(OR('Monthly operating and hiring fo'!F9="",'Pricing and operating assumptio'!B16=""),"",'Monthly operating and hiring fo'!F9>='Pricing and operating assumptio'!B16))="",FALSE,IF(ISERROR('Monthly operating and hiring fo'!F9>='Pricing and operating assumptio'!B16),'Monthly operating and hiring fo'!F9>='Pricing and operating assumptio'!B16,IF(OR('Monthly operating and hiring fo'!F9="",'Pricing and operating assumptio'!B16=""),"",'Monthly operating and hiring fo'!F9>='Pricing and operating assumptio'!B16))),IF('Pricing and operating assumptio'!B15="","",'Pricing and operating assumptio'!B15),0)="",0,IF(IF(IF(ISERROR('Monthly operating and hiring fo'!F9>='Pricing and operating assumptio'!B16),'Monthly operating and hiring fo'!F9>='Pricing and operating assumptio'!B16,IF(OR('Monthly operating and hiring fo'!F9="",'Pricing and operating assumptio'!B16=""),"",'Monthly operating and hiring fo'!F9>='Pricing and operating assumptio'!B16))="",FALSE,IF(ISERROR('Monthly operating and hiring fo'!F9>='Pricing and operating assumptio'!B16),'Monthly operating and hiring fo'!F9>='Pricing and operating assumptio'!B16,IF(OR('Monthly operating and hiring fo'!F9="",'Pricing and operating assumptio'!B16=""),"",'Monthly operating and hiring fo'!F9>='Pricing and operating assumptio'!B16))),IF('Pricing and operating assumptio'!B15="","",'Pricing and operating assumptio'!B15),0)) -> 571 | G7: ='Monthly operating and hiring fo'!G23-IF(IF(IF(IF(ISERROR('Monthly operating and hiring fo'!G9>='Pricing and operating assumptio'!B16),'Monthly operating and hiring fo'!G9>='Pricing and operating assumptio'!B16,IF(OR('Monthly operating and hiring fo'!G9="",'Pricing and operating assumptio'!B16=""),"",'Monthly operating and hiring fo'!G9>='Pricing and operating assumptio'!B16))="",FALSE,IF(ISERROR('Monthly operating and hiring fo'!G9>='Pricing and operating assumptio'!B16),'Monthly operating and hiring fo'!G9>='Pricing and operating assumptio'!B16,IF(OR('Monthly operating and hiring fo'!G9="",'Pricing and operating assumptio'!B16=""),"",'Monthly operating and hiring fo'!G9>='Pricing and operating assumptio'!B16))),IF('Pricing and operating assumptio'!B15="","",'Pricing and operating assumptio'!B15),0)="",0,IF(IF(IF(ISERROR('Monthly operating and hiring fo'!G9>='Pricing and operating assumptio'!B16),'Monthly operating and hiring fo'!G9>='Pricing and operating assumptio'!B16,IF(OR('Monthly operating and hiring fo'!G9="",'Pricing and operating assumptio'!B16=""),"",'Monthly operating and hiring fo'!G9>='Pricing and operating assumptio'!B16))="",FALSE,IF(ISERROR('Monthly operating and hiring fo'!G9>='Pricing and operating assumptio'!B16),'Monthly operating and hiring fo'!G9>='Pricing and operating assumptio'!B16,IF(OR('Monthly operating and hiring fo'!G9="",'Pricing and operating assumptio'!B16=""),"",'Monthly operating and hiring fo'!G9>='Pricing and operating assumptio'!B16))),IF('Pricing and operating assumptio'!B15="","",'Pricing and operating assumptio'!B15),0)) -> 755 | H7: ='Monthly operating and hiring fo'!H23-IF(IF(IF(IF(ISERROR('Monthly operating and hiring fo'!H9>='Pricing and operating assumptio'!B16),'Monthly operating and hiring fo'!H9>='Pricing and operating assumptio'!B16,IF(OR('Monthly operating and hiring fo'!H9="",'Pricing and operating assumptio'!B16=""),"",'Monthly operating and hiring fo'!H9>='Pricing and operating assumptio'!B16))="",FALSE,IF(ISERROR('Monthly operating and hiring fo'!H9>='Pricing and operating assumptio'!B16),'Monthly operating and hiring fo'!H9>='Pricing and operating assumptio'!B16,IF(OR('Monthly operating and hiring fo'!H9="",'Pricing and operating assumptio'!B16=""),"",'Monthly operating and hiring fo'!H9>='Pricing and operating assumptio'!B16))),IF('Pricing and operating assumptio'!B15="","",'Pricing and operating assumptio'!B15),0)="",0,IF(IF(IF(ISERROR('Monthly operating and hiring fo'!H9>='Pricing and operating assumptio'!B16),'Monthly operating and hiring fo'!H9>='Pricing and operating assumptio'!B16,IF(OR('Monthly operating and hiring fo'!H9="",'Pricing and operating assumptio'!B16=""),"",'Monthly operating and hiring fo'!H9>='Pricing and operating assumptio'!B16))="",FALSE,IF(ISERROR('Monthly operating and hiring fo'!H9>='Pricing and operating assumptio'!B16),'Monthly operating and hiring fo'!H9>='Pricing and operating assumptio'!B16,IF(OR('Monthly operating and hiring fo'!H9="",'Pricing and operating assumptio'!B16=""),"",'Monthly operating and hiring fo'!H9>='Pricing and operating assumptio'!B16))),IF('Pricing and operating assumptio'!B15="","",'Pricing and operating assumptio'!B15),0)) -> -2693 | I7: ='Monthly operating and hiring fo'!I23-IF(IF(IF(IF(ISERROR('Monthly operating and hiring fo'!I9>='Pricing and operating assumptio'!B16),'Monthly operating and hiring fo'!I9>='Pricing and operating assumptio'!B16,IF(OR('Monthly operating and hiring fo'!I9="",'Pricing and operating assumptio'!B16=""),"",'Monthly operating and hiring fo'!I9>='Pricing and operating assumptio'!B16))="",FALSE,IF(ISERROR('Monthly operating and hiring fo'!I9>='Pricing and operating assumptio'!B16),'Monthly operating and hiring fo'!I9>='Pricing and operating assumptio'!B16,IF(OR('Monthly operating and hiring fo'!I9="",'Pricing and operating assumptio'!B16=""),"",'Monthly operating and hiring fo'!I9>='Pricing and operating assumptio'!B16))),IF('Pricing and operating assumptio'!B15="","",'Pricing and operating assumptio'!B15),0)="",0,IF(IF(IF(ISERROR('Monthly operating and hiring fo'!I9>='Pricing and operating assumptio'!B16),'Monthly operating and hiring fo'!I9>='Pricing and operating assumptio'!B16,IF(OR('Monthly operating and hiring fo'!I9="",'Pricing and operating assumptio'!B16=""),"",'Monthly operating and hiring fo'!I9>='Pricing and operating assumptio'!B16))="",FALSE,IF(ISERROR('Monthly operating and hiring fo'!I9>='Pricing and operating assumptio'!B16),'Monthly operating and hiring fo'!I9>='Pricing and operating assumptio'!B16,IF(OR('Monthly operating and hiring fo'!I9="",'Pricing and operating assumptio'!B16=""),"",'Monthly operating and hiring fo'!I9>='Pricing and operating assumptio'!B16))),IF('Pricing and operating assumptio'!B15="","",'Pricing and operating assumptio'!B15),0)) -> -2141 | J7: ='Monthly operating and hiring fo'!J23-IF(IF(IF(IF(ISERROR('Monthly operating and hiring fo'!J9>='Pricing and operating assumptio'!B16),'Monthly operating and hiring fo'!J9>='Pricing and operating assumptio'!B16,IF(OR('Monthly operating and hiring fo'!J9="",'Pricing and operating assumptio'!B16=""),"",'Monthly operating and hiring fo'!J9>='Pricing and operating assumptio'!B16))="",FALSE,IF(ISERROR('Monthly operating and hiring fo'!J9>='Pricing and operating assumptio'!B16),'Monthly operating and hiring fo'!J9>='Pricing and operating assumptio'!B16,IF(OR('Monthly operating and hiring fo'!J9="",'Pricing and operating assumptio'!B16=""),"",'Monthly operating and hiring fo'!J9>='Pricing and operating assumptio'!B16))),IF('Pricing and operating assumptio'!B15="","",'Pricing and operating assumptio'!B15),0)="",0,IF(IF(IF(ISERROR('Monthly operating and hiring fo'!J9>='Pricing and operating assumptio'!B16),'Monthly operating and hiring fo'!J9>='Pricing and operating assumptio'!B16,IF(OR('Monthly operating and hiring fo'!J9="",'Pricing and operating assumptio'!B16=""),"",'Monthly operating and hiring fo'!J9>='Pricing and operating assumptio'!B16))="",FALSE,IF(ISERROR('Monthly operating and hiring fo'!J9>='Pricing and operating assumptio'!B16),'Monthly operating and hiring fo'!J9>='Pricing and operating assumptio'!B16,IF(OR('Monthly operating and hiring fo'!J9="",'Pricing and operating assumptio'!B16=""),"",'Monthly operating and hiring fo'!J9>='Pricing and operating assumptio'!B16))),IF('Pricing and operating assumptio'!B15="","",'Pricing and operating assumptio'!B15),0)) -> -1405 | K7: ='Monthly operating and hiring fo'!K23-IF(IF(IF(IF(ISERROR('Monthly operating and hiring fo'!K9>='Pricing and operating assumptio'!B16),'Monthly operating and hiring fo'!K9>='Pricing and operating assumptio'!B16,IF(OR('Monthly operating and hiring fo'!K9="",'Pricing and operating assumptio'!B16=""),"",'Monthly operating and hiring fo'!K9>='Pricing and operating assumptio'!B16))="",FALSE,IF(ISERROR('Monthly operating and hiring fo'!K9>='Pricing and operating assumptio'!B16),'Monthly operating and hiring fo'!K9>='Pricing and operating assumptio'!B16,IF(OR('Monthly operating and hiring fo'!K9="",'Pricing and operating assumptio'!B16=""),"",'Monthly operating and hiring fo'!K9>='Pricing and operating assumptio'!B16))),IF('Pricing and operating assumptio'!B15="","",'Pricing and operating assumptio'!B15),0)="",0,IF(IF(IF(ISERROR('Monthly operating and hiring fo'!K9>='Pricing and operating assumptio'!B16),'Monthly operating and hiring fo'!K9>='Pricing and operating assumptio'!B16,IF(OR('Monthly operating and hiring fo'!K9="",'Pricing and operating assumptio'!B16=""),"",'Monthly operating and hiring fo'!K9>='Pricing and operating assumptio'!B16))="",FALSE,IF(ISERROR('Monthly operating and hiring fo'!K9>='Pricing and operating assumptio'!B16),'Monthly operating and hiring fo'!K9>='Pricing and operating assumptio'!B16,IF(OR('Monthly operating and hiring fo'!K9="",'Pricing and operating assumptio'!B16=""),"",'Monthly operating and hiring fo'!K9>='Pricing and operating assumptio'!B16))),IF('Pricing and operating assumptio'!B15="","",'Pricing and operating assumptio'!B15),0)) -> -6485 | L7: ='Monthly operating and hiring fo'!L23-IF(IF(IF(IF(ISERROR('Monthly operating and hiring fo'!L9>='Pricing and operating assumptio'!B16),'Monthly operating and hiring fo'!L9>='Pricing and operating assumptio'!B16,IF(OR('Monthly operating and hiring fo'!L9="",'Pricing and operating assumptio'!B16=""),"",'Monthly operating and hiring fo'!L9>='Pricing and operating assumptio'!B16))="",FALSE,IF(ISERROR('Monthly operating and hiring fo'!L9>='Pricing and operating assumptio'!B16),'Monthly operating and hiring fo'!L9>='Pricing and operating assumptio'!B16,IF(OR('Monthly operating and hiring fo'!L9="",'Pricing and operating assumptio'!B16=""),"",'Monthly operating and hiring fo'!L9>='Pricing and operating assumptio'!B16))),IF('Pricing and operating assumptio'!B15="","",'Pricing and operating assumptio'!B15),0)="",0,IF(IF(IF(ISERROR('Monthly operating and hiring fo'!L9>='Pricing and operating assumptio'!B16),'Monthly operating and hiring fo'!L9>='Pricing and operating assumptio'!B16,IF(OR('Monthly operating and hiring fo'!L9="",'Pricing and operating assumptio'!B16=""),"",'Monthly operating and hiring fo'!L9>='Pricing and operating assumptio'!B16))="",FALSE,IF(ISERROR('Monthly operating and hiring fo'!L9>='Pricing and operating assumptio'!B16),'Monthly operating and hiring fo'!L9>='Pricing and operating assumptio'!B16,IF(OR('Monthly operating and hiring fo'!L9="",'Pricing and operating assumptio'!B16=""),"",'Monthly operating and hiring fo'!L9>='Pricing and operating assumptio'!B16))),IF('Pricing and operating assumptio'!B15="","",'Pricing and operating assumptio'!B15),0)) -> -5565 | M7: ='Monthly operating and hiring fo'!M23-IF(IF(IF(IF(ISERROR('Monthly operating and hiring fo'!M9>='Pricing and operating assumptio'!B16),'Monthly operating and hiring fo'!M9>='Pricing and operating assumptio'!B16,IF(OR('Monthly operating and hiring fo'!M9="",'Pricing and operating assumptio'!B16=""),"",'Monthly operating and hiring fo'!M9>='Pricing and operating assumptio'!B16))="",FALSE,IF(ISERROR('Monthly operating and hiring fo'!M9>='Pricing and operating assumptio'!B16),'Monthly operating and hiring fo'!M9>='Pricing and operating assumptio'!B16,IF(OR('Monthly operating and hiring fo'!M9="",'Pricing and operating assumptio'!B16=""),"",'Monthly operating and hiring fo'!M9>='Pricing and operating assumptio'!B16))),IF('Pricing and operating assumptio'!B15="","",'Pricing and operating assumptio'!B15),0)="",0,IF(IF(IF(ISERROR('Monthly operating and hiring fo'!M9>='Pricing and operating assumptio'!B16),'Monthly operating and hiring fo'!M9>='Pricing and operating assumptio'!B16,IF(OR('Monthly operating and hiring fo'!M9="",'Pricing and operating assumptio'!B16=""),"",'Monthly operating and hiring fo'!M9>='Pricing and operating assumptio'!B16))="",FALSE,IF(ISERROR('Monthly operating and hiring fo'!M9>='Pricing and operating assumptio'!B16),'Monthly operating and hiring fo'!M9>='Pricing and operating assumptio'!B16,IF(OR('Monthly operating and hiring fo'!M9="",'Pricing and operating assumptio'!B16=""),"",'Monthly operating and hiring fo'!M9>='Pricing and operating assumptio'!B16))),IF('Pricing and operating assumptio'!B15="","",'Pricing and operating assumptio'!B15),0)) -> -4645
A8: Cumulative cash if hired at earliest month | B8: =IF(IF(IF(ISERROR('Monthly operating and hiring fo'!B9=1),'Monthly operating and hiring fo'!B9=1,IF('Monthly operating and hiring fo'!B9="","",'Monthly operating and hiring fo'!B9=1))="",FALSE,IF(ISERROR('Monthly operating and hiring fo'!B9=1),'Monthly operating and hiring fo'!B9=1,IF('Monthly operating and hiring fo'!B9="","",'Monthly operating and hiring fo'!B9=1))),IF('Pricing and early-hire stress t'!B7="","",'Pricing and early-hire stress t'!B7),'Model inputs'!B14+'Pricing and early-hire stress t'!B7) -> -154.5 | C8: =IF(IF(IF(ISERROR('Monthly operating and hiring fo'!C9=1),'Monthly operating and hiring fo'!C9=1,IF('Monthly operating and hiring fo'!C9="","",'Monthly operating and hiring fo'!C9=1))="",FALSE,IF(ISERROR('Monthly operating and hiring fo'!C9=1),'Monthly operating and hiring fo'!C9=1,IF('Monthly operating and hiring fo'!C9="","",'Monthly operating and hiring fo'!C9=1))),IF('Pricing and early-hire stress t'!C7="","",'Pricing and early-hire stress t'!C7),'Pricing and early-hire stress t'!B8+'Pricing and early-hire stress t'!C7) -> -129.5 | D8: =IF(IF(IF(ISERROR('Monthly operating and hiring fo'!D9=1),'Monthly operating and hiring fo'!D9=1,IF('Monthly operating and hiring fo'!D9="","",'Monthly operating and hiring fo'!D9=1))="",FALSE,IF(ISERROR('Monthly operating and hiring fo'!D9=1),'Monthly operating and hiring fo'!D9=1,IF('Monthly operating and hiring fo'!D9="","",'Monthly operating and hiring fo'!D9=1))),IF('Pricing and early-hire stress t'!D7="","",'Pricing and early-hire stress t'!D7),'Pricing and early-hire stress t'!C8+'Pricing and early-hire stress t'!D7) -> 73.5 | E8: =IF(IF(IF(ISERROR('Monthly operating and hiring fo'!E9=1),'Monthly operating and hiring fo'!E9=1,IF('Monthly operating and hiring fo'!E9="","",'Monthly operating and hiring fo'!E9=1))="",FALSE,IF(ISERROR('Monthly operating and hiring fo'!E9=1),'Monthly operating and hiring fo'!E9=1,IF('Monthly operating and hiring fo'!E9="","",'Monthly operating and hiring fo'!E9=1))),IF('Pricing and early-hire stress t'!E7="","",'Pricing and early-hire stress t'!E7),'Pricing and early-hire stress t'!D8+'Pricing and early-hire stress t'!E7) -> 460.5 | F8: =IF(IF(IF(ISERROR('Monthly operating and hiring fo'!F9=1),'Monthly operating and hiring fo'!F9=1,IF('Monthly operating and hiring fo'!F9="","",'Monthly operating and hiring fo'!F9=1))="",FALSE,IF(ISERROR('Monthly operating and hiring fo'!F9=1),'Monthly operating and hiring fo'!F9=1,IF('Monthly operating and hiring fo'!F9="","",'Monthly operating and hiring fo'!F9=1))),IF('Pricing and early-hire stress t'!F7="","",'Pricing and early-hire stress t'!F7),'Pricing and early-hire stress t'!E8+'Pricing and early-hire stress t'!F7) -> 1031.5 | G8: =IF(IF(IF(ISERROR('Monthly operating and hiring fo'!G9=1),'Monthly operating and hiring fo'!G9=1,IF('Monthly operating and hiring fo'!G9="","",'Monthly operating and hiring fo'!G9=1))="",FALSE,IF(ISERROR('Monthly operating and hiring fo'!G9=1),'Monthly operating and hiring fo'!G9=1,IF('Monthly operating and hiring fo'!G9="","",'Monthly operating and hiring fo'!G9=1))),IF('Pricing and early-hire stress t'!G7="","",'Pricing and early-hire stress t'!G7),'Pricing and early-hire stress t'!F8+'Pricing and early-hire stress t'!G7) -> 1786.5 | H8: =IF(IF(IF(ISERROR('Monthly operating and hiring fo'!H9=1),'Monthly operating and hiring fo'!H9=1,IF('Monthly operating and hiring fo'!H9="","",'Monthly operating and hiring fo'!H9=1))="",FALSE,IF(ISERROR('Monthly operating and hiring fo'!H9=1),'Monthly operating and hiring fo'!H9=1,IF('Monthly operating and hiring fo'!H9="","",'Monthly operating and hiring fo'!H9=1))),IF('Pricing and early-hire stress t'!H7="","",'Pricing and early-hire stress t'!H7),'Pricing and early-hire stress t'!G8+'Pricing and early-hire stress t'!H7) -> -906.5 | I8: =IF(IF(IF(ISERROR('Monthly operating and hiring fo'!I9=1),'Monthly operating and hiring fo'!I9=1,IF('Monthly operating and hiring fo'!I9="","",'Monthly operating and hiring fo'!I9=1))="",FALSE,IF(ISERROR('Monthly operating and hiring fo'!I9=1),'Monthly operating and hiring fo'!I9=1,IF('Monthly operating and hiring fo'!I9="","",'Monthly operating and hiring fo'!I9=1))),IF('Pricing and early-hire stress t'!I7="","",'Pricing and early-hire stress t'!I7),'Pricing and early-hire stress t'!H8+'Pricing and early-hire stress t'!I7) -> -3047.5 | J8: =IF(IF(IF(ISERROR('Monthly operating and hiring fo'!J9=1),'Monthly operating and hiring fo'!J9=1,IF('Monthly operating and hiring fo'!J9="","",'Monthly operating and hiring fo'!J9=1))="",FALSE,IF(ISERROR('Monthly operating and hiring fo'!J9=1),'Monthly operating and hiring fo'!J9=1,IF('Monthly operating and hiring fo'!J9="","",'Monthly operating and hiring fo'!J9=1))),IF('Pricing and early-hire stress t'!J7="","",'Pricing and early-hire stress t'!J7),'Pricing and early-hire stress t'!I8+'Pricing and early-hire stress t'!J7) -> -4452.5 | ... M8: =IF(IF(IF(ISERROR('Monthly operating and hiring fo'!M9=1),'Monthly operating and hiring fo'!M9=1,IF('Monthly operating and hiring fo'!M9="","",'Monthly operating and hiring fo'!M9=1))="",FALSE,IF(ISERROR('Monthly operating and hiring fo'!M9=1),'Monthly operating and hiring fo'!M9=1,IF('Monthly operating and hiring fo'!M9="","",'Monthly operating and hiring fo'!M9=1))),IF('Pricing and early-hire stress t'!M7="","",'Pricing and early-hire stress t'!M7),'Pricing and early-hire stress t'!L8+'Pricing and early-hire stress t'!M7) -> -21147.5
A9: Funding if hired at earliest month | B9: =IF(IF(IF(ISERROR('Monthly operating and hiring fo'!B9=1),'Monthly operating and hiring fo'!B9=1,IF('Monthly operating and hiring fo'!B9="","",'Monthly operating and hiring fo'!B9=1))="",FALSE,IF(ISERROR('Monthly operating and hiring fo'!B9=1),'Monthly operating and hiring fo'!B9=1,IF('Monthly operating and hiring fo'!B9="","",'Monthly operating and hiring fo'!B9=1))),MAX(0,-'Pricing and early-hire stress t'!B8),MAX(0,-'Pricing and early-hire stress t'!B8,'Model inputs'!B41)) -> 154.5 | C9: =IF(IF(IF(ISERROR('Monthly operating and hiring fo'!C9=1),'Monthly operating and hiring fo'!C9=1,IF('Monthly operating and hiring fo'!C9="","",'Monthly operating and hiring fo'!C9=1))="",FALSE,IF(ISERROR('Monthly operating and hiring fo'!C9=1),'Monthly operating and hiring fo'!C9=1,IF('Monthly operating and hiring fo'!C9="","",'Monthly operating and hiring fo'!C9=1))),MAX(0,-'Pricing and early-hire stress t'!C8),MAX(0,-'Pricing and early-hire stress t'!C8,'Pricing and early-hire stress t'!B9)) -> 154.5 | D9: =IF(IF(IF(ISERROR('Monthly operating and hiring fo'!D9=1),'Monthly operating and hiring fo'!D9=1,IF('Monthly operating and hiring fo'!D9="","",'Monthly operating and hiring fo'!D9=1))="",FALSE,IF(ISERROR('Monthly operating and hiring fo'!D9=1),'Monthly operating and hiring fo'!D9=1,IF('Monthly operating and hiring fo'!D9="","",'Monthly operating and hiring fo'!D9=1))),MAX(0,-'Pricing and early-hire stress t'!D8),MAX(0,-'Pricing and early-hire stress t'!D8,'Pricing and early-hire stress t'!C9)) -> 154.5 | E9: =IF(IF(IF(ISERROR('Monthly operating and hiring fo'!E9=1),'Monthly operating and hiring fo'!E9=1,IF('Monthly operating and hiring fo'!E9="","",'Monthly operating and hiring fo'!E9=1))="",FALSE,IF(ISERROR('Monthly operating and hiring fo'!E9=1),'Monthly operating and hiring fo'!E9=1,IF('Monthly operating and hiring fo'!E9="","",'Monthly operating and hiring fo'!E9=1))),MAX(0,-'Pricing and early-hire stress t'!E8),MAX(0,-'Pricing and early-hire stress t'!E8,'Pricing and early-hire stress t'!D9)) -> 154.5 | F9: =IF(IF(IF(ISERROR('Monthly operating and hiring fo'!F9=1),'Monthly operating and hiring fo'!F9=1,IF('Monthly operating and hiring fo'!F9="","",'Monthly operating and hiring fo'!F9=1))="",FALSE,IF(ISERROR('Monthly operating and hiring fo'!F9=1),'Monthly operating and hiring fo'!F9=1,IF('Monthly operating and hiring fo'!F9="","",'Monthly operating and hiring fo'!F9=1))),MAX(0,-'Pricing and early-hire stress t'!F8),MAX(0,-'Pricing and early-hire stress t'!F8,'Pricing and early-hire stress t'!E9)) -> 154.5 | G9: =IF(IF(IF(ISERROR('Monthly operating and hiring fo'!G9=1),'Monthly operating and hiring fo'!G9=1,IF('Monthly operating and hiring fo'!G9="","",'Monthly operating and hiring fo'!G9=1))="",FALSE,IF(ISERROR('Monthly operating and hiring fo'!G9=1),'Monthly operating and hiring fo'!G9=1,IF('Monthly operating and hiring fo'!G9="","",'Monthly operating and hiring fo'!G9=1))),MAX(0,-'Pricing and early-hire stress t'!G8),MAX(0,-'Pricing and early-hire stress t'!G8,'Pricing and early-hire stress t'!F9)) -> 154.5 | H9: =IF(IF(IF(ISERROR('Monthly operating and hiring fo'!H9=1),'Monthly operating and hiring fo'!H9=1,IF('Monthly operating and hiring fo'!H9="","",'Monthly operating and hiring fo'!H9=1))="",FALSE,IF(ISERROR('Monthly operating and hiring fo'!H9=1),'Monthly operating and hiring fo'!H9=1,IF('Monthly operating and hiring fo'!H9="","",'Monthly operating and hiring fo'!H9=1))),MAX(0,-'Pricing and early-hire stress t'!H8),MAX(0,-'Pricing and early-hire stress t'!H8,'Pricing and early-hire stress t'!G9)) -> 906.5 | I9: =IF(IF(IF(ISERROR('Monthly operating and hiring fo'!I9=1),'Monthly operating and hiring fo'!I9=1,IF('Monthly operating and hiring fo'!I9="","",'Monthly operating and hiring fo'!I9=1))="",FALSE,IF(ISERROR('Monthly operating and hiring fo'!I9=1),'Monthly operating and hiring fo'!I9=1,IF('Monthly operating and hiring fo'!I9="","",'Monthly operating and hiring fo'!I9=1))),MAX(0,-'Pricing and early-hire stress t'!I8),MAX(0,-'Pricing and early-hire stress t'!I8,'Pricing and early-hire stress t'!H9)) -> 3047.5 | J9: =IF(IF(IF(ISERROR('Monthly operating and hiring fo'!J9=1),'Monthly operating and hiring fo'!J9=1,IF('Monthly operating and hiring fo'!J9="","",'Monthly operating and hiring fo'!J9=1))="",FALSE,IF(ISERROR('Monthly operating and hiring fo'!J9=1),'Monthly operating and hiring fo'!J9=1,IF('Monthly operating and hiring fo'!J9="","",'Monthly operating and hiring fo'!J9=1))),MAX(0,-'Pricing and early-hire stress t'!J8),MAX(0,-'Pricing and early-hire stress t'!J8,'Pricing and early-hire stress t'!I9)) -> 4452.5 | ... M9: =IF(IF(IF(ISERROR('Monthly operating and hiring fo'!M9=1),'Monthly operating and hiring fo'!M9=1,IF('Monthly operating and hiring fo'!M9="","",'Monthly operating and hiring fo'!M9=1))="",FALSE,IF(ISERROR('Monthly operating and hiring fo'!M9=1),'Monthly operating and hiring fo'!M9=1,IF('Monthly operating and hiring fo'!M9="","",'Monthly operating and hiring fo'!M9=1))),MAX(0,-'Pricing and early-hire stress t'!M8),MAX(0,-'Pricing and early-hire stress t'!M8,'Pricing and early-hire stress t'!L9)) -> 21147.5

Sheet Model inputs
A1: Model inputs
A2: Integration values are aggregated snapshots; raw source records are not included.
A4: Variables
A5: Variable / segment | B5: 2026-09 | C5: 2026-10 | D5: 2026-11 | E5: 2026-12 | F5: 2027-01 | G5: 2027-02 | H5: 2027-03 | I5: 2027-04 | J5: 2027-05 | K5: 2027-06 | L5: 2027-07 | M5: 2027-08 | N5: 2027-09 | O5: Value | P5: 2026-01 | Q5: 2026-02 | R5: 2026-03 | S5: 2026-04 | T5: 2026-05 | U5: 2026-06 | V5: 2026-07 | W5: 2026-08
A6: Cash flow before hire · Main Scenario | B6: ='Model inputs'!B42-'Model inputs'!B38-'Model inputs'!B33-'Model inputs'!B35 -> #VALUE! | C6: ='Model inputs'!C42-'Model inputs'!C38-'Model inputs'!C33-'Model inputs'!C35 -> -154.5 | D6: ='Model inputs'!D42-'Model inputs'!D38-'Model inputs'!D33-'Model inputs'!D35 -> 25 | E6: ='Model inputs'!E42-'Model inputs'!E38-'Model inputs'!E33-'Model inputs'!E35 -> 203 | F6: ='Model inputs'!F42-'Model inputs'!F38-'Model inputs'!F33-'Model inputs'!F35 -> 387 | G6: ='Model inputs'!G42-'Model inputs'!G38-'Model inputs'!G33-'Model inputs'!G35 -> 571 | H6: ='Model inputs'!H42-'Model inputs'!H38-'Model inputs'!H33-'Model inputs'!H35 -> 755 | I6: ='Model inputs'!I42-'Model inputs'!I38-'Model inputs'!I33-'Model inputs'!I35 -> -2693 | ... N6: ='Model inputs'!N42-'Model inputs'!N38-'Model inputs'!N33-'Model inputs'!N35 -> 1355
A7: Cash flow before hire · Upside | B7: ='Model inputs'!B87-'Model inputs'!B84-'Model inputs'!B80-'Model inputs'!B82 -> #VALUE! | C7: ='Model inputs'!C87-'Model inputs'!C84-'Model inputs'!C80-'Model inputs'!C82 -> 29.5 | D7: ='Model inputs'!D87-'Model inputs'!D84-'Model inputs'!D80-'Model inputs'!D82 -> 209 | E7: ='Model inputs'!E87-'Model inputs'!E84-'Model inputs'!E80-'Model inputs'!E82 -> 571 | F7: ='Model inputs'!F87-'Model inputs'!F84-'Model inputs'!F80-'Model inputs'!F82 -> 939 | G7: ='Model inputs'!G87-'Model inputs'!G84-'Model inputs'!G80-'Model inputs'!G82 -> 1491 | H7: ='Model inputs'!H87-'Model inputs'!H84-'Model inputs'!H80-'Model inputs'!H82 -> 2043 | I7: ='Model inputs'!I87-'Model inputs'!I84-'Model inputs'!I80-'Model inputs'!I82 -> -1037 | ... N7: ='Model inputs'!N87-'Model inputs'!N84-'Model inputs'!N80-'Model inputs'!N82 -> 6875
A8: Cash flow before hire · Downside | B8: ='Model inputs'!B88-'Model inputs'!B85-'Model inputs'!B81-'Model inputs'!B83 -> #VALUE! | C8: ='Model inputs'!C88-'Model inputs'!C85-'Model inputs'!C81-'Model inputs'!C83 -> -154.5 | D8: ='Model inputs'!D88-'Model inputs'!D85-'Model inputs'!D81-'Model inputs'!D83 -> -159 | E8: ='Model inputs'!E88-'Model inputs'!E85-'Model inputs'!E81-'Model inputs'!E83 -> 19 | F8: ='Model inputs'!F88-'Model inputs'!F85-'Model inputs'!F81-'Model inputs'!F83 -> 19 | G8: ='Model inputs'!G88-'Model inputs'!G85-'Model inputs'!G81-'Model inputs'!G83 -> 203 | H8: ='Model inputs'!H88-'Model inputs'!H85-'Model inputs'!H81-'Model inputs'!H83 -> 203 | I8: ='Model inputs'!I88-'Model inputs'!I85-'Model inputs'!I81-'Model inputs'!I83 -> -3613 | ... N8: ='Model inputs'!N88-'Model inputs'!N85-'Model inputs'!N81-'Model inputs'!N83 -> -1957
A9: Cash flow if hired at earliest month | B9: ='Model inputs'!B6-IF(IF(IF(IF(ISERROR('Model inputs'!B59>='Model inputs'!O18),'Model inputs'!B59>='Model inputs'!O18,IF(OR('Model inputs'!B59="",'Model inputs'!O18=""),"",'Model inputs'!B59>='Model inputs'!O18))="",FALSE,IF(ISERROR('Model inputs'!B59>='Model inputs'!O18),'Model inputs'!B59>='Model inputs'!O18,IF(OR('Model inputs'!B59="",'Model inputs'!O18=""),"",'Model inputs'!B59>='Model inputs'!O18))),IF('Model inputs'!O10="","",'Model inputs'!O10),0)="",0,IF(IF(IF(ISERROR('Model inputs'!B59>='Model inputs'!O18),'Model inputs'!B59>='Model inputs'!O18,IF(OR('Model inputs'!B59="",'Model inputs'!O18=""),"",'Model inputs'!B59>='Model inputs'!O18))="",FALSE,IF(ISERROR('Model inputs'!B59>='Model inputs'!O18),'Model inputs'!B59>='Model inputs'!O18,IF(OR('Model inputs'!B59="",'Model inputs'!O18=""),"",'Model inputs'!B59>='Model inputs'!O18))),IF('Model inputs'!O10="","",'Model inputs'!O10),0)) -> #VALUE! | C9: ='Model inputs'!C6-IF(IF(IF(IF(ISERROR('Model inputs'!C59>='Model inputs'!O18),'Model inputs'!C59>='Model inputs'!O18,IF(OR('Model inputs'!C59="",'Model inputs'!O18=""),"",'Model inputs'!C59>='Model inputs'!O18))="",FALSE,IF(ISERROR('Model inputs'!C59>='Model inputs'!O18),'Model inputs'!C59>='Model inputs'!O18,IF(OR('Model inputs'!C59="",'Model inputs'!O18=""),"",'Model inputs'!C59>='Model inputs'!O18))),IF('Model inputs'!O10="","",'Model inputs'!O10),0)="",0,IF(IF(IF(ISERROR('Model inputs'!C59>='Model inputs'!O18),'Model inputs'!C59>='Model inputs'!O18,IF(OR('Model inputs'!C59="",'Model inputs'!O18=""),"",'Model inputs'!C59>='Model inputs'!O18))="",FALSE,IF(ISERROR('Model inputs'!C59>='Model inputs'!O18),'Model inputs'!C59>='Model inputs'!O18,IF(OR('Model inputs'!C59="",'Model inputs'!O18=""),"",'Model inputs'!C59>='Model inputs'!O18))),IF('Model inputs'!O10="","",'Model inputs'!O10),0)) -> -154.5 | D9: ='Model inputs'!D6-IF(IF(IF(IF(ISERROR('Model inputs'!D59>='Model inputs'!O18),'Model inputs'!D59>='Model inputs'!O18,IF(OR('Model inputs'!D59="",'Model inputs'!O18=""),"",'Model inputs'!D59>='Model inputs'!O18))="",FALSE,IF(ISERROR('Model inputs'!D59>='Model inputs'!O18),'Model inputs'!D59>='Model inputs'!O18,IF(OR('Model inputs'!D59="",'Model inputs'!O18=""),"",'Model inputs'!D59>='Model inputs'!O18))),IF('Model inputs'!O10="","",'Model inputs'!O10),0)="",0,IF(IF(IF(ISERROR('Model inputs'!D59>='Model inputs'!O18),'Model inputs'!D59>='Model inputs'!O18,IF(OR('Model inputs'!D59="",'Model inputs'!O18=""),"",'Model inputs'!D59>='Model inputs'!O18))="",FALSE,IF(ISERROR('Model inputs'!D59>='Model inputs'!O18),'Model inputs'!D59>='Model inputs'!O18,IF(OR('Model inputs'!D59="",'Model inputs'!O18=""),"",'Model inputs'!D59>='Model inputs'!O18))),IF('Model inputs'!O10="","",'Model inputs'!O10),0)) -> 25 | E9: ='Model inputs'!E6-IF(IF(IF(IF(ISERROR('Model inputs'!E59>='Model inputs'!O18),'Model inputs'!E59>='Model inputs'!O18,IF(OR('Model inputs'!E59="",'Model inputs'!O18=""),"",'Model inputs'!E59>='Model inputs'!O18))="",FALSE,IF(ISERROR('Model inputs'!E59>='Model inputs'!O18),'Model inputs'!E59>='Model inputs'!O18,IF(OR('Model inputs'!E59="",'Model inputs'!O18=""),"",'Model inputs'!E59>='Model inputs'!O18))),IF('Model inputs'!O10="","",'Model inputs'!O10),0)="",0,IF(IF(IF(ISERROR('Model inputs'!E59>='Model inputs'!O18),'Model inputs'!E59>='Model inputs'!O18,IF(OR('Model inputs'!E59="",'Model inputs'!O18=""),"",'Model inputs'!E59>='Model inputs'!O18))="",FALSE,IF(ISERROR('Model inputs'!E59>='Model inputs'!O18),'Model inputs'!E59>='Model inputs'!O18,IF(OR('Model inputs'!E59="",'Model inputs'!O18=""),"",'Model inputs'!E59>='Model inputs'!O18))),IF('Model inputs'!O10="","",'Model inputs'!O10),0)) -> 203 | F9: ='Model inputs'!F6-IF(IF(IF(IF(ISERROR('Model inputs'!F59>='Model inputs'!O18),'Model inputs'!F59>='Model inputs'!O18,IF(OR('Model inputs'!F59="",'Model inputs'!O18=""),"",'Model inputs'!F59>='Model inputs'!O18))="",FALSE,IF(ISERROR('Model inputs'!F59>='Model inputs'!O18),'Model inputs'!F59>='Model inputs'!O18,IF(OR('Model inputs'!F59="",'Model inputs'!O18=""),"",'Model inputs'!F59>='Model inputs'!O18))),IF('Model inputs'!O10="","",'Model inputs'!O10),0)="",0,IF(IF(IF(ISERROR('Model inputs'!F59>='Model inputs'!O18),'Model inputs'!F59>='Model inputs'!O18,IF(OR('Model inputs'!F59="",'Model inputs'!O18=""),"",'Model inputs'!F59>='Model inputs'!O18))="",FALSE,IF(ISERROR('Model inputs'!F59>='Model inputs'!O18),'Model inputs'!F59>='Model inputs'!O18,IF(OR('Model inputs'!F59="",'Model inputs'!O18=""),"",'Model inputs'!F59>='Model inputs'!O18))),IF('Model inputs'!O10="","",'Model inputs'!O10),0)) -> 387 | G9: ='Model inputs'!G6-IF(IF(IF(IF(ISERROR('Model inputs'!G59>='Model inputs'!O18),'Model inputs'!G59>='Model inputs'!O18,IF(OR('Model inputs'!G59="",'Model inputs'!O18=""),"",'Model inputs'!G59>='Model inputs'!O18))="",FALSE,IF(ISERROR('Model inputs'!G59>='Model inputs'!O18),'Model inputs'!G59>='Model inputs'!O18,IF(OR('Model inputs'!G59="",'Model inputs'!O18=""),"",'Model inputs'!G59>='Model inputs'!O18))),IF('Model inputs'!O10="","",'Model inputs'!O10),0)="",0,IF(IF(IF(ISERROR('Model inputs'!G59>='Model inputs'!O18),'Model inputs'!G59>='Model inputs'!O18,IF(OR('Model inputs'!G59="",'Model inputs'!O18=""),"",'Model inputs'!G59>='Model inputs'!O18))="",FALSE,IF(ISERROR('Model inputs'!G59>='Model inputs'!O18),'Model inputs'!G59>='Model inputs'!O18,IF(OR('Model inputs'!G59="",'Model inputs'!O18=""),"",'Model inputs'!G59>='Model inputs'!O18))),IF('Model inputs'!O10="","",'Model inputs'!O10),0)) -> 571 | H9: ='Model inputs'!H6-IF(IF(IF(IF(ISERROR('Model inputs'!H59>='Model inputs'!O18),'Model inputs'!H59>='Model inputs'!O18,IF(OR('Model inputs'!H59="",'Model inputs'!O18=""),"",'Model inputs'!H59>='Model inputs'!O18))="",FALSE,IF(ISERROR('Model inputs'!H59>='Model inputs'!O18),'Model inputs'!H59>='Model inputs'!O18,IF(OR('Model inputs'!H59="",'Model inputs'!O18=""),"",'Model inputs'!H59>='Model inputs'!O18))),IF('Model inputs'!O10="","",'Model inputs'!O10),0)="",0,IF(IF(IF(ISERROR('Model inputs'!H59>='Model inputs'!O18),'Model inputs'!H59>='Model inputs'!O18,IF(OR('Model inputs'!H59="",'Model inputs'!O18=""),"",'Model inputs'!H59>='Model inputs'!O18))="",FALSE,IF(ISERROR('Model inputs'!H59>='Model inputs'!O18),'Model inputs'!H59>='Model inputs'!O18,IF(OR('Model inputs'!H59="",'Model inputs'!O18=""),"",'Model inputs'!H59>='Model inputs'!O18))),IF('Model inputs'!O10="","",'Model inputs'!O10),0)) -> 755 | I9: ='Model inputs'!I6-IF(IF(IF(IF(ISERROR('Model inputs'!I59>='Model inputs'!O18),'Model inputs'!I59>='Model inputs'!O18,IF(OR('Model inputs'!I59="",'Model inputs'!O18=""),"",'Model inputs'!I59>='Model inputs'!O18))="",FALSE,IF(ISERROR('Model inputs'!I59>='Model inputs'!O18),'Model inputs'!I59>='Model inputs'!O18,IF(OR('Model inputs'!I59="",'Model inputs'!O18=""),"",'Model inputs'!I59>='Model inputs'!O18))),IF('Model inputs'!O10="","",'Model inputs'!O10),0)="",0,IF(IF(IF(ISERROR('Model inputs'!I59>='Model inputs'!O18),'Model inputs'!I59>='Model inputs'!O18,IF(OR('Model inputs'!I59="",'Model inputs'!O18=""),"",'Model inputs'!I59>='Model inputs'!O18))="",FALSE,IF(ISERROR('Model inputs'!I59>='Model inputs'!O18),'Model inputs'!I59>='Model inputs'!O18,IF(OR('Model inputs'!I59="",'Model inputs'!O18=""),"",'Model inputs'!I59>='Model inputs'!O18))),IF('Model inputs'!O10="","",'Model inputs'!O10),0)) -> -2693 | J9: ='Model inputs'!J6-IF(IF(IF(IF(ISERROR('Model inputs'!J59>='Model inputs'!O18),'Model inputs'!J59>='Model inputs'!O18,IF(OR('Model inputs'!J59="",'Model inputs'!O18=""),"",'Model inputs'!J59>='Model inputs'!O18))="",FALSE,IF(ISERROR('Model inputs'!J59>='Model inputs'!O18),'Model inputs'!J59>='Model inputs'!O18,IF(OR('Model inputs'!J59="",'Model inputs'!O18=""),"",'Model inputs'!J59>='Model inputs'!O18))),IF('Model inputs'!O10="","",'Model inputs'!O10),0)="",0,IF(IF(IF(ISERROR('Model inputs'!J59>='Model inputs'!O18),'Model inputs'!J59>='Model inputs'!O18,IF(OR('Model inputs'!J59="",'Model inputs'!O18=""),"",'Model inputs'!J59>='Model inputs'!O18))="",FALSE,IF(ISERROR('Model inputs'!J59>='Model inputs'!O18),'Model inputs'!J59>='Model inputs'!O18,IF(OR('Model inputs'!J59="",'Model inputs'!O18=""),"",'Model inputs'!J59>='Model inputs'!O18))),IF('Model inputs'!O10="","",'Model inputs'!O10),0)) -> -2141 | K9: ='Model inputs'!K6-IF(IF(IF(IF(ISERROR('Model inputs'!K59>='Model inputs'!O18),'Model inputs'!K59>='Model inputs'!O18,IF(OR('Model inputs'!K59="",'Model inputs'!O18=""),"",'Model inputs'!K59>='Model inputs'!O18))="",FALSE,IF(ISERROR('Model inputs'!K59>='Model inputs'!O18),'Model inputs'!K59>='Model inputs'!O18,IF(OR('Model inputs'!K59="",'Model inputs'!O18=""),"",'Model inputs'!K59>='Model inputs'!O18))),IF('Model inputs'!O10="","",'Model inputs'!O10),0)="",0,IF(IF(IF(ISERROR('Model inputs'!K59>='Model inputs'!O18),'Model inputs'!K59>='Model inputs'!O18,IF(OR('Model inputs'!K59="",'Model inputs'!O18=""),"",'Model inputs'!K59>='Model inputs'!O18))="",FALSE,IF(ISERROR('Model inputs'!K59>='Model inputs'!O18),'Model inputs'!K59>='Model inputs'!O18,IF(OR('Model inputs'!K59="",'Model inputs'!O18=""),"",'Model inputs'!K59>='Model inputs'!O18))),IF('Model inputs'!O10="","",'Model inputs'!O10),0)) -> -1405 | L9: ='Model inputs'!L6-IF(IF(IF(IF(ISERROR('Model inputs'!L59>='Model inputs'!O18),'Model inputs'!L59>='Model inputs'!O18,IF(OR('Model inputs'!L59="",'Model inputs'!O18=""),"",'Model inputs'!L59>='Model inputs'!O18))="",FALSE,IF(ISERROR('Model inputs'!L59>='Model inputs'!O18),'Model inputs'!L59>='Model inputs'!O18,IF(OR('Model inputs'!L59="",'Model inputs'!O18=""),"",'Model inputs'!L59>='Model inputs'!O18))),IF('Model inputs'!O10="","",'Model inputs'!O10),0)="",0,IF(IF(IF(ISERROR('Model inputs'!L59>='Model inputs'!O18),'Model inputs'!L59>='Model inputs'!O18,IF(OR('Model inputs'!L59="",'Model inputs'!O18=""),"",'Model inputs'!L59>='Model inputs'!O18))="",FALSE,IF(ISERROR('Model inputs'!L59>='Model inputs'!O18),'Model inputs'!L59>='Model inputs'!O18,IF(OR('Model inputs'!L59="",'Model inputs'!O18=""),"",'Model inputs'!L59>='Model inputs'!O18))),IF('Model inputs'!O10="","",'Model inputs'!O10),0)) -> -6485 | M9: ='Model inputs'!M6-IF(IF(IF(IF(ISERROR('Model inputs'!M59>='Model inputs'!O18),'Model inputs'!M59>='Model inputs'!O18,IF(OR('Model inputs'!M59="",'Model inputs'!O18=""),"",'Model inputs'!M59>='Model inputs'!O18))="",FALSE,IF(ISERROR('Model inputs'!M59>='Model inputs'!O18),'Model inputs'!M59>='Model inputs'!O18,IF(OR('Model inputs'!M59="",'Model inputs'!O18=""),"",'Model inputs'!M59>='Model inputs'!O18))),IF('Model inputs'!O10="","",'Model inputs'!O10),0)="",0,IF(IF(IF(ISERROR('Model inputs'!M59>='Model inputs'!O18),'Model inputs'!M59>='Model inputs'!O18,IF(OR('Model inputs'!M59="",'Model inputs'!O18=""),"",'Model inputs'!M59>='Model inputs'!O18))="",FALSE,IF(ISERROR('Model inputs'!M59>='Model inputs'!O18),'Model inputs'!M59>='Model inputs'!O18,IF(OR('Model inputs'!M59="",'Model inputs'!O18=""),"",'Model inputs'!M59>='Model inputs'!O18))),IF('Model inputs'!O10="","",'Model inputs'!O10),0)) -> -5565 | N9: ='Model inputs'!N6-IF(IF(IF(IF(ISERROR('Model inputs'!N59>='Model inputs'!O18),'Model inputs'!N59>='Model inputs'!O18,IF(OR('Model inputs'!N59="",'Model inputs'!O18=""),"",'Model inputs'!N59>='Model inputs'!O18))="",FALSE,IF(ISERROR('Model inputs'!N59>='Model inputs'!O18),'Model inputs'!N59>='Model inputs'!O18,IF(OR('Model inputs'!N59="",'Model inputs'!O18=""),"",'Model inputs'!N59>='Model inputs'!O18))),IF('Model inputs'!O10="","",'Model inputs'!O10),0)="",0,IF(IF(IF(ISERROR('Model inputs'!N59>='Model inputs'!O18),'Model inputs'!N59>='Model inputs'!O18,IF(OR('Model inputs'!N59="",'Model inputs'!O18=""),"",'Model inputs'!N59>='Model inputs'!O18))="",FALSE,IF(ISERROR('Model inputs'!N59>='Model inputs'!O18),'Model inputs'!N59>='Model inputs'!O18,IF(OR('Model inputs'!N59="",'Model inputs'!O18=""),"",'Model inputs'!N59>='Model inputs'!O18))),IF('Model inputs'!O10="","",'Model inputs'!O10),0)) -> -4645
A10: Contract engineer monthly cost · Main Scenario | O10: ='Pricing and operating assumptio'!B15 -> 6000
A11: Contract engineer monthly cost · Upside | O11: ='Pricing and operating assumptio'!B15 -> 6000
A12: Contract engineer monthly cost · Downside | O12: ='Pricing and operating assumptio'!B15 -> 6000
A13: Cost per successful fix · Monthly operating and hiring forecast | O13: ='Pricing and operating assumptio'!B9 -> 1.5
